Workbook

Sheet Lookup
A1: project_name | B1: requirement_code | C1: activity_type
A2: Bengkel Net | B2: DC-DS-009/BRD/04/ITE-ATPI/VII/2026-27c2fadd-b592-41bb-bde3-7b7f1a8c0254 | C2: Development
A3: Bidding App SKK Migas | B3: DC-DS-009/BRD/04/ITE-ATPI/VII/2026-31fd9168-ac2e-48f8-bdc4-858bc2d41d71 | C3: Bug Fixing
A4: Cybersecurity - Blokir Domain | B4: DC-DS-009/BRD/04/ITE-ATPI/VII/2026-5ed7d982-37a7-48eb-b625-06c522079cd6 | C4: Testing & QA
A5: Cybersecurity - Patching Aplikasi | B5: DC-DS-009/BRD/04/ITE-ATPI/VII/2026-6f3060bc-c5b3-4114-9959-6b7a66d8447e | C5: Analysis & Requirement
A6: Cybersecurity - People Awarness | B6: DC-MI-009/BRD/04/ITE-ATPI/VII/2026-2eff2016-45c0-43f0-af1f-0bda1b152821 | C6: Technical Documentation
A7: Cybersecurity - Rotasi Password | B7: DC-MI-009/BRD/04/ITE-ATPI/VII/2026-af271844-4ae8-484e-ac57-a02bd00356a4 | C7: Meeting & Discussion
A8: Cybersecurity - Scanning Seluruh Perangkat | B8: DC-MI-009/BRD/04/ITE-ATPI/VII/2026-d6d63e08-04a7-4459-baf6-1d1d5a4bfcea | C8: Code Review
A9: DOTS - Uang Muka Kerja | B9: DC-MI-009/BRD/04/ITE-ATPI/VII/2026-fcce5370-068a-4dd1-9d7b-35c5a980ad9c | C9: Deployment & Infra
A10: DOTS SAP Integration | B10: DC-OUT-009/BRD/04/ITE-ATPI/VII/2026-2be1b015-7fa9-448d-95e8-ee0984d5202e | C10: Maintenance & Support
A11: Enhance tDMS - Policy Workflow | B11: DC-OUT-009/BRD/04/ITE-ATPI/VII/2026-3516f43b-1313-4761-ae81-ab2bfef6eae4 | C11: Knowledge Sharing
A12: Enhancement Extend PPW Polis Korporat | B12: DC-OUT-009/BRD/04/ITE-ATPI/VII/2026-7a1074ad-58b5-4502-99f5-919bd3b4c67d | C12: Enhancement
... A16: Evaluasi Master Data | B16: DC-RET-009/BRD/04/ITE-ATPI/VII/2026-e6f979d5-8e61-4b7b-96b3-6f5148e831cf | C16: UAT & Verification
A17: Item #545 | B17: DC-RET-009/BRD/04/ITE-ATPI/VII/2026-ec63667c-e266-48e7-a248-c6fff49cc5b8
A18: Kesiagaan Siber Pada Event Idul Fitri | B18: FR-001BRD04ITEATPIVI2026-BRYH
A19: Memo Formulir - In House Training (t-DMS) | B19: FR-001BRD04ITEATPIVI2026-EQ3S
A20: Migrasi Datawarehouse ke Cloud | B20: FR-001BRD04ITEATPIVI2026-FBKU
A21: New System - Application Request Management System (ARMS) | B21: FR-001BRD04ITEATPIVI2026-GMLW
A22: Otomatisasi Proses Extract Data BAF R4 ke TICS | B22: FR-001BRD04ITEATPIVI2026-PQ1D
A23: PERURI - Tugu SecureSign | B23: FR-001BRD04ITEATPIVI2026-QDTH
A24: Pemindahan API dari CARE ke TICS - BAF R2 | B24: FR-001BRD04ITEATPIVI2026-UG5A
A25: Pemindahan API dari CARE ke TICS - Tfriends | B25: FR-001BRD04ITEATPIVI2026-ZTSG
A26: Penambahan Report Warranty Date Policy Corporat | B26: FR-009/BRD/04/ITE-ATPI/VII/2026-09d59522-11e2-4bfb-b617-03cca8e3891c
A27: Penambahan Status Flagging Product Pada Object Batch TICS Corporate Policy | B27: FR-009/BRD/04/ITE-ATPI/VII/2026-4b1ef905-21ba-46a8-81d1-b955a601cf3f
A28: Pengadaan Google Cloud | B28: FR-009/BRD/04/ITE-ATPI/VII/2026-703785a9-9e33-449e-b9d4-4a6935ab8582
... A33: SAP - Coding Blok | B33: REQ-0009
A34: SAP - Corp Card
A35: SAP - FPSL
A36: SAP - ZFIR026
A37: SAP -Security
A38: SKK MIGAS
A39: SOA Treaty
A40: Sharepoint - tDMS
A41: TCES - Polis
A42: TDMS - Sistem Tata Kelola
A43: TEST
A44: TICS - Claim
A45: TICS - Pre Enforce
... A57: Validasi TICS - Policy Automation

Sheet RealTime_Dashboard
A1: REAL-TIME TASK ANALYSIS DASHBOARD
A3: Person | B3: Total Tasks | C3: DONE | D3: IN_PROGRESS | E3: TODO/Other | F3: Chart Names
A4: Syafix (Business Analyst) | B4: =COUNTIFS(Master_Data!$A:$A, $A4, Master_Data!$C:$C, "<>") -> 113 | C4: =COUNTIFS(Master_Data!$A:$A, $A4, Master_Data!$D:$D, "DONE") -> 105 | D4: =COUNTIFS(Master_Data!$A:$A, $A4, Master_Data!$D:$D, "IN_PROGRESS") -> 5 | E4: =$B4-$C4-$D4 -> 3 | F4: Syafix
A5: Haviz (Developer) | B5: =COUNTIFS(Master_Data!$A:$A, $A5, Master_Data!$C:$C, "<>") -> 77 | C5: =COUNTIFS(Master_Data!$A:$A, $A5, Master_Data!$D:$D, "DONE") -> 76 | D5: =COUNTIFS(Master_Data!$A:$A, $A5, Master_Data!$D:$D, "IN_PROGRESS") -> 1 | E5: =$B5-$C5-$D5 -> 0 | F5: Haviz
A6: Danang (Quality Assurance) | B6: =COUNTIFS(Master_Data!$A:$A, $A6, Master_Data!$C:$C, "<>") -> 47 | C6: =COUNTIFS(Master_Data!$A:$A, $A6, Master_Data!$D:$D, "DONE") -> 47 | D6: =COUNTIFS(Master_Data!$A:$A, $A6, Master_Data!$D:$D, "IN_PROGRESS") -> 0 | E6: =$B6-$C6-$D6 -> 0 | F6: Danang
A7: Athallah (Technical Writer) | B7: =COUNTIFS(Master_Data!$A:$A, $A7, Master_Data!$C:$C, "<>") -> 73 | C7: =COUNTIFS(Master_Data!$A:$A, $A7, Master_Data!$D:$D, "DONE") -> 71 | D7: =COUNTIFS(Master_Data!$A:$A, $A7, Master_Data!$D:$D, "IN_PROGRESS") -> 2 | E7: =$B7-$C7-$D7 -> 0 | F7: Atha
A8: Iqbal (Developer) | B8: =COUNTIFS(Master_Data!$A:$A, $A8, Master_Data!$C:$C, "<>") -> 71 | C8: =COUNTIFS(Master_Data!$A:$A, $A8, Master_Data!$D:$D, "DONE") -> 71 | D8: =COUNTIFS(Master_Data!$A:$A, $A8, Master_Data!$D:$D, "IN_PROGRESS") -> 0 | E8: =$B8-$C8-$D8 -> 0 | F8: Iqbal
A9: Glenn (Developer) | B9: =COUNTIFS(Master_Data!$A:$A, $A9, Master_Data!$C:$C, "<>") -> 58 | C9: =COUNTIFS(Master_Data!$A:$A, $A9, Master_Data!$D:$D, "DONE") -> 57 | D9: =COUNTIFS(Master_Data!$A:$A, $A9, Master_Data!$D:$D, "IN_PROGRESS") -> 1 | E9: =$B9-$C9-$D9 -> 0 | F9: Glenn
A10: Heni (Developer) | B10: =COUNTIFS(Master_Data!$A:$A, $A10, Master_Data!$C:$C, "<>") -> 59 | C10: =COUNTIFS(Master_Data!$A:$A, $A10, Master_Data!$D:$D, "DONE") -> 59 | D10: =COUNTIFS(Master_Data!$A:$A, $A10, Master_Data!$D:$D, "IN_PROGRESS") -> 0 | E10: =$B10-$C10-$D10 -> 0 | F10: Heni
A11: Syifa (Quality Assurance) | B11: =COUNTIF(Syifa!$D$2:$D$198, "<>") -> 14 | C11: =COUNTIF(Syifa!$E:$E, "DONE") -> 14 | D11: =COUNTIF(Syifa!$E:$E, "IN_PROGRESS") -> 0 | E11: =B11-C11-D11 -> 0 | F11: Syifa
L46: ;;

Sheet Master_Data
A1: Person | B1: Project | C1: Task Title | D1: Status | E1: Start Date | F1: Duration | G1: Due Date | H1: Gantt Label
A2: =IF(INDEX(Syafix!$D:$D, 2)="", NA(), "Syafix (Business Analyst)") -> Syafix (Business Analyst) | B2: =IF(INDEX(Syafix!$D:$D, 2)="", NA(), INDEX(Syafix!$B:$B, 2)) -> Pengembangan Mass Product Retail | C2: =IF(INDEX(Syafix!$D:$D, 2)="", NA(), INDEX(Syafix!$D:$D, 2)) -> Checking & Testing Product, Scheming & premium class TICS vs Mass Product | D2: =IF(INDEX(Syafix!$D:$D, 2)="", NA(), INDEX(Syafix!$E:$E, 2)) -> DONE | E2: =IF(INDEX(Syafix!$D:$D, 2)="", NA(), INDEX(Syafix!$K:$K, 2)) -> 46238 | F2: =IF(OR(E2="", ISNA(E2), ISNA(G2)), 0, MAX(1, G2-E2)) -> 2 | G2: =IF(INDEX(Syafix!$D:$D, 2)="", NA(), INDEX(Syafix!$L:$L, 2)) -> 46240 | H2: =IF(ISNA(C2), NA(), A2 & " - " & B2 & " - " & C2) -> Syafix (Business Analyst) - Pengembangan Mass Product Retail - Checking & Testing Product, Scheming & premium class TICS vs Mass Product
A3: =IF(INDEX(Syafix!$D:$D, 3)="", NA(), "Syafix (Business Analyst)") -> Syafix (Business Analyst) | B3: =IF(INDEX(Syafix!$D:$D, 3)="", NA(), INDEX(Syafix!$B:$B, 3)) -> Integrasi TCES TICS | C3: =IF(INDEX(Syafix!$D:$D, 3)="", NA(), INDEX(Syafix!$D:$D, 3)) -> perancangan solusi integrasi TCES - TCIS | D3: =IF(INDEX(Syafix!$D:$D, 3)="", NA(), INDEX(Syafix!$E:$E, 3)) -> DONE | E3: =IF(INDEX(Syafix!$D:$D, 3)="", NA(), INDEX(Syafix!$K:$K, 3)) -> 46239 | F3: =IF(OR(E3="", ISNA(E3), ISNA(G3)), 0, MAX(1, G3-E3)) -> 1 | G3: =IF(INDEX(Syafix!$D:$D, 3)="", NA(), INDEX(Syafix!$L:$L, 3)) -> 46239 | H3: =IF(ISNA(C3), NA(), A3 & " - " & B3 & " - " & C3) -> Syafix (Business Analyst) - Integrasi TCES TICS - perancangan solusi integrasi TCES - TCIS
A4: =IF(INDEX(Syafix!$D:$D, 4)="", NA(), "Syafix (Business Analyst)") -> Syafix (Business Analyst) | B4: =IF(INDEX(Syafix!$D:$D, 4)="", NA(), INDEX(Syafix!$B:$B, 4)) -> Integrasi TCES TICS | C4: =IF(INDEX(Syafix!$D:$D, 4)="", NA(), INDEX(Syafix!$D:$D, 4)) -> Mendefinisikan Tugas API Endpoint (BA), Membuat Diagram Flow API Integration (BA) | D4: =IF(INDEX(Syafix!$D:$D, 4)="", NA(), INDEX(Syafix!$E:$E, 4)) -> DONE | E4: =IF(INDEX(Syafix!$D:$D, 4)="", NA(), INDEX(Syafix!$K:$K, 4)) -> 46240 | F4: =IF(OR(E4="", ISNA(E4), ISNA(G4)), 0, MAX(1, G4-E4)) -> 1 | G4: =IF(INDEX(Syafix!$D:$D, 4)="", NA(), INDEX(Syafix!$L:$L, 4)) -> 46240 | H4: =IF(ISNA(C4), NA(), A4 & " - " & B4 & " - " & C4) -> Syafix (Business Analyst) - Integrasi TCES TICS - Mendefinisikan Tugas API Endpoint (BA), Membuat Diagram Flow API Integration (BA)
A5: =IF(INDEX(Syafix!$D:$D, 5)="", NA(), "Syafix (Business Analyst)") -> Syafix (Business Analyst) | B5: =IF(INDEX(Syafix!$D:$D, 5)="", NA(), INDEX(Syafix!$B:$B, 5)) -> Pengembangan Mass Product Retail | C5: =IF(INDEX(Syafix!$D:$D, 5)="", NA(), INDEX(Syafix!$D:$D, 5)) -> Pengujian Penggunaan Product, Scheming, Premium Class di Aplikasi Mass Product | D5: =IF(INDEX(Syafix!$D:$D, 5)="", NA(), INDEX(Syafix!$E:$E, 5)) -> DONE | E5: =IF(INDEX(Syafix!$D:$D, 5)="", NA(), INDEX(Syafix!$K:$K, 5)) -> 46240 | F5: =IF(OR(E5="", ISNA(E5), ISNA(G5)), 0, MAX(1, G5-E5)) -> 6 | G5: =IF(INDEX(Syafix!$D:$D, 5)="", NA(), INDEX(Syafix!$L:$L, 5)) -> 46246 | H5: =IF(ISNA(C5), NA(), A5 & " - " & B5 & " - " & C5) -> Syafix (Business Analyst) - Pengembangan Mass Product Retail - Pengujian Penggunaan Product, Scheming, Premium Class di Aplikasi Mass Product
A6: =IF(INDEX(Syafix!$D:$D, 6)="", NA(), "Syafix (Business Analyst)") -> Syafix (Business Analyst) | B6: =IF(INDEX(Syafix!$D:$D, 6)="", NA(), INDEX(Syafix!$B:$B, 6)) -> Integrasi TCES TICS | C6: =IF(INDEX(Syafix!$D:$D, 6)="", NA(), INDEX(Syafix!$D:$D, 6)) -> Membuat Diagram HLD dan LLD API Integration | D6: =IF(INDEX(Syafix!$D:$D, 6)="", NA(), INDEX(Syafix!$E:$E, 6)) -> DONE | E6: =IF(INDEX(Syafix!$D:$D, 6)="", NA(), INDEX(Syafix!$K:$K, 6)) -> 46241 | F6: =IF(OR(E6="", ISNA(E6), ISNA(G6)), 0, MAX(1, G6-E6)) -> 5 | G6: =IF(INDEX(Syafix!$D:$D, 6)="", NA(), INDEX(Syafix!$L:$L, 6)) -> 46246 | H6: =IF(ISNA(C6), NA(), A6 & " - " & B6 & " - " & C6) -> Syafix (Business Analyst) - Integrasi TCES TICS - Membuat Diagram HLD dan LLD API Integration
A7: =IF(INDEX(Syafix!$D:$D, 7)="", NA(), "Syafix (Business Analyst)") -> Syafix (Business Analyst) | B7: =IF(INDEX(Syafix!$D:$D, 7)="", NA(), INDEX(Syafix!$B:$B, 7)) -> Integrasi TCES TICS | C7: =IF(INDEX(Syafix!$D:$D, 7)="", NA(), INDEX(Syafix!$D:$D, 7)) -> Membuat QA Tracker untuk kebutuhan pengujian testing API integration | D7: =IF(INDEX(Syafix!$D:$D, 7)="", NA(), INDEX(Syafix!$E:$E, 7)) -> DONE | E7: =IF(INDEX(Syafix!$D:$D, 7)="", NA(), INDEX(Syafix!$K:$K, 7)) -> 46241 | F7: =IF(OR(E7="", ISNA(E7), ISNA(G7)), 0, MAX(1, G7-E7)) -> 5 | G7: =IF(INDEX(Syafix!$D:$D, 7)="", NA(), INDEX(Syafix!$L:$L, 7)) -> 46246 | H7: =IF(ISNA(C7), NA(), A7 & " - " & B7 & " - " & C7) -> Syafix (Business Analyst) - Integrasi TCES TICS - Membuat QA Tracker untuk kebutuhan pengujian testing API integration
A8: =IF(INDEX(Syafix!$D:$D, 8)="", NA(), "Syafix (Business Analyst)") -> Syafix (Business Analyst) | B8: =IF(INDEX(Syafix!$D:$D, 8)="", NA(), INDEX(Syafix!$B:$B, 8)) -> Integrasi TCES TICS | C8: =IF(INDEX(Syafix!$D:$D, 8)="", NA(), INDEX(Syafix!$D:$D, 8)) -> Meeting Pembahasan Alur Proses API Integration, Pembahasan Teknis, Informasi Pengujian Aplikasi | D8: =IF(INDEX(Syafix!$D:$D, 8)="", NA(), INDEX(Syafix!$E:$E, 8)) -> DONE | E8: =IF(INDEX(Syafix!$D:$D, 8)="", NA(), INDEX(Syafix!$K:$K, 8)) -> 46244 | F8: =IF(OR(E8="", ISNA(E8), ISNA(G8)), 0, MAX(1, G8-E8)) -> 1 | G8: =IF(INDEX(Syafix!$D:$D, 8)="", NA(), INDEX(Syafix!$L:$L, 8)) -> 46244 | H8: =IF(ISNA(C8), NA(), A8 & " - " & B8 & " - " & C8) -> Syafix (Business Analyst) - Integrasi TCES TICS - Meeting Pembahasan Alur Proses API Integration, Pembahasan Teknis, Informasi Pengujian Aplikasi
A9: =IF(INDEX(Syafix!$D:$D, 9)="", NA(), "Syafix (Business Analyst)") -> Syafix (Business Analyst) | B9: =IF(INDEX(Syafix!$D:$D, 9)="", NA(), INDEX(Syafix!$B:$B, 9)) -> Integrasi TCES TICS | C9: =IF(INDEX(Syafix!$D:$D, 9)="", NA(), INDEX(Syafix!$D:$D, 9)) -> Pembuatan Dokumen TSD - Membuat Diagram Arsitektur Flow API Integration (BA) | D9: =IF(INDEX(Syafix!$D:$D, 9)="", NA(), INDEX(Syafix!$E:$E, 9)) -> DONE | E9: =IF(INDEX(Syafix!$D:$D, 9)="", NA(), INDEX(Syafix!$K:$K, 9)) -> 46244 | F9: =IF(OR(E9="", ISNA(E9), ISNA(G9)), 0, MAX(1, G9-E9)) -> 4 | G9: =IF(INDEX(Syafix!$D:$D, 9)="", NA(), INDEX(Syafix!$L:$L, 9)) -> 46248 | H9: =IF(ISNA(C9), NA(), A9 & " - " & B9 & " - " & C9) -> Syafix (Business Analyst) - Integrasi TCES TICS - Pembuatan Dokumen TSD - Membuat Diagram Arsitektur Flow API Integration (BA)
A10: =IF(INDEX(Syafix!$D:$D, 10)="", NA(), "Syafix (Business Analyst)") -> Syafix (Business Analyst) | B10: =IF(INDEX(Syafix!$D:$D, 10)="", NA(), INDEX(Syafix!$B:$B, 10)) -> Integrasi TCES TICS | C10: =IF(INDEX(Syafix!$D:$D, 10)="", NA(), INDEX(Syafix!$D:$D, 10)) -> Pembuatan Template Dokumen FSD | D10: =IF(INDEX(Syafix!$D:$D, 10)="", NA(), INDEX(Syafix!$E:$E, 10)) -> DONE | E10: =IF(INDEX(Syafix!$D:$D, 10)="", NA(), INDEX(Syafix!$K:$K, 10)) -> 46244 | F10: =IF(OR(E10="", ISNA(E10), ISNA(G10)), 0, MAX(1, G10-E10)) -> 4 | G10: =IF(INDEX(Syafix!$D:$D, 10)="", NA(), INDEX(Syafix!$L:$L, 10)) -> 46248 | H10: =IF(ISNA(C10), NA(), A10 & " - " & B10 & " - " & C10) -> Syafix (Business Analyst) - Integrasi TCES TICS - Pembuatan Template Dokumen FSD
A11: =IF(INDEX(Syafix!$D:$D, 11)="", NA(), "Syafix (Business Analyst)") -> Syafix (Business Analyst) | B11: =IF(INDEX(Syafix!$D:$D, 11)="", NA(), INDEX(Syafix!$B:$B, 11)) -> Integrasi TCES TICS | C11: =IF(INDEX(Syafix!$D:$D, 11)="", NA(), INDEX(Syafix!$D:$D, 11)) -> Pembuatan Template Dokumen TSD | D11: =IF(INDEX(Syafix!$D:$D, 11)="", NA(), INDEX(Syafix!$E:$E, 11)) -> DONE | E11: =IF(INDEX(Syafix!$D:$D, 11)="", NA(), INDEX(Syafix!$K:$K, 11)) -> 46244 | F11: =IF(OR(E11="", ISNA(E11), ISNA(G11)), 0, MAX(1, G11-E11)) -> 4 | G11: =IF(INDEX(Syafix!$D:$D, 11)="", NA(), INDEX(Syafix!$L:$L, 11)) -> 46248 | H11: =IF(ISNA(C11), NA(), A11 & " - " & B11 & " - " & C11) -> Syafix (Business Analyst) - Integrasi TCES TICS - Pembuatan Template Dokumen TSD
A12: =IF(INDEX(Syafix!$D:$D, 12)="", NA(), "Syafix (Business Analyst)") -> Syafix (Business Analyst) | B12: =IF(INDEX(Syafix!$D:$D, 12)="", NA(), INDEX(Syafix!$B:$B, 12)) -> Integrasi TCES TICS | C12: =IF(INDEX(Syafix!$D:$D, 12)="", NA(), INDEX(Syafix!$D:$D, 12)) -> Training TCES dan flow sistem aplikasi | D12: =IF(INDEX(Syafix!$D:$D, 12)="", NA(), INDEX(Syafix!$E:$E, 12)) -> DONE | E12: =IF(INDEX(Syafix!$D:$D, 12)="", NA(), INDEX(Syafix!$K:$K, 12)) -> 46245 | F12: =IF(OR(E12="", ISNA(E12), ISNA(G12)), 0, MAX(1, G12-E12)) -> 1 | G12: =IF(INDEX(Syafix!$D:$D, 12)="", NA(), INDEX(Syafix!$L:$L, 12)) -> 46245 | H12: =IF(ISNA(C12), NA(), A12 & " - " & B12 & " - " & C12) -> Syafix (Business Analyst) - Integrasi TCES TICS - Training TCES dan flow sistem aplikasi
A13: =IF(INDEX(Syafix!$D:$D, 13)="", NA(), "Syafix (Business Analyst)") -> Syafix (Business Analyst) | B13: =IF(INDEX(Syafix!$D:$D, 13)="", NA(), INDEX(Syafix!$B:$B, 13)) -> Integrasi TCES TICS | C13: =IF(INDEX(Syafix!$D:$D, 13)="", NA(), INDEX(Syafix!$D:$D, 13)) -> Akses ke database TICS | D13: =IF(INDEX(Syafix!$D:$D, 13)="", NA(), INDEX(Syafix!$E:$E, 13)) -> DONE | E13: =IF(INDEX(Syafix!$D:$D, 13)="", NA(), INDEX(Syafix!$K:$K, 13)) -> 46246 | F13: =IF(OR(E13="", ISNA(E13), ISNA(G13)), 0, MAX(1, G13-E13)) -> 2 | G13: =IF(INDEX(Syafix!$D:$D, 13)="", NA(), INDEX(Syafix!$L:$L, 13)) -> 46248 | H13: =IF(ISNA(C13), NA(), A13 & " - " & B13 & " - " & C13) -> Syafix (Business Analyst) - Integrasi TCES TICS - Akses ke database TICS
A14: =IF(INDEX(Syafix!$D:$D, 14)="", NA(), "Syafix (Business Analyst)") -> Syafix (Business Analyst) | B14: =IF(INDEX(Syafix!$D:$D, 14)="", NA(), INDEX(Syafix!$B:$B, 14)) -> Pengembangan Mass Product Retail | C14: =IF(INDEX(Syafix!$D:$D, 14)="", NA(), INDEX(Syafix!$D:$D, 14)) -> Pencarian bugs atau kendala dari pembuatan polis asuransi hingga claim asuransi | D14: =IF(INDEX(Syafix!$D:$D, 14)="", NA(), INDEX(Syafix!$E:$E, 14)) -> DONE | E14: =IF(INDEX(Syafix!$D:$D, 14)="", NA(), INDEX(Syafix!$K:$K, 14)) -> 46247 | F14: =IF(OR(E14="", ISNA(E14), ISNA(G14)), 0, MAX(1, G14-E14)) -> 5 | G14: =IF(INDEX(Syafix!$D:$D, 14)="", NA(), INDEX(Syafix!$L:$L, 14)) -> 46252 | H14: =IF(ISNA(C14), NA(), A14 & " - " & B14 & " - " & C14) -> Syafix (Business Analyst) - Pengembangan Mass Product Retail - Pencarian bugs atau kendala dari pembuatan polis asuransi hingga claim asuransi
A15: =IF(INDEX(Syafix!$D:$D, 15)="", NA(), "Syafix (Business Analyst)") -> Syafix (Business Analyst) | B15: =IF(INDEX(Syafix!$D:$D, 15)="", NA(), INDEX(Syafix!$B:$B, 15)) -> Integrasi TCES TICS | C15: =IF(INDEX(Syafix!$D:$D, 15)="", NA(), INDEX(Syafix!$D:$D, 15)) -> Pembuatan Dokumen FSD - Membuat diagram arsitektur API Integration | D15: =IF(INDEX(Syafix!$D:$D, 15)="", NA(), INDEX(Syafix!$E:$E, 15)) -> DONE | E15: =IF(INDEX(Syafix!$D:$D, 15)="", NA(), INDEX(Syafix!$K:$K, 15)) -> 46248 | F15: =IF(OR(E15="", ISNA(E15), ISNA(G15)), 0, MAX(1, G15-E15)) -> 1 | G15: =IF(INDEX(Syafix!$D:$D, 15)="", NA(), INDEX(Syafix!$L:$L, 15)) -> 46248 | H15: =IF(ISNA(C15), NA(), A15 & " - " & B15 & " - " & C15) -> Syafix (Business Analyst) - Integrasi TCES TICS - Pembuatan Dokumen FSD - Membuat diagram arsitektur API Integration
A16: =IF(INDEX(Syafix!$D:$D, 16)="", NA(), "Syafix (Business Analyst)") -> Syafix (Business Analyst) | B16: =IF(INDEX(Syafix!$D:$D, 16)="", NA(), INDEX(Syafix!$B:$B, 16)) -> Integrasi TCES TICS | C16: =IF(INDEX(Syafix!$D:$D, 16)="", NA(), INDEX(Syafix!$D:$D, 16)) -> Pembuatan Dokumen FSD - Penambahan Penjelasan User Flow Diagram | D16: =IF(INDEX(Syafix!$D:$D, 16)="", NA(), INDEX(Syafix!$E:$E, 16)) -> DONE | E16: =IF(INDEX(Syafix!$D:$D, 16)="", NA(), INDEX(Syafix!$K:$K, 16)) -> 46248 | F16: =IF(OR(E16="", ISNA(E16), ISNA(G16)), 0, MAX(1, G16-E16)) -> 4 | G16: =IF(INDEX(Syafix!$D:$D, 16)="", NA(), INDEX(Syafix!$L:$L, 16)) -> 46252 | H16: =IF(ISNA(C16), NA(), A16 & " - " & B16 & " - " & C16) -> Syafix (Business Analyst) - Integrasi TCES TICS - Pembuatan Dokumen FSD - Penambahan Penjelasan User Flow Diagram
A17: =IF(INDEX(Syafix!$D:$D, 17)="", NA(), "Syafix (Business Analyst)") -> Syafix (Business Analyst) | B17: =IF(INDEX(Syafix!$D:$D, 17)="", NA(), INDEX(Syafix!$B:$B, 17)) -> Integrasi TCES TICS | C17: =IF(INDEX(Syafix!$D:$D, 17)="", NA(), INDEX(Syafix!$D:$D, 17)) -> Pembuatan Draft BRD | D17: =IF(INDEX(Syafix!$D:$D, 17)="", NA(), INDEX(Syafix!$E:$E, 17)) -> DONE | E17: =IF(INDEX(Syafix!$D:$D, 17)="", NA(), INDEX(Syafix!$K:$K, 17)) -> 46248 | F17: =IF(OR(E17="", ISNA(E17), ISNA(G17)), 0, MAX(1, G17-E17)) -> 4 | G17: =IF(INDEX(Syafix!$D:$D, 17)="", NA(), INDEX(Syafix!$L:$L, 17)) -> 46252 | H17: =IF(ISNA(C17), NA(), A17 & " - " & B17 & " - " & C17) -> Syafix (Business Analyst) - Integrasi TCES TICS - Pembuatan Draft BRD
A18: =IF(INDEX(Syafix!$D:$D, 18)="", NA(), "Syafix (Business Analyst)") -> Syafix (Business Analyst) | B18: =IF(INDEX(Syafix!$D:$D, 18)="", NA(), INDEX(Syafix!$B:$B, 18)) -> Integrasi TCES TICS | C18: =IF(INDEX(Syafix!$D:$D, 18)="", NA(), INDEX(Syafix!$D:$D, 18)) -> Gathering database schema dan pendokumentasian | D18: =IF(INDEX(Syafix!$D:$D, 18)="", NA(), INDEX(Syafix!$E:$E, 18)) -> DONE | E18: =IF(INDEX(Syafix!$D:$D, 18)="", NA(), INDEX(Syafix!$K:$K, 18)) -> 46248 | F18: =IF(OR(E18="", ISNA(E18), ISNA(G18)), 0, MAX(1, G18-E18)) -> 5 | G18: =IF(INDEX(Syafix!$D:$D, 18)="", NA(), INDEX(Syafix!$L:$L, 18)) -> 46253 | H18: =IF(ISNA(C18), NA(), A18 & " - " & B18 & " - " & C18) -> Syafix (Business Analyst) - Integrasi TCES TICS - Gathering database schema dan pendokumentasian
A19: =IF(INDEX(Syafix!$D:$D, 19)="", NA(), "Syafix (Business Analyst)") -> Syafix (Business Analyst) | B19: =IF(INDEX(Syafix!$D:$D, 19)="", NA(), INDEX(Syafix!$B:$B, 19)) -> Integrasi TCES TICS | C19: =IF(INDEX(Syafix!$D:$D, 19)="", NA(), INDEX(Syafix!$D:$D, 19)) -> Diskusi dengan tim IT Infra dan IT App untuk kebutuhan permohonan penggunaan docker pada API Integration | D19: =IF(INDEX(Syafix!$D:$D, 19)="", NA(), INDEX(Syafix!$E:$E, 19)) -> DONE | E19: =IF(INDEX(Syafix!$D:$D, 19)="", NA(), INDEX(Syafix!$K:$K, 19)) -> 46248 | F19: =IF(OR(E19="", ISNA(E19), ISNA(G19)), 0, MAX(1, G19-E19)) -> 5 | G19: =IF(INDEX(Syafix!$D:$D, 19)="", NA(), INDEX(Syafix!$L:$L, 19)) -> 46253 | H19: =IF(ISNA(C19), NA(), A19 & " - " & B19 & " - " & C19) -> Syafix (Business Analyst) - Integrasi TCES TICS - Diskusi dengan tim IT Infra dan IT App untuk kebutuhan permohonan penggunaan docker pada API Integration
A20: =IF(INDEX(Syafix!$D:$D, 20)="", NA(), "Syafix (Business Analyst)") -> Syafix (Business Analyst) | B20: =IF(INDEX(Syafix!$D:$D, 20)="", NA(), INDEX(Syafix!$B:$B, 20)) -> Pengembangan Mass Product Retail | C20: =IF(INDEX(Syafix!$D:$D, 20)="", NA(), INDEX(Syafix!$D:$D, 20)) -> Pengujian pembuatan master product baru, scheme baru, polis baru, declaration baru, dan proses claim baru, dengan nama product terbaru adalah TPACC | D20: =IF(INDEX(Syafix!$D:$D, 20)="", NA(), INDEX(Syafix!$E:$E, 20)) -> DONE | E20: =IF(INDEX(Syafix!$D:$D, 20)="", NA(), INDEX(Syafix!$K:$K, 20)) -> 46252 | F20: =IF(OR(E20="", ISNA(E20), ISNA(G20)), 0, MAX(1, G20-E20)) -> 2 | G20: =IF(INDEX(Syafix!$D:$D, 20)="", NA(), INDEX(Syafix!$L:$L, 20)) -> 46254 | H20: =IF(ISNA(C20), NA(), A20 & " - " & B20 & " - " & C20) -> Syafix (Business Analyst) - Pengembangan Mass Product Retail - Pengujian pembuatan master product baru, scheme baru, polis baru, declaration baru, dan proses claim baru, dengan nama product terbaru adalah TPACC
A21: =IF(INDEX(Syafix!$D:$D, 21)="", NA(), "Syafix (Business Analyst)") -> Syafix (Business Analyst) | B21: =IF(INDEX(Syafix!$D:$D, 21)="", NA(), INDEX(Syafix!$B:$B, 21)) -> Integrasi TCES TICS | C21: =IF(INDEX(Syafix!$D:$D, 21)="", NA(), INDEX(Syafix!$D:$D, 21)) -> Update Draft BRD | D21: =IF(INDEX(Syafix!$D:$D, 21)="", NA(), INDEX(Syafix!$E:$E, 21)) -> DONE | E21: =IF(INDEX(Syafix!$D:$D, 21)="", NA(), INDEX(Syafix!$K:$K, 21)) -> 46252 | F21: =IF(OR(E21="", ISNA(E21), ISNA(G21)), 0, MAX(1, G21-E21)) -> 24 | G21: =IF(INDEX(Syafix!$D:$D, 21)="", NA(), INDEX(Syafix!$L:$L, 21)) -> 46276 | H21: =IF(ISNA(C21), NA(), A21 & " - " & B21 & " - " & C21) -> Syafix (Business Analyst) - Integrasi TCES TICS - Update Draft BRD
A22: =IF(INDEX(Syafix!$D:$D, 22)="", NA(), "Syafix (Business Analyst)") -> Syafix (Business Analyst) | B22: =IF(INDEX(Syafix!$D:$D, 22)="", NA(), INDEX(Syafix!$B:$B, 22)) -> Integrasi TCES TICS | C22: =IF(INDEX(Syafix!$D:$D, 22)="", NA(), INDEX(Syafix!$D:$D, 22)) -> Pembuatan data payload test API Integration sebanyak 1000 buah untuk pengujian performance test | D22: =IF(INDEX(Syafix!$D:$D, 22)="", NA(), INDEX(Syafix!$E:$E, 22)) -> DONE | E22: =IF(INDEX(Syafix!$D:$D, 22)="", NA(), INDEX(Syafix!$K:$K, 22)) -> 46254 | F22: =IF(OR(E22="", ISNA(E22), ISNA(G22)), 0, MAX(1, G22-E22)) -> 1 | G22: =IF(INDEX(Syafix!$D:$D, 22)="", NA(), INDEX(Syafix!$L:$L, 22)) -> 46254 | H22: =IF(ISNA(C22), NA(), A22 & " - " & B22 & " - " & C22) -> Syafix (Business Analyst) - Integrasi TCES TICS - Pembuatan data payload test API Integration sebanyak 1000 buah untuk pengujian performance test
A23: =IF(INDEX(Syafix!$D:$D, 23)="", NA(), "Syafix (Business Analyst)") -> Syafix (Business Analyst) | B23: =IF(INDEX(Syafix!$D:$D, 23)="", NA(), INDEX(Syafix!$B:$B, 23)) -> Integrasi TCES TICS | C23: =IF(INDEX(Syafix!$D:$D, 23)="", NA(), INDEX(Syafix!$D:$D, 23)) -> Meeting Product Mapping TProperty dengn mas julyan dan mas fergy | D23: =IF(INDEX(Syafix!$D:$D, 23)="", NA(), INDEX(Syafix!$E:$E, 23)) -> DONE | E23: =IF(INDEX(Syafix!$D:$D, 23)="", NA(), INDEX(Syafix!$K:$K, 23)) -> 46254 | F23: =IF(OR(E23="", ISNA(E23), ISNA(G23)), 0, MAX(1, G23-E23)) -> 1 | G23: =IF(INDEX(Syafix!$D:$D, 23)="", NA(), INDEX(Syafix!$L:$L, 23)) -> 46254 | H23: =IF(ISNA(C23), NA(), A23 & " - " & B23 & " - " & C23) -> Syafix (Business Analyst) - Integrasi TCES TICS - Meeting Product Mapping TProperty dengn mas julyan dan mas fergy
A24: =IF(INDEX(Syafix!$D:$D, 24)="", NA(), "Syafix (Business Analyst)") -> Syafix (Business Analyst) | B24: =IF(INDEX(Syafix!$D:$D, 24)="", NA(), INDEX(Syafix!$B:$B, 24)) -> Integrasi TCES TICS | C24: =IF(INDEX(Syafix!$D:$D, 24)="", NA(), INDEX(Syafix!$D:$D, 24)) -> Membantu QA melakukan proses pengujian Stress Test dan Performance Test | D24: =IF(INDEX(Syafix!$D:$D, 24)="", NA(), INDEX(Syafix!$E:$E, 24)) -> DONE | E24: =IF(INDEX(Syafix!$D:$D, 24)="", NA(), INDEX(Syafix!$K:$K, 24)) -> 46254 | F24: =IF(OR(E24="", ISNA(E24), ISNA(G24)), 0, MAX(1, G24-E24)) -> 1 | G24: =IF(INDEX(Syafix!$D:$D, 24)="", NA(), INDEX(Syafix!$L:$L, 24)) -> 46255 | H24: =IF(ISNA(C24), NA(), A24 & " - " & B24 & " - " & C24) -> Syafix (Business Analyst) - Integrasi TCES TICS - Membantu QA melakukan proses pengujian Stress Test dan Performance Test
A25: =IF(INDEX(Syafix!$D:$D, 25)="", NA(), "Syafix (Business Analyst)") -> Syafix (Business Analyst) | B25: =IF(INDEX(Syafix!$D:$D, 25)="", NA(), INDEX(Syafix!$B:$B, 25)) -> Integrasi TCES TICS | C25: =IF(INDEX(Syafix!$D:$D, 25)="", NA(), INDEX(Syafix!$D:$D, 25)) -> Pengecekan hasil QA Testing dengan value yang berada pada sistem TCES untuk memastikan kesesuaian dengan TICS | D25: =IF(INDEX(Syafix!$D:$D, 25)="", NA(), INDEX(Syafix!$E:$E, 25)) -> DONE | E25: =IF(INDEX(Syafix!$D:$D, 25)="", NA(), INDEX(Syafix!$K:$K, 25)) -> 46255 | F25: =IF(OR(E25="", ISNA(E25), ISNA(G25)), 0, MAX(1, G25-E25)) -> 7 | G25: =IF(INDEX(Syafix!$D:$D, 25)="", NA(), INDEX(Syafix!$L:$L, 25)) -> 46262 | H25: =IF(ISNA(C25), NA(), A25 & " - " & B25 & " - " & C25) -> Syafix (Business Analyst) - Integrasi TCES TICS - Pengecekan hasil QA Testing dengan value yang berada pada sistem TCES untuk memastikan kesesuaian dengan TICS
A26: =IF(INDEX(Syafix!$D:$D, 26)="", NA(), "Syafix (Business Analyst)") -> Syafix (Business Analyst) | B26: =IF(INDEX(Syafix!$D:$D, 26)="", NA(), INDEX(Syafix!$B:$B, 26)) -> Integrasi TCES TICS | C26: =IF(INDEX(Syafix!$D:$D, 26)="", NA(), INDEX(Syafix!$D:$D, 26)) -> Pengecekan Ulang Endpoint API Integration sebelum melakukan testing | D26: =IF(INDEX(Syafix!$D:$D, 26)="", NA(), INDEX(Syafix!$E:$E, 26)) -> DONE | E26: =IF(INDEX(Syafix!$D:$D, 26)="", NA(), INDEX(Syafix!$K:$K, 26)) -> 46258 | F26: =IF(OR(E26="", ISNA(E26), ISNA(G26)), 0, MAX(1, G26-E26)) -> 1 | G26: =IF(INDEX(Syafix!$D:$D, 26)="", NA(), INDEX(Syafix!$L:$L, 26)) -> 46258 | H26: =IF(ISNA(C26), NA(), A26 & " - " & B26 & " - " & C26) -> Syafix (Business Analyst) - Integrasi TCES TICS - Pengecekan Ulang Endpoint API Integration sebelum melakukan testing
A27: =IF(INDEX(Syafix!$D:$D, 27)="", NA(), "Syafix (Business Analyst)") -> Syafix (Business Analyst) | B27: =IF(INDEX(Syafix!$D:$D, 27)="", NA(), INDEX(Syafix!$B:$B, 27)) -> Integrasi TCES TICS | C27: =IF(INDEX(Syafix!$D:$D, 27)="", NA(), INDEX(Syafix!$D:$D, 27)) -> Melakukan meeting terkait progress review task yang sudah dikerjakan bersama tim dan stakeholder | D27: =IF(INDEX(Syafix!$D:$D, 27)="", NA(), INDEX(Syafix!$E:$E, 27)) -> DONE | E27: =IF(INDEX(Syafix!$D:$D, 27)="", NA(), INDEX(Syafix!$K:$K, 27)) -> 46258 | F27: =IF(OR(E27="", ISNA(E27), ISNA(G27)), 0, MAX(1, G27-E27)) -> 1 | G27: =IF(INDEX(Syafix!$D:$D, 27)="", NA(), INDEX(Syafix!$L:$L, 27)) -> 46258 | H27: =IF(ISNA(C27), NA(), A27 & " - " & B27 & " - " & C27) -> Syafix (Business Analyst) - Integrasi TCES TICS - Melakukan meeting terkait progress review task yang sudah dikerjakan bersama tim dan stakeholder
A28: =IF(INDEX(Syafix!$D:$D, 28)="", NA(), "Syafix (Business Analyst)") -> Syafix (Business Analyst) | B28: =IF(INDEX(Syafix!$D:$D, 28)="", NA(), INDEX(Syafix!$B:$B, 28)) -> Integrasi TCES TICS | C28: =IF(INDEX(Syafix!$D:$D, 28)="", NA(), INDEX(Syafix!$D:$D, 28)) -> Membuat Data Order TCES untuk kebutuhan pengetesan end-to-end ke TICS | D28: =IF(INDEX(Syafix!$D:$D, 28)="", NA(), INDEX(Syafix!$E:$E, 28)) -> DONE | E28: =IF(INDEX(Syafix!$D:$D, 28)="", NA(), INDEX(Syafix!$K:$K, 28)) -> 46258 | F28: =IF(OR(E28="", ISNA(E28), ISNA(G28)), 0, MAX(1, G28-E28)) -> 2 | G28: =IF(INDEX(Syafix!$D:$D, 28)="", NA(), INDEX(Syafix!$L:$L, 28)) -> 46260 | H28: =IF(ISNA(C28), NA(), A28 & " - " & B28 & " - " & C28) -> Syafix (Business Analyst) - Integrasi TCES TICS - Membuat Data Order TCES untuk kebutuhan pengetesan end-to-end ke TICS
A29: =IF(INDEX(Syafix!$D:$D, 29)="", NA(), "Syafix (Business Analyst)") -> Syafix (Business Analyst) | B29: =IF(INDEX(Syafix!$D:$D, 29)="", NA(), INDEX(Syafix!$B:$B, 29)) -> Integrasi TCES TICS | C29: =IF(INDEX(Syafix!$D:$D, 29)="", NA(), INDEX(Syafix!$D:$D, 29)) -> Membuat data Payload untuk pengujian Travela dan TFire | D29: =IF(INDEX(Syafix!$D:$D, 29)="", NA(), INDEX(Syafix!$E:$E, 29)) -> DONE | E29: =IF(INDEX(Syafix!$D:$D, 29)="", NA(), INDEX(Syafix!$K:$K, 29)) -> 46260 | F29: =IF(OR(E29="", ISNA(E29), ISNA(G29)), 0, MAX(1, G29-E29)) -> 1 | G29: =IF(INDEX(Syafix!$D:$D, 29)="", NA(), INDEX(Syafix!$L:$L, 29)) -> 46261 | H29: =IF(ISNA(C29), NA(), A29 & " - " & B29 & " - " & C29) -> Syafix (Business Analyst) - Integrasi TCES TICS - Membuat data Payload untuk pengujian Travela dan TFire
A30: =IF(INDEX(Syafix!$D:$D, 30)="", NA(), "Syafix (Business Analyst)") -> Syafix (Business Analyst) | B30: =IF(INDEX(Syafix!$D:$D, 30)="", NA(), INDEX(Syafix!$B:$B, 30)) -> Pengembangan Mass Product Retail | C30: =IF(INDEX(Syafix!$D:$D, 30)="", NA(), INDEX(Syafix!$D:$D, 30)) -> Pengetesan master data region untuk pencocokan data polis dengan region BP | D30: =IF(INDEX(Syafix!$D:$D, 30)="", NA(), INDEX(Syafix!$E:$E, 30)) -> TODO | E30: =IF(INDEX(Syafix!$D:$D, 30)="", NA(), INDEX(Syafix!$K:$K, 30)) -> 46260 | F30: =IF(OR(E30="", ISNA(E30), ISNA(G30)), 0, MAX(1, G30-E30)) -> 2 | G30: =IF(INDEX(Syafix!$D:$D, 30)="", NA(), INDEX(Syafix!$L:$L, 30)) -> 46262 | H30: =IF(ISNA(C30), NA(), A30 & " - " & B30 & " - " & C30) -> Syafix (Business Analyst) - Pengembangan Mass Product Retail - Pengetesan master data region untuk pencocokan data polis dengan region BP
A31: =IF(INDEX(Syafix!$D:$D, 31)="", NA(), "Syafix (Business Analyst)") -> Syafix (Business Analyst) | B31: =IF(INDEX(Syafix!$D:$D, 31)="", NA(), INDEX(Syafix!$B:$B, 31)) -> Integrasi TCES TICS | C31: =IF(INDEX(Syafix!$D:$D, 31)="", NA(), INDEX(Syafix!$D:$D, 31)) -> Membuat test case untuk end-to-end TCES untuk produk Tride dan execute testing sampai terbentuk polis number (BA) | D31: =IF(INDEX(Syafix!$D:$D, 31)="", NA(), INDEX(Syafix!$E:$E, 31)) -> DONE | E31: =IF(INDEX(Syafix!$D:$D, 31)="", NA(), INDEX(Syafix!$K:$K, 31)) -> 46261 | F31: =IF(OR(E31="", ISNA(E31), ISNA(G31)), 0, MAX(1, G31-E31)) -> 1 | G31: =IF(INDEX(Syafix!$D:$D, 31)="", NA(), INDEX(Syafix!$L:$L, 31)) -> 46261 | H31: =IF(ISNA(C31), NA(), A31 & " - " & B31 & " - " & C31) -> Syafix (Business Analyst) - Integrasi TCES TICS - Membuat test case untuk end-to-end TCES untuk produk Tride dan execute testing sampai terbentuk polis number (BA)
A32: =IF(INDEX(Syafix!$D:$D, 32)="", NA(), "Syafix (Business Analyst)") -> Syafix (Business Analyst) | B32: =IF(INDEX(Syafix!$D:$D, 32)="", NA(), INDEX(Syafix!$B:$B, 32)) -> Integrasi TCES TICS | C32: =IF(INDEX(Syafix!$D:$D, 32)="", NA(), INDEX(Syafix!$D:$D, 32)) -> Mencari temuan hasil pengecekan input TCES ke TICS via API Integration (T-Ride) | D32: =IF(INDEX(Syafix!$D:$D, 32)="", NA(), INDEX(Syafix!$E:$E, 32)) -> DONE | E32: =IF(INDEX(Syafix!$D:$D, 32)="", NA(), INDEX(Syafix!$K:$K, 32)) -> 46262 | F32: =IF(OR(E32="", ISNA(E32), ISNA(G32)), 0, MAX(1, G32-E32)) -> 1 | G32: =IF(INDEX(Syafix!$D:$D, 32)="", NA(), INDEX(Syafix!$L:$L, 32)) -> 46262 | H32: =IF(ISNA(C32), NA(), A32 & " - " & B32 & " - " & C32) -> Syafix (Business Analyst) - Integrasi TCES TICS - Mencari temuan hasil pengecekan input TCES ke TICS via API Integration (T-Ride)
A33: =IF(INDEX(Syafix!$D:$D, 33)="", NA(), "Syafix (Business Analyst)") -> Syafix (Business Analyst) | B33: =IF(INDEX(Syafix!$D:$D, 33)="", NA(), INDEX(Syafix!$B:$B, 33)) -> Integrasi TCES TICS | C33: =IF(INDEX(Syafix!$D:$D, 33)="", NA(), INDEX(Syafix!$D:$D, 33)) -> Pembuatan Sequence Diagram untuk flow end-to-end API Integration | D33: =IF(INDEX(Syafix!$D:$D, 33)="", NA(), INDEX(Syafix!$E:$E, 33)) -> DONE | E33: =IF(INDEX(Syafix!$D:$D, 33)="", NA(), INDEX(Syafix!$K:$K, 33)) -> 46262 | F33: =IF(OR(E33="", ISNA(E33), ISNA(G33)), 0, MAX(1, G33-E33)) -> 1 | G33: =IF(INDEX(Syafix!$D:$D, 33)="", NA(), INDEX(Syafix!$L:$L, 33)) -> 46262 | H33: =IF(ISNA(C33), NA(), A33 & " - " & B33 & " - " & C33) -> Syafix (Business Analyst) - Integrasi TCES TICS - Pembuatan Sequence Diagram untuk flow end-to-end API Integration
A34: =IF(INDEX(Syafix!$D:$D, 34)="", NA(), "Syafix (Business Analyst)") -> Syafix (Business Analyst) | B34: =IF(INDEX(Syafix!$D:$D, 34)="", NA(), INDEX(Syafix!$B:$B, 34)) -> Integrasi TCES TICS | C34: =IF(INDEX(Syafix!$D:$D, 34)="", NA(), INDEX(Syafix!$D:$D, 34)) -> Pembuatan timesheet elistec | D34: =IF(INDEX(Syafix!$D:$D, 34)="", NA(), INDEX(Syafix!$E:$E, 34)) -> DONE | E34: =IF(INDEX(Syafix!$D:$D, 34)="", NA(), INDEX(Syafix!$K:$K, 34)) -> 46265 | F34: =IF(OR(E34="", ISNA(E34), ISNA(G34)), 0, MAX(1, G34-E34)) -> 1 | G34: =IF(INDEX(Syafix!$D:$D, 34)="", NA(), INDEX(Syafix!$L:$L, 34)) -> 46265 | H34: =IF(ISNA(C34), NA(), A34 & " - " & B34 & " - " & C34) -> Syafix (Business Analyst) - Integrasi TCES TICS - Pembuatan timesheet elistec
A35: =IF(INDEX(Syafix!$D:$D, 35)="", NA(), "Syafix (Business Analyst)") -> Syafix (Business Analyst) | B35: =IF(INDEX(Syafix!$D:$D, 35)="", NA(), INDEX(Syafix!$B:$B, 35)) -> Integrasi TCES TICS | C35: =IF(INDEX(Syafix!$D:$D, 35)="", NA(), INDEX(Syafix!$D:$D, 35)) -> Pembuatan Data Travel dengan QA dan pengujian pada environment DEV | D35: =IF(INDEX(Syafix!$D:$D, 35)="", NA(), INDEX(Syafix!$E:$E, 35)) -> DONE | E35: =IF(INDEX(Syafix!$D:$D, 35)="", NA(), INDEX(Syafix!$K:$K, 35)) -> 46265 | F35: =IF(OR(E35="", ISNA(E35), ISNA(G35)), 0, MAX(1, G35-E35)) -> 1 | G35: =IF(INDEX(Syafix!$D:$D, 35)="", NA(), INDEX(Syafix!$L:$L, 35)) -> 46266 | H35: =IF(ISNA(C35), NA(), A35 & " - " & B35 & " - " & C35) -> Syafix (Business Analyst) - Integrasi TCES TICS - Pembuatan Data Travel dengan QA dan pengujian pada environment DEV
A36: =IF(INDEX(Syafix!$D:$D, 36)="", NA(), "Syafix (Business Analyst)") -> Syafix (Business Analyst) | B36: =IF(INDEX(Syafix!$D:$D, 36)="", NA(), INDEX(Syafix!$B:$B, 36)) -> Integrasi TCES TICS | C36: =IF(INDEX(Syafix!$D:$D, 36)="", NA(), INDEX(Syafix!$D:$D, 36)) -> Pengujian TRide 4 Roda, end-to-end dari TCES hingga SAP | D36: =IF(INDEX(Syafix!$D:$D, 36)="", NA(), INDEX(Syafix!$E:$E, 36)) -> DONE | E36: =IF(INDEX(Syafix!$D:$D, 36)="", NA(), INDEX(Syafix!$K:$K, 36)) -> 46266 | F36: =IF(OR(E36="", ISNA(E36), ISNA(G36)), 0, MAX(1, G36-E36)) -> 1 | G36: =IF(INDEX(Syafix!$D:$D, 36)="", NA(), INDEX(Syafix!$L:$L, 36)) -> 46266 | H36: =IF(ISNA(C36), NA(), A36 & " - " & B36 & " - " & C36) -> Syafix (Business Analyst) - Integrasi TCES TICS - Pengujian TRide 4 Roda, end-to-end dari TCES hingga SAP
A37: =IF(INDEX(Syafix!$D:$D, 37)="", NA(), "Syafix (Business Analyst)") -> Syafix (Business Analyst) | B37: =IF(INDEX(Syafix!$D:$D, 37)="", NA(), INDEX(Syafix!$B:$B, 37)) -> Integrasi TCES TICS | C37: =IF(INDEX(Syafix!$D:$D, 37)="", NA(), INDEX(Syafix!$D:$D, 37)) -> Melakukan Pengujian Perbaikan dari TDrive pada tanggal 1/9/2026 atau pada no row 31 | D37: =IF(INDEX(Syafix!$D:$D, 37)="", NA(), INDEX(Syafix!$E:$E, 37)) -> DONE | E37: =IF(INDEX(Syafix!$D:$D, 37)="", NA(), INDEX(Syafix!$K:$K, 37)) -> 46267 | F37: =IF(OR(E37="", ISNA(E37), ISNA(G37)), 0, MAX(1, G37-E37)) -> 1 | G37: =IF(INDEX(Syafix!$D:$D, 37)="", NA(), INDEX(Syafix!$L:$L, 37)) -> 46267 | H37: =IF(ISNA(C37), NA(), A37 & " - " & B37 & " - " & C37) -> Syafix (Business Analyst) - Integrasi TCES TICS - Melakukan Pengujian Perbaikan dari TDrive pada tanggal 1/9/2026 atau pada no row 31
A38: =IF(INDEX(Syafix!$D:$D, 38)="", NA(), "Syafix (Business Analyst)") -> Syafix (Business Analyst) | B38: =IF(INDEX(Syafix!$D:$D, 38)="", NA(), INDEX(Syafix!$B:$B, 38)) -> Integrasi TCES TICS | C38: =IF(INDEX(Syafix!$D:$D, 38)="", NA(), INDEX(Syafix!$D:$D, 38)) -> Membuat Test Case untuk pengujian end-to-end Travela | D38: =IF(INDEX(Syafix!$D:$D, 38)="", NA(), INDEX(Syafix!$E:$E, 38)) -> DONE | E38: =IF(INDEX(Syafix!$D:$D, 38)="", NA(), INDEX(Syafix!$K:$K, 38)) -> 46267 | F38: =IF(OR(E38="", ISNA(E38), ISNA(G38)), 0, MAX(1, G38-E38)) -> 1 | G38: =IF(INDEX(Syafix!$D:$D, 38)="", NA(), INDEX(Syafix!$L:$L, 38)) -> 46267 | H38: =IF(ISNA(C38), NA(), A38 & " - " & B38 & " - " & C38) -> Syafix (Business Analyst) - Integrasi TCES TICS - Membuat Test Case untuk pengujian end-to-end Travela
A39: =IF(INDEX(Syafix!$D:$D, 39)="", NA(), "Syafix (Business Analyst)") -> Syafix (Business Analyst) | B39: =IF(INDEX(Syafix!$D:$D, 39)="", NA(), INDEX(Syafix!$B:$B, 39)) -> Integrasi TCES TICS | C39: =IF(INDEX(Syafix!$D:$D, 39)="", NA(), INDEX(Syafix!$D:$D, 39)) -> Membuat Matrix Pengujian Data TFire bersama QA dan TW | D39: =IF(INDEX(Syafix!$D:$D, 39)="", NA(), INDEX(Syafix!$E:$E, 39)) -> DONE | E39: =IF(INDEX(Syafix!$D:$D, 39)="", NA(), INDEX(Syafix!$K:$K, 39)) -> 46268 | F39: =IF(OR(E39="", ISNA(E39), ISNA(G39)), 0, MAX(1, G39-E39)) -> 1 | G39: =IF(INDEX(Syafix!$D:$D, 39)="", NA(), INDEX(Syafix!$L:$L, 39)) -> 46268 | H39: =IF(ISNA(C39), NA(), A39 & " - " & B39 & " - " & C39) -> Syafix (Business Analyst) - Integrasi TCES TICS - Membuat Matrix Pengujian Data TFire bersama QA dan TW
A40: =IF(INDEX(Syafix!$D:$D, 40)="", NA(), "Syafix (Business Analyst)") -> Syafix (Business Analyst) | B40: =IF(INDEX(Syafix!$D:$D, 40)="", NA(), INDEX(Syafix!$B:$B, 40)) -> Integrasi TCES TICS | C40: =IF(INDEX(Syafix!$D:$D, 40)="", NA(), INDEX(Syafix!$D:$D, 40)) -> Membuat Summary Pengujian TFire u/ Tanggal 3 Sept | D40: =IF(INDEX(Syafix!$D:$D, 40)="", NA(), INDEX(Syafix!$E:$E, 40)) -> DONE | E40: =IF(INDEX(Syafix!$D:$D, 40)="", NA(), INDEX(Syafix!$K:$K, 40)) -> 46268 | F40: =IF(OR(E40="", ISNA(E40), ISNA(G40)), 0, MAX(1, G40-E40)) -> 1 | G40: =IF(INDEX(Syafix!$D:$D, 40)="", NA(), INDEX(Syafix!$L:$L, 40)) -> 46268 | H40: =IF(ISNA(C40), NA(), A40 & " - " & B40 & " - " & C40) -> Syafix (Business Analyst) - Integrasi TCES TICS - Membuat Summary Pengujian TFire u/ Tanggal 3 Sept
A41: =IF(INDEX(Syafix!$D:$D, 41)="", NA(), "Syafix (Business Analyst)") -> Syafix (Business Analyst) | B41: =IF(INDEX(Syafix!$D:$D, 41)="", NA(), INDEX(Syafix!$B:$B, 41)) -> Integrasi TCES TICS | C41: =IF(INDEX(Syafix!$D:$D, 41)="", NA(), INDEX(Syafix!$D:$D, 41)) -> Membuat data input untuk pengujian yang sudah di Fix untuk Travela dan TFire | D41: =IF(INDEX(Syafix!$D:$D, 41)="", NA(), INDEX(Syafix!$E:$E, 41)) -> DONE | E41: =IF(INDEX(Syafix!$D:$D, 41)="", NA(), INDEX(Syafix!$K:$K, 41)) -> 46268 | F41: =IF(OR(E41="", ISNA(E41), ISNA(G41)), 0, MAX(1, G41-E41)) -> 1 | G41: =IF(INDEX(Syafix!$D:$D, 41)="", NA(), INDEX(Syafix!$L:$L, 41)) -> 46269 | H41: =IF(ISNA(C41), NA(), A41 & " - " & B41 & " - " & C41) -> Syafix (Business Analyst) - Integrasi TCES TICS - Membuat data input untuk pengujian yang sudah di Fix untuk Travela dan TFire
A42: =IF(INDEX(Syafix!$D:$D, 42)="", NA(), "Syafix (Business Analyst)") -> Syafix (Business Analyst) | B42: =IF(INDEX(Syafix!$D:$D, 42)="", NA(), INDEX(Syafix!$B:$B, 42)) -> Integrasi TCES TICS | C42: =IF(INDEX(Syafix!$D:$D, 42)="", NA(), INDEX(Syafix!$D:$D, 42)) -> Pengujian kembali dari data TCES untuk TDrive, TRide, TFire, dan Travela setelah terdapat perbaikan pada aplikasi | D42: =IF(INDEX(Syafix!$D:$D, 42)="", NA(), INDEX(Syafix!$E:$E, 42)) -> DONE | E42: =IF(INDEX(Syafix!$D:$D, 42)="", NA(), INDEX(Syafix!$K:$K, 42)) -> 46269 | F42: =IF(OR(E42="", ISNA(E42), ISNA(G42)), 0, MAX(1, G42-E42)) -> 1 | G42: =IF(INDEX(Syafix!$D:$D, 42)="", NA(), INDEX(Syafix!$L:$L, 42)) -> 46269 | H42: =IF(ISNA(C42), NA(), A42 & " - " & B42 & " - " & C42) -> Syafix (Business Analyst) - Integrasi TCES TICS - Pengujian kembali dari data TCES untuk TDrive, TRide, TFire, dan Travela setelah terdapat perbaikan pada aplikasi
A43: =IF(INDEX(Syafix!$D:$D, 43)="", NA(), "Syafix (Business Analyst)") -> Syafix (Business Analyst) | B43: =IF(INDEX(Syafix!$D:$D, 43)="", NA(), INDEX(Syafix!$B:$B, 43)) -> Integrasi TCES TICS | C43: =IF(INDEX(Syafix!$D:$D, 43)="", NA(), INDEX(Syafix!$D:$D, 43)) -> Meng-update kembali QA Tracker untuk pengujian sebelum dan sesudah fixing | D43: =IF(INDEX(Syafix!$D:$D, 43)="", NA(), INDEX(Syafix!$E:$E, 43)) -> DONE | E43: =IF(INDEX(Syafix!$D:$D, 43)="", NA(), INDEX(Syafix!$K:$K, 43)) -> 46269 | F43: =IF(OR(E43="", ISNA(E43), ISNA(G43)), 0, MAX(1, G43-E43)) -> 1 | G43: =IF(INDEX(Syafix!$D:$D, 43)="", NA(), INDEX(Syafix!$L:$L, 43)) -> 46269 | H43: =IF(ISNA(C43), NA(), A43 & " - " & B43 & " - " & C43) -> Syafix (Business Analyst) - Integrasi TCES TICS - Meng-update kembali QA Tracker untuk pengujian sebelum dan sesudah fixing
A44: =IF(INDEX(Syafix!$D:$D, 44)="", NA(), "Syafix (Business Analyst)") -> Syafix (Business Analyst) | B44: =IF(INDEX(Syafix!$D:$D, 44)="", NA(), INDEX(Syafix!$B:$B, 44)) -> Integrasi TCES TICS | C44: =IF(INDEX(Syafix!$D:$D, 44)="", NA(), INDEX(Syafix!$D:$D, 44)) -> Meeting Pembahasan CMS TCES | D44: =IF(INDEX(Syafix!$D:$D, 44)="", NA(), INDEX(Syafix!$E:$E, 44)) -> DONE | E44: =IF(INDEX(Syafix!$D:$D, 44)="", NA(), INDEX(Syafix!$K:$K, 44)) -> 46269 | F44: =IF(OR(E44="", ISNA(E44), ISNA(G44)), 0, MAX(1, G44-E44)) -> 1 | G44: =IF(INDEX(Syafix!$D:$D, 44)="", NA(), INDEX(Syafix!$L:$L, 44)) -> 46269 | H44: =IF(ISNA(C44), NA(), A44 & " - " & B44 & " - " & C44) -> Syafix (Business Analyst) - Integrasi TCES TICS - Meeting Pembahasan CMS TCES
A45: =IF(INDEX(Syafix!$D:$D, 45)="", NA(), "Syafix (Business Analyst)") -> Syafix (Business Analyst) | B45: =IF(INDEX(Syafix!$D:$D, 45)="", NA(), INDEX(Syafix!$B:$B, 45)) -> Integrasi TCES TICS | C45: =IF(INDEX(Syafix!$D:$D, 45)="", NA(), INDEX(Syafix!$D:$D, 45)) -> Meeting Pembahasan Pembagian Pekerjaan dan Percepatan untuk Go Live TCES Khusus untuk product TRide dan TDrive | D45: =IF(INDEX(Syafix!$D:$D, 45)="", NA(), INDEX(Syafix!$E:$E, 45)) -> DONE | E45: =IF(INDEX(Syafix!$D:$D, 45)="", NA(), INDEX(Syafix!$K:$K, 45)) -> 46272 | F45: =IF(OR(E45="", ISNA(E45), ISNA(G45)), 0, MAX(1, G45-E45)) -> 1 | G45: =IF(INDEX(Syafix!$D:$D, 45)="", NA(), INDEX(Syafix!$L:$L, 45)) -> 46272 | H45: =IF(ISNA(C45), NA(), A45 & " - " & B45 & " - " & C45) -> Syafix (Business Analyst) - Integrasi TCES TICS - Meeting Pembahasan Pembagian Pekerjaan dan Percepatan untuk Go Live TCES Khusus untuk product TRide dan TDrive
A46: =IF(INDEX(Syafix!$D:$D, 46)="", NA(), "Syafix (Business Analyst)") -> Syafix (Business Analyst) | B46: =IF(INDEX(Syafix!$D:$D, 46)="", NA(), INDEX(Syafix!$B:$B, 46)) -> Integrasi TCES TICS | C46: =IF(INDEX(Syafix!$D:$D, 46)="", NA(), INDEX(Syafix!$D:$D, 46)) -> Membuat laporan BAST Elistec dan kelengkapan informasi data task pengerjaan project dari keseluruhan member | D46: =IF(INDEX(Syafix!$D:$D, 46)="", NA(), INDEX(Syafix!$E:$E, 46)) -> DONE | E46: =IF(INDEX(Syafix!$D:$D, 46)="", NA(), INDEX(Syafix!$K:$K, 46)) -> 46272 | F46: =IF(OR(E46="", ISNA(E46), ISNA(G46)), 0, MAX(1, G46-E46)) -> 1 | G46: =IF(INDEX(Syafix!$D:$D, 46)="", NA(), INDEX(Syafix!$L:$L, 46)) -> 46273 | H46: =IF(ISNA(C46), NA(), A46 & " - " & B46 & " - " & C46) -> Syafix (Business Analyst) - Integrasi TCES TICS - Membuat laporan BAST Elistec dan kelengkapan informasi data task pengerjaan project dari keseluruhan member
A47: =IF(INDEX(Syafix!$D:$D, 47)="", NA(), "Syafix (Business Analyst)") -> Syafix (Business Analyst) | B47: =IF(INDEX(Syafix!$D:$D, 47)="", NA(), INDEX(Syafix!$B:$B, 47)) -> Integrasi TCES TICS | C47: =IF(INDEX(Syafix!$D:$D, 47)="", NA(), INDEX(Syafix!$D:$D, 47)) -> Perbaikan Struktur BRD | D47: =IF(INDEX(Syafix!$D:$D, 47)="", NA(), INDEX(Syafix!$E:$E, 47)) -> DONE | E47: =IF(INDEX(Syafix!$D:$D, 47)="", NA(), INDEX(Syafix!$K:$K, 47)) -> 46272 | F47: =IF(OR(E47="", ISNA(E47), ISNA(G47)), 0, MAX(1, G47-E47)) -> 4 | G47: =IF(INDEX(Syafix!$D:$D, 47)="", NA(), INDEX(Syafix!$L:$L, 47)) -> 46276 | H47: =IF(ISNA(C47), NA(), A47 & " - " & B47 & " - " & C47) -> Syafix (Business Analyst) - Integrasi TCES TICS - Perbaikan Struktur BRD
A48: =IF(INDEX(Syafix!$D:$D, 48)="", NA(), "Syafix (Business Analyst)") -> Syafix (Business Analyst) | B48: =IF(INDEX(Syafix!$D:$D, 48)="", NA(), INDEX(Syafix!$B:$B, 48)) -> Integrasi TCES TICS | C48: =IF(INDEX(Syafix!$D:$D, 48)="", NA(), INDEX(Syafix!$D:$D, 48)) -> Penambahan informasi link evidence untuk semua timesheet kebutuhan BAST | D48: =IF(INDEX(Syafix!$D:$D, 48)="", NA(), INDEX(Syafix!$E:$E, 48)) -> DONE | E48: =IF(INDEX(Syafix!$D:$D, 48)="", NA(), INDEX(Syafix!$K:$K, 48)) -> 46273 | F48: =IF(OR(E48="", ISNA(E48), ISNA(G48)), 0, MAX(1, G48-E48)) -> 1 | G48: =IF(INDEX(Syafix!$D:$D, 48)="", NA(), INDEX(Syafix!$L:$L, 48)) -> 46273 | H48: =IF(ISNA(C48), NA(), A48 & " - " & B48 & " - " & C48) -> Syafix (Business Analyst) - Integrasi TCES TICS - Penambahan informasi link evidence untuk semua timesheet kebutuhan BAST
A49: =IF(INDEX(Syafix!$D:$D, 49)="", NA(), "Syafix (Business Analyst)") -> Syafix (Business Analyst) | B49: =IF(INDEX(Syafix!$D:$D, 49)="", NA(), INDEX(Syafix!$B:$B, 49)) -> Pengembangan Mass Product Retail | C49: =IF(INDEX(Syafix!$D:$D, 49)="", NA(), INDEX(Syafix!$D:$D, 49)) -> Pembuatan TC Kebutuhan Testing Mass Product | D49: =IF(INDEX(Syafix!$D:$D, 49)="", NA(), INDEX(Syafix!$E:$E, 49)) -> TODO | E49: =IF(INDEX(Syafix!$D:$D, 49)="", NA(), INDEX(Syafix!$K:$K, 49)) -> 46275 | F49: =IF(OR(E49="", ISNA(E49), ISNA(G49)), 0, MAX(1, G49-E49)) -> 1 | G49: =IF(INDEX(Syafix!$D:$D, 49)="", NA(), INDEX(Syafix!$L:$L, 49)) -> 46275 | H49: =IF(ISNA(C49), NA(), A49 & " - " & B49 & " - " & C49) -> Syafix (Business Analyst) - Pengembangan Mass Product Retail - Pembuatan TC Kebutuhan Testing Mass Product
A50: =IF(INDEX(Syafix!$D:$D, 50)="", NA(), "Syafix (Business Analyst)") -> Syafix (Business Analyst) | B50: =IF(INDEX(Syafix!$D:$D, 50)="", NA(), INDEX(Syafix!$B:$B, 50)) -> Pengembangan Mass Product Retail | C50: =IF(INDEX(Syafix!$D:$D, 50)="", NA(), INDEX(Syafix!$D:$D, 50)) -> Meeting penjelasan work flow mass product dengan developer, qa, dan BA | D50: =IF(INDEX(Syafix!$D:$D, 50)="", NA(), INDEX(Syafix!$E:$E, 50)) -> TODO | E50: =IF(INDEX(Syafix!$D:$D, 50)="", NA(), INDEX(Syafix!$K:$K, 50)) -> 46275 | F50: =IF(OR(E50="", ISNA(E50), ISNA(G50)), 0, MAX(1, G50-E50)) -> 1 | G50: =IF(INDEX(Syafix!$D:$D, 50)="", NA(), INDEX(Syafix!$L:$L, 50)) -> 46275 | H50: =IF(ISNA(C50), NA(), A50 & " - " & B50 & " - " & C50) -> Syafix (Business Analyst) - Pengembangan Mass Product Retail - Meeting penjelasan work flow mass product dengan developer, qa, dan BA
A51: =IF(INDEX(Syafix!$D:$D, 51)="", NA(), "Syafix (Business Analyst)") -> Syafix (Business Analyst) | B51: =IF(INDEX(Syafix!$D:$D, 51)="", NA(), INDEX(Syafix!$B:$B, 51)) -> Integrasi TCES TICS | C51: =IF(INDEX(Syafix!$D:$D, 51)="", NA(), INDEX(Syafix!$D:$D, 51)) -> Finalisasi FSD | D51: =IF(INDEX(Syafix!$D:$D, 51)="", NA(), INDEX(Syafix!$E:$E, 51)) -> DONE | E51: =IF(INDEX(Syafix!$D:$D, 51)="", NA(), INDEX(Syafix!$K:$K, 51)) -> 46275 | F51: =IF(OR(E51="", ISNA(E51), ISNA(G51)), 0, MAX(1, G51-E51)) -> 1 | G51: =IF(INDEX(Syafix!$D:$D, 51)="", NA(), INDEX(Syafix!$L:$L, 51)) -> 46276 | H51: =IF(ISNA(C51), NA(), A51 & " - " & B51 & " - " & C51) -> Syafix (Business Analyst) - Integrasi TCES TICS - Finalisasi FSD
A52: =IF(INDEX(Syafix!$D:$D, 52)="", NA(), "Syafix (Business Analyst)") -> Syafix (Business Analyst) | B52: =IF(INDEX(Syafix!$D:$D, 52)="", NA(), INDEX(Syafix!$B:$B, 52)) -> Integrasi TCES TICS | C52: =IF(INDEX(Syafix!$D:$D, 52)="", NA(), INDEX(Syafix!$D:$D, 52)) -> Finalisasi TSD (BA) | D52: =IF(INDEX(Syafix!$D:$D, 52)="", NA(), INDEX(Syafix!$E:$E, 52)) -> DONE | E52: =IF(INDEX(Syafix!$D:$D, 52)="", NA(), INDEX(Syafix!$K:$K, 52)) -> 46275 | F52: =IF(OR(E52="", ISNA(E52), ISNA(G52)), 0, MAX(1, G52-E52)) -> 1 | G52: =IF(INDEX(Syafix!$D:$D, 52)="", NA(), INDEX(Syafix!$L:$L, 52)) -> 46276 | H52: =IF(ISNA(C52), NA(), A52 & " - " & B52 & " - " & C52) -> Syafix (Business Analyst) - Integrasi TCES TICS - Finalisasi TSD (BA)
A53: =IF(INDEX(Syafix!$D:$D, 53)="", NA(), "Syafix (Business Analyst)") -> Syafix (Business Analyst) | B53: =IF(INDEX(Syafix!$D:$D, 53)="", NA(), INDEX(Syafix!$B:$B, 53)) -> Integrasi TCES TICS | C53: =IF(INDEX(Syafix!$D:$D, 53)="", NA(), INDEX(Syafix!$D:$D, 53)) -> Pengujian Kembali dari Data TCES untuk TDRive, TRide, pada tanggal 8 Sept untuk penambahan pengujian promo | D53: =IF(INDEX(Syafix!$D:$D, 53)="", NA(), INDEX(Syafix!$E:$E, 53)) -> DONE | E53: =IF(INDEX(Syafix!$D:$D, 53)="", NA(), INDEX(Syafix!$K:$K, 53)) -> 46275 | F53: =IF(OR(E53="", ISNA(E53), ISNA(G53)), 0, MAX(1, G53-E53)) -> 1 | G53: =IF(INDEX(Syafix!$D:$D, 53)="", NA(), INDEX(Syafix!$L:$L, 53)) -> 46276 | H53: =IF(ISNA(C53), NA(), A53 & " - " & B53 & " - " & C53) -> Syafix (Business Analyst) - Integrasi TCES TICS - Pengujian Kembali dari Data TCES untuk TDRive, TRide, pada tanggal 8 Sept untuk penambahan pengujian promo
A54: =IF(INDEX(Syafix!$D:$D, 54)="", NA(), "Syafix (Business Analyst)") -> Syafix (Business Analyst) | B54: =IF(INDEX(Syafix!$D:$D, 54)="", NA(), INDEX(Syafix!$B:$B, 54)) -> Integrasi TCES TICS | C54: =IF(INDEX(Syafix!$D:$D, 54)="", NA(), INDEX(Syafix!$D:$D, 54)) -> Lanjutan - Pengujian Kembali dari Data TCES untuk TDRive, TRide, pada tanggal 10 Sept untuk penambahan pengujian promo | D54: =IF(INDEX(Syafix!$D:$D, 54)="", NA(), INDEX(Syafix!$E:$E, 54)) -> DONE | E54: =IF(INDEX(Syafix!$D:$D, 54)="", NA(), INDEX(Syafix!$K:$K, 54)) -> 46276 | F54: =IF(OR(E54="", ISNA(E54), ISNA(G54)), 0, MAX(1, G54-E54)) -> 1 | G54: =IF(INDEX(Syafix!$D:$D, 54)="", NA(), INDEX(Syafix!$L:$L, 54)) -> 46276 | H54: =IF(ISNA(C54), NA(), A54 & " - " & B54 & " - " & C54) -> Syafix (Business Analyst) - Integrasi TCES TICS - Lanjutan - Pengujian Kembali dari Data TCES untuk TDRive, TRide, pada tanggal 10 Sept untuk penambahan pengujian promo
A55: =IF(INDEX(Syafix!$D:$D, 55)="", NA(), "Syafix (Business Analyst)") -> Syafix (Business Analyst) | B55: =IF(INDEX(Syafix!$D:$D, 55)="", NA(), INDEX(Syafix!$B:$B, 55)) -> Integrasi TCES TICS | C55: =IF(INDEX(Syafix!$D:$D, 55)="", NA(), INDEX(Syafix!$D:$D, 55)) -> Mempelajari Treaty Travela dengan mas Egy dan mba Etha | D55: =IF(INDEX(Syafix!$D:$D, 55)="", NA(), INDEX(Syafix!$E:$E, 55)) -> DONE | E55: =IF(INDEX(Syafix!$D:$D, 55)="", NA(), INDEX(Syafix!$K:$K, 55)) -> 46276 | F55: =IF(OR(E55="", ISNA(E55), ISNA(G55)), 0, MAX(1, G55-E55)) -> 1 | G55: =IF(INDEX(Syafix!$D:$D, 55)="", NA(), INDEX(Syafix!$L:$L, 55)) -> 46276 | H55: =IF(ISNA(C55), NA(), A55 & " - " & B55 & " - " & C55) -> Syafix (Business Analyst) - Integrasi TCES TICS - Mempelajari Treaty Travela dengan mas Egy dan mba Etha
A56: =IF(INDEX(Syafix!$D:$D, 56)="", NA(), "Syafix (Business Analyst)") -> Syafix (Business Analyst) | B56: =IF(INDEX(Syafix!$D:$D, 56)="", NA(), INDEX(Syafix!$B:$B, 56)) -> Integrasi TCES TICS | C56: =IF(INDEX(Syafix!$D:$D, 56)="", NA(), INDEX(Syafix!$D:$D, 56)) -> Update TCES Payload untuk penambahan informasi kode kendaraan agar sync dengan TICS | D56: =IF(INDEX(Syafix!$D:$D, 56)="", NA(), INDEX(Syafix!$E:$E, 56)) -> DONE | E56: =IF(INDEX(Syafix!$D:$D, 56)="", NA(), INDEX(Syafix!$K:$K, 56)) -> 46280 | F56: =IF(OR(E56="", ISNA(E56), ISNA(G56)), 0, MAX(1, G56-E56)) -> 3 | G56: =IF(INDEX(Syafix!$D:$D, 56)="", NA(), INDEX(Syafix!$L:$L, 56)) -> 46283 | H56: =IF(ISNA(C56), NA(), A56 & " - " & B56 & " - " & C56) -> Syafix (Business Analyst) - Integrasi TCES TICS - Update TCES Payload untuk penambahan informasi kode kendaraan agar sync dengan TICS
A57: =IF(INDEX(Syafix!$D:$D, 57)="", NA(), "Syafix (Business Analyst)") -> Syafix (Business Analyst) | B57: =IF(INDEX(Syafix!$D:$D, 57)="", NA(), INDEX(Syafix!$B:$B, 57)) -> API Settlement Payment | C57: =IF(INDEX(Syafix!$D:$D, 57)="", NA(), INDEX(Syafix!$D:$D, 57)) -> Perancangan Sistem dan Project API Settlement Payment | D57: =IF(INDEX(Syafix!$D:$D, 57)="", NA(), INDEX(Syafix!$E:$E, 57)) -> DONE | E57: =IF(INDEX(Syafix!$D:$D, 57)="", NA(), INDEX(Syafix!$K:$K, 57)) -> 46280 | F57: =IF(OR(E57="", ISNA(E57), ISNA(G57)), 0, MAX(1, G57-E57)) -> 3 | G57: =IF(INDEX(Syafix!$D:$D, 57)="", NA(), INDEX(Syafix!$L:$L, 57)) -> 46283 | H57: =IF(ISNA(C57), NA(), A57 & " - " & B57 & " - " & C57) -> Syafix (Business Analyst) - API Settlement Payment - Perancangan Sistem dan Project API Settlement Payment
A58: =IF(INDEX(Syafix!$D:$D, 58)="", NA(), "Syafix (Business Analyst)") -> Syafix (Business Analyst) | B58: =IF(INDEX(Syafix!$D:$D, 58)="", NA(), INDEX(Syafix!$B:$B, 58)) -> API Settlement Payment | C58: =IF(INDEX(Syafix!$D:$D, 58)="", NA(), INDEX(Syafix!$D:$D, 58)) -> Meeting Pembahasan Settlement Payment Flow | D58: =IF(INDEX(Syafix!$D:$D, 58)="", NA(), INDEX(Syafix!$E:$E, 58)) -> DONE | E58: =IF(INDEX(Syafix!$D:$D, 58)="", NA(), INDEX(Syafix!$K:$K, 58)) -> 46280 | F58: =IF(OR(E58="", ISNA(E58), ISNA(G58)), 0, MAX(1, G58-E58)) -> 1 | G58: =IF(INDEX(Syafix!$D:$D, 58)="", NA(), INDEX(Syafix!$L:$L, 58)) -> 46280 | H58: =IF(ISNA(C58), NA(), A58 & " - " & B58 & " - " & C58) -> Syafix (Business Analyst) - API Settlement Payment - Meeting Pembahasan Settlement Payment Flow
A59: =IF(INDEX(Syafix!$D:$D, 59)="", NA(), "Syafix (Business Analyst)") -> Syafix (Business Analyst) | B59: =IF(INDEX(Syafix!$D:$D, 59)="", NA(), INDEX(Syafix!$B:$B, 59)) -> API Settlement Payment | C59: =IF(INDEX(Syafix!$D:$D, 59)="", NA(), INDEX(Syafix!$D:$D, 59)) -> Membuat Diagram Proses Perancangan API Settlement Payment | D59: =IF(INDEX(Syafix!$D:$D, 59)="", NA(), INDEX(Syafix!$E:$E, 59)) -> DONE | E59: =IF(INDEX(Syafix!$D:$D, 59)="", NA(), INDEX(Syafix!$K:$K, 59)) -> 46280 | F59: =IF(OR(E59="", ISNA(E59), ISNA(G59)), 0, MAX(1, G59-E59)) -> 3 | G59: =IF(INDEX(Syafix!$D:$D, 59)="", NA(), INDEX(Syafix!$L:$L, 59)) -> 46283 | H59: =IF(ISNA(C59), NA(), A59 & " - " & B59 & " - " & C59) -> Syafix (Business Analyst) - API Settlement Payment - Membuat Diagram Proses Perancangan API Settlement Payment
A60: =IF(INDEX(Syafix!$D:$D, 60)="", NA(), "Syafix (Business Analyst)") -> Syafix (Business Analyst) | B60: =IF(INDEX(Syafix!$D:$D, 60)="", NA(), INDEX(Syafix!$B:$B, 60)) -> Integrasi TCES TICS | C60: =IF(INDEX(Syafix!$D:$D, 60)="", NA(), INDEX(Syafix!$D:$D, 60)) -> Meeting pembahasan Claim Polis TCES dengan Business User dan Elistec | D60: =IF(INDEX(Syafix!$D:$D, 60)="", NA(), INDEX(Syafix!$E:$E, 60)) -> DONE | E60: =IF(INDEX(Syafix!$D:$D, 60)="", NA(), INDEX(Syafix!$K:$K, 60)) -> 46281 | F60: =IF(OR(E60="", ISNA(E60), ISNA(G60)), 0, MAX(1, G60-E60)) -> 1 | G60: =IF(INDEX(Syafix!$D:$D, 60)="", NA(), INDEX(Syafix!$L:$L, 60)) -> 46281 | H60: =IF(ISNA(C60), NA(), A60 & " - " & B60 & " - " & C60) -> Syafix (Business Analyst) - Integrasi TCES TICS - Meeting pembahasan Claim Polis TCES dengan Business User dan Elistec
A61: =IF(INDEX(Syafix!$D:$D, 61)="", NA(), "Syafix (Business Analyst)") -> Syafix (Business Analyst) | B61: =IF(INDEX(Syafix!$D:$D, 61)="", NA(), INDEX(Syafix!$B:$B, 61)) -> API Settlement Payment | C61: =IF(INDEX(Syafix!$D:$D, 61)="", NA(), INDEX(Syafix!$D:$D, 61)) -> Pembuatan BRD API Settlement Payment | D61: =IF(INDEX(Syafix!$D:$D, 61)="", NA(), INDEX(Syafix!$E:$E, 61)) -> DONE | E61: =IF(INDEX(Syafix!$D:$D, 61)="", NA(), INDEX(Syafix!$K:$K, 61)) -> 46281 | F61: =IF(OR(E61="", ISNA(E61), ISNA(G61)), 0, MAX(1, G61-E61)) -> 15 | G61: =IF(INDEX(Syafix!$D:$D, 61)="", NA(), INDEX(Syafix!$L:$L, 61)) -> 46296 | H61: =IF(ISNA(C61), NA(), A61 & " - " & B61 & " - " & C61) -> Syafix (Business Analyst) - API Settlement Payment - Pembuatan BRD API Settlement Payment
A62: =IF(INDEX(Syafix!$D:$D, 62)="", NA(), "Syafix (Business Analyst)") -> Syafix (Business Analyst) | B62: =IF(INDEX(Syafix!$D:$D, 62)="", NA(), INDEX(Syafix!$B:$B, 62)) -> Integrasi TCES TICS | C62: =IF(INDEX(Syafix!$D:$D, 62)="", NA(), INDEX(Syafix!$D:$D, 62)) -> Membantu QA melakukan pengecekan data testing yang blocked | D62: =IF(INDEX(Syafix!$D:$D, 62)="", NA(), INDEX(Syafix!$E:$E, 62)) -> DONE | E62: =IF(INDEX(Syafix!$D:$D, 62)="", NA(), INDEX(Syafix!$K:$K, 62)) -> 46282 | F62: =IF(OR(E62="", ISNA(E62), ISNA(G62)), 0, MAX(1, G62-E62)) -> 1 | G62: =IF(INDEX(Syafix!$D:$D, 62)="", NA(), INDEX(Syafix!$L:$L, 62)) -> 46282 | H62: =IF(ISNA(C62), NA(), A62 & " - " & B62 & " - " & C62) -> Syafix (Business Analyst) - Integrasi TCES TICS - Membantu QA melakukan pengecekan data testing yang blocked
A63: =IF(INDEX(Syafix!$D:$D, 63)="", NA(), "Syafix (Business Analyst)") -> Syafix (Business Analyst) | B63: =IF(INDEX(Syafix!$D:$D, 63)="", NA(), INDEX(Syafix!$B:$B, 63)) -> Integrasi TCES TICS | C63: =IF(INDEX(Syafix!$D:$D, 63)="", NA(), INDEX(Syafix!$D:$D, 63)) -> Meeting Sharing Knowledge TCES oleh tim Elistec dan Tugu | D63: =IF(INDEX(Syafix!$D:$D, 63)="", NA(), INDEX(Syafix!$E:$E, 63)) -> DONE | E63: =IF(INDEX(Syafix!$D:$D, 63)="", NA(), INDEX(Syafix!$K:$K, 63)) -> 46283 | F63: =IF(OR(E63="", ISNA(E63), ISNA(G63)), 0, MAX(1, G63-E63)) -> 1 | G63: =IF(INDEX(Syafix!$D:$D, 63)="", NA(), INDEX(Syafix!$L:$L, 63)) -> 46283 | H63: =IF(ISNA(C63), NA(), A63 & " - " & B63 & " - " & C63) -> Syafix (Business Analyst) - Integrasi TCES TICS - Meeting Sharing Knowledge TCES oleh tim Elistec dan Tugu
A64: =IF(INDEX(Syafix!$D:$D, 64)="", NA(), "Syafix (Business Analyst)") -> Syafix (Business Analyst) | B64: =IF(INDEX(Syafix!$D:$D, 64)="", NA(), INDEX(Syafix!$B:$B, 64)) -> API Settlement Payment | C64: =IF(INDEX(Syafix!$D:$D, 64)="", NA(), INDEX(Syafix!$D:$D, 64)) -> Melengkapi Dokumen TSD | D64: =IF(INDEX(Syafix!$D:$D, 64)="", NA(), INDEX(Syafix!$E:$E, 64)) -> DONE | E64: =IF(INDEX(Syafix!$D:$D, 64)="", NA(), INDEX(Syafix!$K:$K, 64)) -> 46283 | F64: =IF(OR(E64="", ISNA(E64), ISNA(G64)), 0, MAX(1, G64-E64)) -> 17 | G64: =IF(INDEX(Syafix!$D:$D, 64)="", NA(), INDEX(Syafix!$L:$L, 64)) -> 46300 | H64: =IF(ISNA(C64), NA(), A64 & " - " & B64 & " - " & C64) -> Syafix (Business Analyst) - API Settlement Payment - Melengkapi Dokumen TSD
A65: =IF(INDEX(Syafix!$D:$D, 65)="", NA(), "Syafix (Business Analyst)") -> Syafix (Business Analyst) | B65: =IF(INDEX(Syafix!$D:$D, 65)="", NA(), INDEX(Syafix!$B:$B, 65)) -> API Settlement Payment | C65: =IF(INDEX(Syafix!$D:$D, 65)="", NA(), INDEX(Syafix!$D:$D, 65)) -> Melengkapi Dokumen FSD | D65: =IF(INDEX(Syafix!$D:$D, 65)="", NA(), INDEX(Syafix!$E:$E, 65)) -> DONE | E65: =IF(INDEX(Syafix!$D:$D, 65)="", NA(), INDEX(Syafix!$K:$K, 65)) -> 46283 | F65: =IF(OR(E65="", ISNA(E65), ISNA(G65)), 0, MAX(1, G65-E65)) -> 17 | G65: =IF(INDEX(Syafix!$D:$D, 65)="", NA(), INDEX(Syafix!$L:$L, 65)) -> 46300 | H65: =IF(ISNA(C65), NA(), A65 & " - " & B65 & " - " & C65) -> Syafix (Business Analyst) - API Settlement Payment - Melengkapi Dokumen FSD
A66: =IF(INDEX(Syafix!$D:$D, 66)="", NA(), "Syafix (Business Analyst)") -> Syafix (Business Analyst) | B66: =IF(INDEX(Syafix!$D:$D, 66)="", NA(), INDEX(Syafix!$B:$B, 66)) -> API Settlement Payment | C66: =IF(INDEX(Syafix!$D:$D, 66)="", NA(), INDEX(Syafix!$D:$D, 66)) -> Membuat Diagram Sequence API Settlemen Payment | D66: =IF(INDEX(Syafix!$D:$D, 66)="", NA(), INDEX(Syafix!$E:$E, 66)) -> DONE | E66: =IF(INDEX(Syafix!$D:$D, 66)="", NA(), INDEX(Syafix!$K:$K, 66)) -> 46286 | F66: =IF(OR(E66="", ISNA(E66), ISNA(G66)), 0, MAX(1, G66-E66)) -> 2 | G66: =IF(INDEX(Syafix!$D:$D, 66)="", NA(), INDEX(Syafix!$L:$L, 66)) -> 46288 | H66: =IF(ISNA(C66), NA(), A66 & " - " & B66 & " - " & C66) -> Syafix (Business Analyst) - API Settlement Payment - Membuat Diagram Sequence API Settlemen Payment
A67: =IF(INDEX(Syafix!$D:$D, 67)="", NA(), "Syafix (Business Analyst)") -> Syafix (Business Analyst) | B67: =IF(INDEX(Syafix!$D:$D, 67)="", NA(), INDEX(Syafix!$B:$B, 67)) -> API Settlement Payment | C67: =IF(INDEX(Syafix!$D:$D, 67)="", NA(), INDEX(Syafix!$D:$D, 67)) -> Membuat ERD API Settlemen Payment | D67: =IF(INDEX(Syafix!$D:$D, 67)="", NA(), INDEX(Syafix!$E:$E, 67)) -> DONE | E67: =IF(INDEX(Syafix!$D:$D, 67)="", NA(), INDEX(Syafix!$K:$K, 67)) -> 46286 | F67: =IF(OR(E67="", ISNA(E67), ISNA(G67)), 0, MAX(1, G67-E67)) -> 2 | G67: =IF(INDEX(Syafix!$D:$D, 67)="", NA(), INDEX(Syafix!$L:$L, 67)) -> 46288 | H67: =IF(ISNA(C67), NA(), A67 & " - " & B67 & " - " & C67) -> Syafix (Business Analyst) - API Settlement Payment - Membuat ERD API Settlemen Payment
A68: =IF(INDEX(Syafix!$D:$D, 68)="", NA(), "Syafix (Business Analyst)") -> Syafix (Business Analyst) | B68: =IF(INDEX(Syafix!$D:$D, 68)="", NA(), INDEX(Syafix!$B:$B, 68)) -> API Settlement Payment | C68: =IF(INDEX(Syafix!$D:$D, 68)="", NA(), INDEX(Syafix!$D:$D, 68)) -> Perancangan Struktur Payload untuk Settlement Payment TCES - TICS | D68: =IF(INDEX(Syafix!$D:$D, 68)="", NA(), INDEX(Syafix!$E:$E, 68)) -> DONE | E68: =IF(INDEX(Syafix!$D:$D, 68)="", NA(), INDEX(Syafix!$K:$K, 68)) -> 46286 | F68: =IF(OR(E68="", ISNA(E68), ISNA(G68)), 0, MAX(1, G68-E68)) -> 2 | G68: =IF(INDEX(Syafix!$D:$D, 68)="", NA(), INDEX(Syafix!$L:$L, 68)) -> 46288 | H68: =IF(ISNA(C68), NA(), A68 & " - " & B68 & " - " & C68) -> Syafix (Business Analyst) - API Settlement Payment - Perancangan Struktur Payload untuk Settlement Payment TCES - TICS
A69: =IF(INDEX(Syafix!$D:$D, 69)="", NA(), "Syafix (Business Analyst)") -> Syafix (Business Analyst) | B69: =IF(INDEX(Syafix!$D:$D, 69)="", NA(), INDEX(Syafix!$B:$B, 69)) -> API Settlement Payment | C69: =IF(INDEX(Syafix!$D:$D, 69)="", NA(), INDEX(Syafix!$D:$D, 69)) -> Membuat penambahan kolom untuk menggunakan table lama yang sudah dibuat untuk sesuai dengan Settlement Payment | D69: =IF(INDEX(Syafix!$D:$D, 69)="", NA(), INDEX(Syafix!$E:$E, 69)) -> DONE | E69: =IF(INDEX(Syafix!$D:$D, 69)="", NA(), INDEX(Syafix!$K:$K, 69)) -> 46287 | F69: =IF(OR(E69="", ISNA(E69), ISNA(G69)), 0, MAX(1, G69-E69)) -> 2 | G69: =IF(INDEX(Syafix!$D:$D, 69)="", NA(), INDEX(Syafix!$L:$L, 69)) -> 46289 | H69: =IF(ISNA(C69), NA(), A69 & " - " & B69 & " - " & C69) -> Syafix (Business Analyst) - API Settlement Payment - Membuat penambahan kolom untuk menggunakan table lama yang sudah dibuat untuk sesuai dengan Settlement Payment
A70: =IF(INDEX(Syafix!$D:$D, 70)="", NA(), "Syafix (Business Analyst)") -> Syafix (Business Analyst) | B70: =IF(INDEX(Syafix!$D:$D, 70)="", NA(), INDEX(Syafix!$B:$B, 70)) -> API Settlement Payment | C70: =IF(INDEX(Syafix!$D:$D, 70)="", NA(), INDEX(Syafix!$D:$D, 70)) -> Pendefinisian informasi pengambilan data ZSDDT0002 untuk spesifik zreq id tertentu dan informasi balikan dari SAP terkait GJAHR dan BELNR | D70: =IF(INDEX(Syafix!$D:$D, 70)="", NA(), INDEX(Syafix!$E:$E, 70)) -> DONE | E70: =IF(INDEX(Syafix!$D:$D, 70)="", NA(), INDEX(Syafix!$K:$K, 70)) -> 46287 | F70: =IF(OR(E70="", ISNA(E70), ISNA(G70)), 0, MAX(1, G70-E70)) -> 2 | G70: =IF(INDEX(Syafix!$D:$D, 70)="", NA(), INDEX(Syafix!$L:$L, 70)) -> 46289 | H70: =IF(ISNA(C70), NA(), A70 & " - " & B70 & " - " & C70) -> Syafix (Business Analyst) - API Settlement Payment - Pendefinisian informasi pengambilan data ZSDDT0002 untuk spesifik zreq id tertentu dan informasi balikan dari SAP terkait GJAHR dan BELNR
A71: =IF(INDEX(Syafix!$D:$D, 71)="", NA(), "Syafix (Business Analyst)") -> Syafix (Business Analyst) | B71: =IF(INDEX(Syafix!$D:$D, 71)="", NA(), INDEX(Syafix!$B:$B, 71)) -> API Settlement Payment | C71: =IF(INDEX(Syafix!$D:$D, 71)="", NA(), INDEX(Syafix!$D:$D, 71)) -> Update diagram Sequence API Settlement Payment | D71: =IF(INDEX(Syafix!$D:$D, 71)="", NA(), INDEX(Syafix!$E:$E, 71)) -> DONE | E71: =IF(INDEX(Syafix!$D:$D, 71)="", NA(), INDEX(Syafix!$K:$K, 71)) -> 46288 | F71: =IF(OR(E71="", ISNA(E71), ISNA(G71)), 0, MAX(1, G71-E71)) -> 1 | G71: =IF(INDEX(Syafix!$D:$D, 71)="", NA(), INDEX(Syafix!$L:$L, 71)) -> 46288 | H71: =IF(ISNA(C71), NA(), A71 & " - " & B71 & " - " & C71) -> Syafix (Business Analyst) - API Settlement Payment - Update diagram Sequence API Settlement Payment
A72: =IF(INDEX(Syafix!$D:$D, 72)="", NA(), "Syafix (Business Analyst)") -> Syafix (Business Analyst) | B72: =IF(INDEX(Syafix!$D:$D, 72)="", NA(), INDEX(Syafix!$B:$B, 72)) -> API Settlement Payment | C72: =IF(INDEX(Syafix!$D:$D, 72)="", NA(), INDEX(Syafix!$D:$D, 72)) -> Update diagram FlowChart API Settlement Payment | D72: =IF(INDEX(Syafix!$D:$D, 72)="", NA(), INDEX(Syafix!$E:$E, 72)) -> DONE | E72: =IF(INDEX(Syafix!$D:$D, 72)="", NA(), INDEX(Syafix!$K:$K, 72)) -> 46288 | F72: =IF(OR(E72="", ISNA(E72), ISNA(G72)), 0, MAX(1, G72-E72)) -> 1 | G72: =IF(INDEX(Syafix!$D:$D, 72)="", NA(), INDEX(Syafix!$L:$L, 72)) -> 46288 | H72: =IF(ISNA(C72), NA(), A72 & " - " & B72 & " - " & C72) -> Syafix (Business Analyst) - API Settlement Payment - Update diagram FlowChart API Settlement Payment
A73: =IF(INDEX(Syafix!$D:$D, 73)="", NA(), "Syafix (Business Analyst)") -> Syafix (Business Analyst) | B73: =IF(INDEX(Syafix!$D:$D, 73)="", NA(), INDEX(Syafix!$B:$B, 73)) -> API Settlement Payment | C73: =IF(INDEX(Syafix!$D:$D, 73)="", NA(), INDEX(Syafix!$D:$D, 73)) -> Perancangan model scheduler pada API Settlement Payment untuk melakukan rekonsiliasi data | D73: =IF(INDEX(Syafix!$D:$D, 73)="", NA(), INDEX(Syafix!$E:$E, 73)) -> DONE | E73: =IF(INDEX(Syafix!$D:$D, 73)="", NA(), INDEX(Syafix!$K:$K, 73)) -> 46288 | F73: =IF(OR(E73="", ISNA(E73), ISNA(G73)), 0, MAX(1, G73-E73)) -> 1 | G73: =IF(INDEX(Syafix!$D:$D, 73)="", NA(), INDEX(Syafix!$L:$L, 73)) -> 46289 | H73: =IF(ISNA(C73), NA(), A73 & " - " & B73 & " - " & C73) -> Syafix (Business Analyst) - API Settlement Payment - Perancangan model scheduler pada API Settlement Payment untuk melakukan rekonsiliasi data
A74: =IF(INDEX(Syafix!$D:$D, 74)="", NA(), "Syafix (Business Analyst)") -> Syafix (Business Analyst) | B74: =IF(INDEX(Syafix!$D:$D, 74)="", NA(), INDEX(Syafix!$B:$B, 74)) -> API Settlement Payment | C74: =IF(INDEX(Syafix!$D:$D, 74)="", NA(), INDEX(Syafix!$D:$D, 74)) -> Pengecekan api-doc / Swagger untuk API Settlement Payment | D74: =IF(INDEX(Syafix!$D:$D, 74)="", NA(), INDEX(Syafix!$E:$E, 74)) -> DONE | E74: =IF(INDEX(Syafix!$D:$D, 74)="", NA(), INDEX(Syafix!$K:$K, 74)) -> 46288 | F74: =IF(OR(E74="", ISNA(E74), ISNA(G74)), 0, MAX(1, G74-E74)) -> 1 | G74: =IF(INDEX(Syafix!$D:$D, 74)="", NA(), INDEX(Syafix!$L:$L, 74)) -> 46289 | H74: =IF(ISNA(C74), NA(), A74 & " - " & B74 & " - " & C74) -> Syafix (Business Analyst) - API Settlement Payment - Pengecekan api-doc / Swagger untuk API Settlement Payment
A75: =IF(INDEX(Syafix!$D:$D, 75)="", NA(), "Syafix (Business Analyst)") -> Syafix (Business Analyst) | B75: =IF(INDEX(Syafix!$D:$D, 75)="", NA(), INDEX(Syafix!$B:$B, 75)) -> API Settlement Payment | C75: =IF(INDEX(Syafix!$D:$D, 75)="", NA(), INDEX(Syafix!$D:$D, 75)) -> Pembuatan Test Case scenario untuk melihat transaction date dan bill date sesuai | D75: =IF(INDEX(Syafix!$D:$D, 75)="", NA(), INDEX(Syafix!$E:$E, 75)) -> DONE | E75: =IF(INDEX(Syafix!$D:$D, 75)="", NA(), INDEX(Syafix!$K:$K, 75)) -> 46289 | F75: =IF(OR(E75="", ISNA(E75), ISNA(G75)), 0, MAX(1, G75-E75)) -> 1 | G75: =IF(INDEX(Syafix!$D:$D, 75)="", NA(), INDEX(Syafix!$L:$L, 75)) -> 46290 | H75: =IF(ISNA(C75), NA(), A75 & " - " & B75 & " - " & C75) -> Syafix (Business Analyst) - API Settlement Payment - Pembuatan Test Case scenario untuk melihat transaction date dan bill date sesuai
A76: =IF(INDEX(Syafix!$D:$D, 76)="", NA(), "Syafix (Business Analyst)") -> Syafix (Business Analyst) | B76: =IF(INDEX(Syafix!$D:$D, 76)="", NA(), INDEX(Syafix!$B:$B, 76)) -> API Settlement Payment | C76: =IF(INDEX(Syafix!$D:$D, 76)="", NA(), INDEX(Syafix!$D:$D, 76)) -> Pengecekan API Settlement Payment integrasi antara TCES dengan TICS | D76: =IF(INDEX(Syafix!$D:$D, 76)="", NA(), INDEX(Syafix!$E:$E, 76)) -> DONE | E76: =IF(INDEX(Syafix!$D:$D, 76)="", NA(), INDEX(Syafix!$K:$K, 76)) -> 46289 | F76: =IF(OR(E76="", ISNA(E76), ISNA(G76)), 0, MAX(1, G76-E76)) -> 6 | G76: =IF(INDEX(Syafix!$D:$D, 76)="", NA(), INDEX(Syafix!$L:$L, 76)) -> 46295 | H76: =IF(ISNA(C76), NA(), A76 & " - " & B76 & " - " & C76) -> Syafix (Business Analyst) - API Settlement Payment - Pengecekan API Settlement Payment integrasi antara TCES dengan TICS
A77: =IF(INDEX(Syafix!$D:$D, 77)="", NA(), "Syafix (Business Analyst)") -> Syafix (Business Analyst) | B77: =IF(INDEX(Syafix!$D:$D, 77)="", NA(), INDEX(Syafix!$B:$B, 77)) -> API Settlement Payment | C77: =IF(INDEX(Syafix!$D:$D, 77)="", NA(), INDEX(Syafix!$D:$D, 77)) -> Finalisasi Diagram Arsitektural, FlowChart, Sequence API Settlement Payment | D77: =IF(INDEX(Syafix!$D:$D, 77)="", NA(), INDEX(Syafix!$E:$E, 77)) -> DONE | E77: =IF(INDEX(Syafix!$D:$D, 77)="", NA(), INDEX(Syafix!$K:$K, 77)) -> 46289 | F77: =IF(OR(E77="", ISNA(E77), ISNA(G77)), 0, MAX(1, G77-E77)) -> 1 | G77: =IF(INDEX(Syafix!$D:$D, 77)="", NA(), INDEX(Syafix!$L:$L, 77)) -> 46289 | H77: =IF(ISNA(C77), NA(), A77 & " - " & B77 & " - " & C77) -> Syafix (Business Analyst) - API Settlement Payment - Finalisasi Diagram Arsitektural, FlowChart, Sequence API Settlement Payment
A78: =IF(INDEX(Syafix!$D:$D, 78)="", NA(), "Syafix (Business Analyst)") -> Syafix (Business Analyst) | B78: =IF(INDEX(Syafix!$D:$D, 78)="", NA(), INDEX(Syafix!$B:$B, 78)) -> API Settlement Payment | C78: =IF(INDEX(Syafix!$D:$D, 78)="", NA(), INDEX(Syafix!$D:$D, 78)) -> Membuat table definition untuk kebutuhan update dokumen TSD | D78: =IF(INDEX(Syafix!$D:$D, 78)="", NA(), INDEX(Syafix!$E:$E, 78)) -> DONE | E78: =IF(INDEX(Syafix!$D:$D, 78)="", NA(), INDEX(Syafix!$K:$K, 78)) -> 46293 | F78: =IF(OR(E78="", ISNA(E78), ISNA(G78)), 0, MAX(1, G78-E78)) -> 1 | G78: =IF(INDEX(Syafix!$D:$D, 78)="", NA(), INDEX(Syafix!$L:$L, 78)) -> 46293 | H78: =IF(ISNA(C78), NA(), A78 & " - " & B78 & " - " & C78) -> Syafix (Business Analyst) - API Settlement Payment - Membuat table definition untuk kebutuhan update dokumen TSD
A79: =IF(INDEX(Syafix!$D:$D, 79)="", NA(), "Syafix (Business Analyst)") -> Syafix (Business Analyst) | B79: =IF(INDEX(Syafix!$D:$D, 79)="", NA(), INDEX(Syafix!$B:$B, 79)) -> API Settlement Payment | C79: =IF(INDEX(Syafix!$D:$D, 79)="", NA(), INDEX(Syafix!$D:$D, 79)) -> Meeting Pembahasan rekonsiliasi Settlement Payment antara API Settlement vs Stagging | D79: =IF(INDEX(Syafix!$D:$D, 79)="", NA(), INDEX(Syafix!$E:$E, 79)) -> DONE | E79: =IF(INDEX(Syafix!$D:$D, 79)="", NA(), INDEX(Syafix!$K:$K, 79)) -> 46293 | F79: =IF(OR(E79="", ISNA(E79), ISNA(G79)), 0, MAX(1, G79-E79)) -> 1 | G79: =IF(INDEX(Syafix!$D:$D, 79)="", NA(), INDEX(Syafix!$L:$L, 79)) -> 46293 | H79: =IF(ISNA(C79), NA(), A79 & " - " & B79 & " - " & C79) -> Syafix (Business Analyst) - API Settlement Payment - Meeting Pembahasan rekonsiliasi Settlement Payment antara API Settlement vs Stagging
A80: =IF(INDEX(Syafix!$D:$D, 80)="", NA(), "Syafix (Business Analyst)") -> Syafix (Business Analyst) | B80: =IF(INDEX(Syafix!$D:$D, 80)="", NA(), INDEX(Syafix!$B:$B, 80)) -> API Settlement Payment | C80: =IF(INDEX(Syafix!$D:$D, 80)="", NA(), INDEX(Syafix!$D:$D, 80)) -> Percobaan enforce manual stagging untuk spesifik no polis dan request id tertentu ke stagging dan SAP | D80: =IF(INDEX(Syafix!$D:$D, 80)="", NA(), INDEX(Syafix!$E:$E, 80)) -> DONE | E80: =IF(INDEX(Syafix!$D:$D, 80)="", NA(), INDEX(Syafix!$K:$K, 80)) -> 46294 | F80: =IF(OR(E80="", ISNA(E80), ISNA(G80)), 0, MAX(1, G80-E80)) -> 2 | G80: =IF(INDEX(Syafix!$D:$D, 80)="", NA(), INDEX(Syafix!$L:$L, 80)) -> 46296 | H80: =IF(ISNA(C80), NA(), A80 & " - " & B80 & " - " & C80) -> Syafix (Business Analyst) - API Settlement Payment - Percobaan enforce manual stagging untuk spesifik no polis dan request id tertentu ke stagging dan SAP
A81: =IF(INDEX(Syafix!$D:$D, 81)="", NA(), "Syafix (Business Analyst)") -> Syafix (Business Analyst) | B81: =IF(INDEX(Syafix!$D:$D, 81)="", NA(), INDEX(Syafix!$B:$B, 81)) -> API Settlement Payment | C81: =IF(INDEX(Syafix!$D:$D, 81)="", NA(), INDEX(Syafix!$D:$D, 81)) -> Input data sampling khusus untuk bisnis class TProperty dan Travela via payload untuk pengecekan Stagging | D81: =IF(INDEX(Syafix!$D:$D, 81)="", NA(), INDEX(Syafix!$E:$E, 81)) -> DONE | E81: =IF(INDEX(Syafix!$D:$D, 81)="", NA(), INDEX(Syafix!$K:$K, 81)) -> 46294 | F81: =IF(OR(E81="", ISNA(E81), ISNA(G81)), 0, MAX(1, G81-E81)) -> 1 | G81: =IF(INDEX(Syafix!$D:$D, 81)="", NA(), INDEX(Syafix!$L:$L, 81)) -> 46294 | H81: =IF(ISNA(C81), NA(), A81 & " - " & B81 & " - " & C81) -> Syafix (Business Analyst) - API Settlement Payment - Input data sampling khusus untuk bisnis class TProperty dan Travela via payload untuk pengecekan Stagging
A82: =IF(INDEX(Syafix!$D:$D, 82)="", NA(), "Syafix (Business Analyst)") -> Syafix (Business Analyst) | B82: =IF(INDEX(Syafix!$D:$D, 82)="", NA(), INDEX(Syafix!$B:$B, 82)) -> API Settlement Payment | C82: =IF(INDEX(Syafix!$D:$D, 82)="", NA(), INDEX(Syafix!$D:$D, 82)) -> Melakukan rekonsiliasi data secara manual untuk data MV dan Non-MV Pre proses oleh aplikasi | D82: =IF(INDEX(Syafix!$D:$D, 82)="", NA(), INDEX(Syafix!$E:$E, 82)) -> DONE | E82: =IF(INDEX(Syafix!$D:$D, 82)="", NA(), INDEX(Syafix!$K:$K, 82)) -> 46295 | F82: =IF(OR(E82="", ISNA(E82), ISNA(G82)), 0, MAX(1, G82-E82)) -> 2 | G82: =IF(INDEX(Syafix!$D:$D, 82)="", NA(), INDEX(Syafix!$L:$L, 82)) -> 46297 | H82: =IF(ISNA(C82), NA(), A82 & " - " & B82 & " - " & C82) -> Syafix (Business Analyst) - API Settlement Payment - Melakukan rekonsiliasi data secara manual untuk data MV dan Non-MV Pre proses oleh aplikasi
A83: =IF(INDEX(Syafix!$D:$D, 83)="", NA(), "Syafix (Business Analyst)") -> Syafix (Business Analyst) | B83: =IF(INDEX(Syafix!$D:$D, 83)="", NA(), INDEX(Syafix!$B:$B, 83)) -> API Settlement Payment | C83: =IF(INDEX(Syafix!$D:$D, 83)="", NA(), INDEX(Syafix!$D:$D, 83)) -> Pengecekan Rekonsiliasi dengan sejumlah premi yang ditambahkan dan pengecekan manual | D83: =IF(INDEX(Syafix!$D:$D, 83)="", NA(), INDEX(Syafix!$E:$E, 83)) -> DONE | E83: =IF(INDEX(Syafix!$D:$D, 83)="", NA(), INDEX(Syafix!$K:$K, 83)) -> 46296 | F83: =IF(OR(E83="", ISNA(E83), ISNA(G83)), 0, MAX(1, G83-E83)) -> 1 | G83: =IF(INDEX(Syafix!$D:$D, 83)="", NA(), INDEX(Syafix!$L:$L, 83)) -> 46297 | H83: =IF(ISNA(C83), NA(), A83 & " - " & B83 & " - " & C83) -> Syafix (Business Analyst) - API Settlement Payment - Pengecekan Rekonsiliasi dengan sejumlah premi yang ditambahkan dan pengecekan manual
A84: =IF(INDEX(Syafix!$D:$D, 84)="", NA(), "Syafix (Business Analyst)") -> Syafix (Business Analyst) | B84: =IF(INDEX(Syafix!$D:$D, 84)="", NA(), INDEX(Syafix!$B:$B, 84)) -> API Settlement Payment | C84: =IF(INDEX(Syafix!$D:$D, 84)="", NA(), INDEX(Syafix!$D:$D, 84)) -> Update & finalisasi laporan akhir bulan API Settlement Payment | D84: =IF(INDEX(Syafix!$D:$D, 84)="", NA(), INDEX(Syafix!$E:$E, 84)) -> DONE | E84: =IF(INDEX(Syafix!$D:$D, 84)="", NA(), INDEX(Syafix!$K:$K, 84)) -> 46296 | F84: =IF(OR(E84="", ISNA(E84), ISNA(G84)), 0, MAX(1, G84-E84)) -> 1 | G84: =IF(INDEX(Syafix!$D:$D, 84)="", NA(), INDEX(Syafix!$L:$L, 84)) -> 46297 | H84: =IF(ISNA(C84), NA(), A84 & " - " & B84 & " - " & C84) -> Syafix (Business Analyst) - API Settlement Payment - Update & finalisasi laporan akhir bulan API Settlement Payment
A85: =IF(INDEX(Syafix!$D:$D, 85)="", NA(), "Syafix (Business Analyst)") -> Syafix (Business Analyst) | B85: =IF(INDEX(Syafix!$D:$D, 85)="", NA(), INDEX(Syafix!$B:$B, 85)) -> API Settlement Payment | C85: =IF(INDEX(Syafix!$D:$D, 85)="", NA(), INDEX(Syafix!$D:$D, 85)) -> Pembuatan Timesheet & Project Summary | D85: =IF(INDEX(Syafix!$D:$D, 85)="", NA(), INDEX(Syafix!$E:$E, 85)) -> DONE | E85: =IF(INDEX(Syafix!$D:$D, 85)="", NA(), INDEX(Syafix!$K:$K, 85)) -> 46297 | F85: =IF(OR(E85="", ISNA(E85), ISNA(G85)), 0, MAX(1, G85-E85)) -> 1 | G85: =IF(INDEX(Syafix!$D:$D, 85)="", NA(), INDEX(Syafix!$L:$L, 85)) -> 46297 | H85: =IF(ISNA(C85), NA(), A85 & " - " & B85 & " - " & C85) -> Syafix (Business Analyst) - API Settlement Payment - Pembuatan Timesheet & Project Summary
A86: =IF(INDEX(Syafix!$D:$D, 86)="", NA(), "Syafix (Business Analyst)") -> Syafix (Business Analyst) | B86: =IF(INDEX(Syafix!$D:$D, 86)="", NA(), INDEX(Syafix!$B:$B, 86)) -> API Settlement Payment | C86: =IF(INDEX(Syafix!$D:$D, 86)="", NA(), INDEX(Syafix!$D:$D, 86)) -> Meeting Pembahasan integrasi Settlement BengkelNet | D86: =IF(INDEX(Syafix!$D:$D, 86)="", NA(), INDEX(Syafix!$E:$E, 86)) -> DONE | E86: =IF(INDEX(Syafix!$D:$D, 86)="", NA(), INDEX(Syafix!$K:$K, 86)) -> 46301 | F86: =IF(OR(E86="", ISNA(E86), ISNA(G86)), 0, MAX(1, G86-E86)) -> 1 | G86: =IF(INDEX(Syafix!$D:$D, 86)="", NA(), INDEX(Syafix!$L:$L, 86)) -> 46301 | H86: =IF(ISNA(C86), NA(), A86 & " - " & B86 & " - " & C86) -> Syafix (Business Analyst) - API Settlement Payment - Meeting Pembahasan integrasi Settlement BengkelNet
A87: =IF(INDEX(Syafix!$D:$D, 87)="", NA(), "Syafix (Business Analyst)") -> Syafix (Business Analyst) | B87: =IF(INDEX(Syafix!$D:$D, 87)="", NA(), INDEX(Syafix!$B:$B, 87)) -> Staging Cloud | C87: =IF(INDEX(Syafix!$D:$D, 87)="", NA(), INDEX(Syafix!$D:$D, 87)) -> Mempelajari Alur Process Stagging Cloud | D87: =IF(INDEX(Syafix!$D:$D, 87)="", NA(), INDEX(Syafix!$E:$E, 87)) -> DONE | E87: =IF(INDEX(Syafix!$D:$D, 87)="", NA(), INDEX(Syafix!$K:$K, 87)) -> 46302 | F87: =IF(OR(E87="", ISNA(E87), ISNA(G87)), 0, MAX(1, G87-E87)) -> 5 | G87: =IF(INDEX(Syafix!$D:$D, 87)="", NA(), INDEX(Syafix!$L:$L, 87)) -> 46307 | H87: =IF(ISNA(C87), NA(), A87 & " - " & B87 & " - " & C87) -> Syafix (Business Analyst) - Staging Cloud - Mempelajari Alur Process Stagging Cloud
A88: =IF(INDEX(Syafix!$D:$D, 88)="", NA(), "Syafix (Business Analyst)") -> Syafix (Business Analyst) | B88: =IF(INDEX(Syafix!$D:$D, 88)="", NA(), INDEX(Syafix!$B:$B, 88)) -> API Settlement Payment | C88: =IF(INDEX(Syafix!$D:$D, 88)="", NA(), INDEX(Syafix!$D:$D, 88)) -> Pengecekan input data TCES dengan sejumlah no polis untuk melakukan proses rekonsiliasi secara otomatis dengan scheduler. | D88: =IF(INDEX(Syafix!$D:$D, 88)="", NA(), INDEX(Syafix!$E:$E, 88)) -> DONE | E88: =IF(INDEX(Syafix!$D:$D, 88)="", NA(), INDEX(Syafix!$K:$K, 88)) -> 46302 | F88: =IF(OR(E88="", ISNA(E88), ISNA(G88)), 0, MAX(1, G88-E88)) -> 1 | G88: =IF(INDEX(Syafix!$D:$D, 88)="", NA(), INDEX(Syafix!$L:$L, 88)) -> 46303 | H88: =IF(ISNA(C88), NA(), A88 & " - " & B88 & " - " & C88) -> Syafix (Business Analyst) - API Settlement Payment - Pengecekan input data TCES dengan sejumlah no polis untuk melakukan proses rekonsiliasi secara otomatis dengan scheduler.
A89: =IF(INDEX(Syafix!$D:$D, 89)="", NA(), "Syafix (Business Analyst)") -> Syafix (Business Analyst) | B89: =IF(INDEX(Syafix!$D:$D, 89)="", NA(), INDEX(Syafix!$B:$B, 89)) -> Staging Cloud | C89: =IF(INDEX(Syafix!$D:$D, 89)="", NA(), INDEX(Syafix!$D:$D, 89)) -> Perancangan diagram alur proses staging cloud - master data | D89: =IF(INDEX(Syafix!$D:$D, 89)="", NA(), INDEX(Syafix!$E:$E, 89)) -> DONE | E89: =IF(INDEX(Syafix!$D:$D, 89)="", NA(), INDEX(Syafix!$K:$K, 89)) -> 46303 | F89: =IF(OR(E89="", ISNA(E89), ISNA(G89)), 0, MAX(1, G89-E89)) -> 1 | G89: =IF(INDEX(Syafix!$D:$D, 89)="", NA(), INDEX(Syafix!$L:$L, 89)) -> 46304 | H89: =IF(ISNA(C89), NA(), A89 & " - " & B89 & " - " & C89) -> Syafix (Business Analyst) - Staging Cloud - Perancangan diagram alur proses staging cloud - master data
A90: =IF(INDEX(Syafix!$D:$D, 90)="", NA(), "Syafix (Business Analyst)") -> Syafix (Business Analyst) | B90: =IF(INDEX(Syafix!$D:$D, 90)="", NA(), INDEX(Syafix!$B:$B, 90)) -> Staging Cloud | C90: =IF(INDEX(Syafix!$D:$D, 90)="", NA(), INDEX(Syafix!$D:$D, 90)) -> Perancangan proses validasi data input untuk di proses oleh SAP dari SP ke bentuk service | D90: =IF(INDEX(Syafix!$D:$D, 90)="", NA(), INDEX(Syafix!$E:$E, 90)) -> DONE | E90: =IF(INDEX(Syafix!$D:$D, 90)="", NA(), INDEX(Syafix!$K:$K, 90)) -> 46303 | F90: =IF(OR(E90="", ISNA(E90), ISNA(G90)), 0, MAX(1, G90-E90)) -> 4 | G90: =IF(INDEX(Syafix!$D:$D, 90)="", NA(), INDEX(Syafix!$L:$L, 90)) -> 46307 | H90: =IF(ISNA(C90), NA(), A90 & " - " & B90 & " - " & C90) -> Syafix (Business Analyst) - Staging Cloud - Perancangan proses validasi data input untuk di proses oleh SAP dari SP ke bentuk service
A91: =IF(INDEX(Syafix!$D:$D, 91)="", NA(), "Syafix (Business Analyst)") -> Syafix (Business Analyst) | B91: =IF(INDEX(Syafix!$D:$D, 91)="", NA(), INDEX(Syafix!$B:$B, 91)) -> API Settlement Payment | C91: =IF(INDEX(Syafix!$D:$D, 91)="", NA(), INDEX(Syafix!$D:$D, 91)) -> Pengubahan counter percobaan scheduler API Settlement menjadi 60x yang sebelumnya 84x | D91: =IF(INDEX(Syafix!$D:$D, 91)="", NA(), INDEX(Syafix!$E:$E, 91)) -> DONE | E91: =IF(INDEX(Syafix!$D:$D, 91)="", NA(), INDEX(Syafix!$K:$K, 91)) -> 46304 | F91: =IF(OR(E91="", ISNA(E91), ISNA(G91)), 0, MAX(1, G91-E91)) -> 1 | G91: =IF(INDEX(Syafix!$D:$D, 91)="", NA(), INDEX(Syafix!$L:$L, 91)) -> 46304 | H91: =IF(ISNA(C91), NA(), A91 & " - " & B91 & " - " & C91) -> Syafix (Business Analyst) - API Settlement Payment - Pengubahan counter percobaan scheduler API Settlement menjadi 60x yang sebelumnya 84x
A92: =IF(INDEX(Syafix!$D:$D, 92)="", NA(), "Syafix (Business Analyst)") -> Syafix (Business Analyst) | B92: =IF(INDEX(Syafix!$D:$D, 92)="", NA(), INDEX(Syafix!$B:$B, 92)) -> Integrasi TCES TICS | C92: =IF(INDEX(Syafix!$D:$D, 92)="", NA(), INDEX(Syafix!$D:$D, 92)) -> Restrukturisasi dan merging dokumen BRD API Settlement & API Integration | D92: =IF(INDEX(Syafix!$D:$D, 92)="", NA(), INDEX(Syafix!$E:$E, 92)) -> DONE | E92: =IF(INDEX(Syafix!$D:$D, 92)="", NA(), INDEX(Syafix!$K:$K, 92)) -> 46304 | F92: =IF(OR(E92="", ISNA(E92), ISNA(G92)), 0, MAX(1, G92-E92)) -> 14 | G92: =IF(INDEX(Syafix!$D:$D, 92)="", NA(), INDEX(Syafix!$L:$L, 92)) -> 46318 | H92: =IF(ISNA(C92), NA(), A92 & " - " & B92 & " - " & C92) -> Syafix (Business Analyst) - Integrasi TCES TICS - Restrukturisasi dan merging dokumen BRD API Settlement & API Integration
A93: =IF(INDEX(Syafix!$D:$D, 93)="", NA(), "Syafix (Business Analyst)") -> Syafix (Business Analyst) | B93: =IF(INDEX(Syafix!$D:$D, 93)="", NA(), INDEX(Syafix!$B:$B, 93)) -> Integrasi TCES TICS | C93: =IF(INDEX(Syafix!$D:$D, 93)="", NA(), INDEX(Syafix!$D:$D, 93)) -> Restrukturisasi dan merging dokumen FSD API Settlement & API Integration | D93: =IF(INDEX(Syafix!$D:$D, 93)="", NA(), INDEX(Syafix!$E:$E, 93)) -> DONE | E93: =IF(INDEX(Syafix!$D:$D, 93)="", NA(), INDEX(Syafix!$K:$K, 93)) -> 46304 | F93: =IF(OR(E93="", ISNA(E93), ISNA(G93)), 0, MAX(1, G93-E93)) -> 14 | G93: =IF(INDEX(Syafix!$D:$D, 93)="", NA(), INDEX(Syafix!$L:$L, 93)) -> 46318 | H93: =IF(ISNA(C93), NA(), A93 & " - " & B93 & " - " & C93) -> Syafix (Business Analyst) - Integrasi TCES TICS - Restrukturisasi dan merging dokumen FSD API Settlement & API Integration
A94: =IF(INDEX(Syafix!$D:$D, 94)="", NA(), "Syafix (Business Analyst)") -> Syafix (Business Analyst) | B94: =IF(INDEX(Syafix!$D:$D, 94)="", NA(), INDEX(Syafix!$B:$B, 94)) -> Integrasi TCES TICS | C94: =IF(INDEX(Syafix!$D:$D, 94)="", NA(), INDEX(Syafix!$D:$D, 94)) -> Restrukturisasi dan merging dokumen TSD API Settlement & API Integration | D94: =IF(INDEX(Syafix!$D:$D, 94)="", NA(), INDEX(Syafix!$E:$E, 94)) -> DONE | E94: =IF(INDEX(Syafix!$D:$D, 94)="", NA(), INDEX(Syafix!$K:$K, 94)) -> 46304 | F94: =IF(OR(E94="", ISNA(E94), ISNA(G94)), 0, MAX(1, G94-E94)) -> 14 | G94: =IF(INDEX(Syafix!$D:$D, 94)="", NA(), INDEX(Syafix!$L:$L, 94)) -> 46318 | H94: =IF(ISNA(C94), NA(), A94 & " - " & B94 & " - " & C94) -> Syafix (Business Analyst) - Integrasi TCES TICS - Restrukturisasi dan merging dokumen TSD API Settlement & API Integration
A95: =IF(INDEX(Syafix!$D:$D, 95)="", NA(), "Syafix (Business Analyst)") -> Syafix (Business Analyst) | B95: =IF(INDEX(Syafix!$D:$D, 95)="", NA(), INDEX(Syafix!$B:$B, 95)) -> Staging Cloud | C95: =IF(INDEX(Syafix!$D:$D, 95)="", NA(), INDEX(Syafix!$D:$D, 95)) -> Pembuatan Test Case Staging Cloud | D95: =IF(INDEX(Syafix!$D:$D, 95)="", NA(), INDEX(Syafix!$E:$E, 95)) -> DONE | E95: =IF(INDEX(Syafix!$D:$D, 95)="", NA(), INDEX(Syafix!$K:$K, 95)) -> 46307 | F95: =IF(OR(E95="", ISNA(E95), ISNA(G95)), 0, MAX(1, G95-E95)) -> 2 | G95: =IF(INDEX(Syafix!$D:$D, 95)="", NA(), INDEX(Syafix!$L:$L, 95)) -> 46309 | H95: =IF(ISNA(C95), NA(), A95 & " - " & B95 & " - " & C95) -> Syafix (Business Analyst) - Staging Cloud - Pembuatan Test Case Staging Cloud
A96: =IF(INDEX(Syafix!$D:$D, 96)="", NA(), "Syafix (Business Analyst)") -> Syafix (Business Analyst) | B96: =IF(INDEX(Syafix!$D:$D, 96)="", NA(), INDEX(Syafix!$B:$B, 96)) -> Staging Cloud | C96: =IF(INDEX(Syafix!$D:$D, 96)="", NA(), INDEX(Syafix!$D:$D, 96)) -> Mengkomunikasikan mitirgasi terkait kebutuhan enkripsi antara TICS dengan Staging Cloud | D96: =IF(INDEX(Syafix!$D:$D, 96)="", NA(), INDEX(Syafix!$E:$E, 96)) -> DONE | E96: =IF(INDEX(Syafix!$D:$D, 96)="", NA(), INDEX(Syafix!$K:$K, 96)) -> 46308 | F96: =IF(OR(E96="", ISNA(E96), ISNA(G96)), 0, MAX(1, G96-E96)) -> 3 | G96: =IF(INDEX(Syafix!$D:$D, 96)="", NA(), INDEX(Syafix!$L:$L, 96)) -> 46311 | H96: =IF(ISNA(C96), NA(), A96 & " - " & B96 & " - " & C96) -> Syafix (Business Analyst) - Staging Cloud - Mengkomunikasikan mitirgasi terkait kebutuhan enkripsi antara TICS dengan Staging Cloud
A97: =IF(INDEX(Syafix!$D:$D, 97)="", NA(), "Syafix (Business Analyst)") -> Syafix (Business Analyst) | B97: =IF(INDEX(Syafix!$D:$D, 97)="", NA(), INDEX(Syafix!$B:$B, 97)) -> Staging Cloud | C97: =IF(INDEX(Syafix!$D:$D, 97)="", NA(), INDEX(Syafix!$D:$D, 97)) -> Validasi pengecekan alur proses data testing untuk Staging Cloud dengan dev dan tim internal terkait | D97: =IF(INDEX(Syafix!$D:$D, 97)="", NA(), INDEX(Syafix!$E:$E, 97)) -> DONE | E97: =IF(INDEX(Syafix!$D:$D, 97)="", NA(), INDEX(Syafix!$K:$K, 97)) -> 46309 | F97: =IF(OR(E97="", ISNA(E97), ISNA(G97)), 0, MAX(1, G97-E97)) -> 2 | G97: =IF(INDEX(Syafix!$D:$D, 97)="", NA(), INDEX(Syafix!$L:$L, 97)) -> 46311 | H97: =IF(ISNA(C97), NA(), A97 & " - " & B97 & " - " & C97) -> Syafix (Business Analyst) - Staging Cloud - Validasi pengecekan alur proses data testing untuk Staging Cloud dengan dev dan tim internal terkait
A98: =IF(INDEX(Syafix!$D:$D, 98)="", NA(), "Syafix (Business Analyst)") -> Syafix (Business Analyst) | B98: =IF(INDEX(Syafix!$D:$D, 98)="", NA(), INDEX(Syafix!$B:$B, 98)) -> Staging Cloud | C98: =IF(INDEX(Syafix!$D:$D, 98)="", NA(), INDEX(Syafix!$D:$D, 98)) -> Finalisasi Diagram Arsitektur Staging Cloud | D98: =IF(INDEX(Syafix!$D:$D, 98)="", NA(), INDEX(Syafix!$E:$E, 98)) -> DONE | E98: =IF(INDEX(Syafix!$D:$D, 98)="", NA(), INDEX(Syafix!$K:$K, 98)) -> 46309 | F98: =IF(OR(E98="", ISNA(E98), ISNA(G98)), 0, MAX(1, G98-E98)) -> 2 | G98: =IF(INDEX(Syafix!$D:$D, 98)="", NA(), INDEX(Syafix!$L:$L, 98)) -> 46311 | H98: =IF(ISNA(C98), NA(), A98 & " - " & B98 & " - " & C98) -> Syafix (Business Analyst) - Staging Cloud - Finalisasi Diagram Arsitektur Staging Cloud
A99: =IF(INDEX(Syafix!$D:$D, 99)="", NA(), "Syafix (Business Analyst)") -> Syafix (Business Analyst) | B99: =IF(INDEX(Syafix!$D:$D, 99)="", NA(), INDEX(Syafix!$B:$B, 99)) -> Staging Cloud | C99: =IF(INDEX(Syafix!$D:$D, 99)="", NA(), INDEX(Syafix!$D:$D, 99)) -> Persiapan Pembuatan BRD dan dokumen FSD, TSD Staging Cloud | D99: =IF(INDEX(Syafix!$D:$D, 99)="", NA(), INDEX(Syafix!$E:$E, 99)) -> DONE | E99: =IF(INDEX(Syafix!$D:$D, 99)="", NA(), INDEX(Syafix!$K:$K, 99)) -> 46310 | F99: =IF(OR(E99="", ISNA(E99), ISNA(G99)), 0, MAX(1, G99-E99)) -> 1 | G99: =IF(INDEX(Syafix!$D:$D, 99)="", NA(), INDEX(Syafix!$L:$L, 99)) -> 46311 | H99: =IF(ISNA(C99), NA(), A99 & " - " & B99 & " - " & C99) -> Syafix (Business Analyst) - Staging Cloud - Persiapan Pembuatan BRD dan dokumen FSD, TSD Staging Cloud
A100: =IF(INDEX(Syafix!$D:$D, 100)="", NA(), "Syafix (Business Analyst)") -> Syafix (Business Analyst) | B100: =IF(INDEX(Syafix!$D:$D, 100)="", NA(), INDEX(Syafix!$B:$B, 100)) -> Staging Cloud | C100: =IF(INDEX(Syafix!$D:$D, 100)="", NA(), INDEX(Syafix!$D:$D, 100)) -> Implementasi Kafka UI di SC - Outbound | D100: =IF(INDEX(Syafix!$D:$D, 100)="", NA(), INDEX(Syafix!$E:$E, 100)) -> Done | E100: =IF(INDEX(Syafix!$D:$D, 100)="", NA(), INDEX(Syafix!$K:$K, 100)) -> 46311 | F100: =IF(OR(E100="", ISNA(E100), ISNA(G100)), 0, MAX(1, G100-E100)) -> 3 | G100: =IF(INDEX(Syafix!$D:$D, 100)="", NA(), INDEX(Syafix!$L:$L, 100)) -> 46314 | H100: =IF(ISNA(C100), NA(), A100 & " - " & B100 & " - " & C100) -> Syafix (Business Analyst) - Staging Cloud - Implementasi Kafka UI di SC - Outbound
...

Sheet Syafix
A1: No. | B1: project_name | C1: requirement_code | D1: title | E1: status | F1: priority | G1: jenis_task | H1: module_name | I1: bug_type | J1: progress | K1: start_date | L1: due_date | M1: completed_date | N1: developer_emails | O1: ba_emails | P1: infra_emails | Q1: master_data_emails | R1: tester_emails | S1: technical_writer_emails | T1: quality_assurance_emails | U1: system_analyst_emails | V1: kendala | W1: solusi | X1: evidence | Y1: kode_task | Z1: Milestone
B2: Pengembangan Mass Product Retail | D2: Checking & Testing Product, Scheming & premium class TICS vs Mass Product | E2: DONE | F2: MEDIUM | G2: NEW_APPLICATION | H2: Policy Automation | J2: 1 | K2: 46238 | L2: 46240 | M2: 46240 | O2: syafix.said@elistec.com | R2: mohammad.danang@elistec.com | V2: Kendala awal | W2: Rencana solusi awal
A3: =IF(OR(D3<>"", B3<>""), ROW()-1, "") -> 2 | B3: Integrasi TCES TICS | D3: perancangan solusi integrasi TCES - TCIS | E3: DONE | F3: HIGH | G3: NEW_APPLICATION | H3: TCES | J3: 1 | K3: 46239 | L3: 46239 | M3: 46239 | N3: haviz.indra@elistec.com | O3: syafix.said@elistec.com | S3: athallah.bariq@elistec.com | T3: mohammad.danang@elistec.com | V3: menunggu akses ke database, repository, dan environment | W3: Perancangan awal pengambilan data JSON, pembagian struktur data, validasi, pengiriman ke TICS https://tugu.sharepoint.com/:i:/r/sites/TUGUFILESHARING/Documents/IT/External%20Share/2026%20Manage%20Service%20Elistec/API%20Integration/3.%20Document/Supporting%20Data/API%20Integration%20-%20Overview%20Diagram-Architectured%20Diagram.drawio.png?d=w1e84c5e313ff44cc82a1b73bb6607700&csf=1&web=1&e=6PYf4I
A4: =IF(OR(D4<>"", B4<>""), ROW()-1, "") -> 3 | B4: Integrasi TCES TICS | D4: Mendefinisikan Tugas API Endpoint (BA), Membuat Diagram Flow API Integration (BA) | E4: DONE | F4: MEDIUM | G4: ENHANCEMENT | H4: TCES | J4: 1 | K4: 46240 | L4: 46240 | M4: 46240 | N4: haviz.indra@elistec.com | O4: syafix.said@elistec.com | S4: athallah.bariq@elistec.com | T4: mohammad.danang@elistec.com | V4: Membutuhkan akses | W4: Mendapatkan akses untuk mengecek endpoint https://appsdev.tugu.com/tics-mv-api/api/documentation#/TICS%20Transaction%20v2/50bcb787c24c768949e32cbc51387ee7
A5: =IF(OR(D5<>"", B5<>""), ROW()-1, "") -> 4 | B5: Pengembangan Mass Product Retail | D5: Pengujian Penggunaan Product, Scheming, Premium Class di Aplikasi Mass Product | E5: DONE | F5: MEDIUM | G5: NEW_APPLICATION | H5: Policy Automation | J5: 1 | K5: 46240 | L5: 46246 | M5: 46246 | O5: syafix.said@elistec.com | R5: mohammad.danang@elistec.com | V5: Kebutuhan pengecekan data produk antara TICS dengan Mass Product | W5: Pembuatan product dari mass product dan di sesuaikan dengan kebutuhan TICS
A6: =IF(OR(D6<>"", B6<>""), ROW()-1, "") -> 5 | B6: Integrasi TCES TICS | D6: Membuat Diagram HLD dan LLD API Integration | E6: DONE | F6: MEDIUM | G6: NEW_APPLICATION | H6: TCES | J6: 1 | K6: 46241 | L6: 46246 | M6: 46246 | N6: haviz.indra@elistec.com | O6: syafix.said@elistec.com | S6: athallah.bariq@elistec.com | T6: mohammad.danang@elistec.com | V6: Kebutuhan meeting dengan tim vendor untuk gambaran overview dan teknis flow process | W6: Telah di lakukan permintaan meeting offline dengan tim vendor pada hari senin siang. Pmebuatan diagram telah selesai
A7: =IF(OR(D7<>"", B7<>""), ROW()-1, "") -> 6 | B7: Integrasi TCES TICS | D7: Membuat QA Tracker untuk kebutuhan pengujian testing API integration | E7: DONE | F7: MEDIUM | G7: NEW_APPLICATION | H7: TCES | J7: 1 | K7: 46241 | L7: 46246 | M7: 46246 | N7: haviz.indra@elistec.com | O7: syafix.said@elistec.com | S7: athallah.bariq@elistec.com | T7: mohammad.danang@elistec.com | V7: Pembuatan TC akan berkoordinasi dengan tim QA untuk pemetaan keseluruhan pengujian akan membutuhkan informasi dari tim vendor terkait flow process nya | W7: Telah di lakukan permintaan meeting offline dengan tim vendor pada hari senin siang
A8: =IF(OR(D8<>"", B8<>""), ROW()-1, "") -> 7 | B8: Integrasi TCES TICS | D8: Meeting Pembahasan Alur Proses API Integration, Pembahasan Teknis, Informasi Pengujian Aplikasi | E8: DONE | F8: MEDIUM | G8: NEW_APPLICATION | H8: TCES | J8: 1 | K8: 46244 | L8: 46244 | M8: 46244 | N8: haviz.indra@elistec.com | O8: syafix.said@elistec.com | S8: athallah.bariq@elistec.com | T8: mohammad.danang@elistec.com | W8: Pembahasan teknis untuk proses endpoint dan alur proses keseluruhan API Integration : https://appsdev.tugu.com/tics-mv-api/api/documentation#/TICS%20Transaction%20v2/50bcb787c24c768949e32cbc51387ee7
A9: =IF(OR(D9<>"", B9<>""), ROW()-1, "") -> 8 | B9: Integrasi TCES TICS | D9: Pembuatan Dokumen TSD - Membuat Diagram Arsitektur Flow API Integration (BA) | E9: DONE | F9: MEDIUM | G9: ENHANCEMENT | H9: TCES | J9: 1 | K9: 46244 | L9: 46248 | M9: 46248 | N9: haviz.indra@elistec.com | O9: syafix.said@elistec.com | S9: athallah.bariq@elistec.com | T9: mohammad.danang@elistec.com | V9: Membutuhkan akses | W9: Mendapatkan akses untuk mengecek endpoint
A10: =IF(OR(D10<>"", B10<>""), ROW()-1, "") -> 9 | B10: Integrasi TCES TICS | D10: Pembuatan Template Dokumen FSD | E10: DONE | F10: MEDIUM | G10: ENHANCEMENT | H10: TCES | J10: 1 | K10: 46244 | L10: 46248 | M10: 46248 | N10: haviz.indra@elistec.com | O10: syafix.said@elistec.com | S10: athallah.bariq@elistec.com | T10: mohammad.danang@elistec.com | W10: dokumen pada link berikut : https://tugu.sharepoint.com/:w:/r/sites/TUGUFILESHARING/_layouts/15/Doc.aspx?sourcedoc=%7BA0EE9E32-7BFD-467A-9DBB-3BE526AF199C%7D&file=Draft%20Update%20-%20FSD.docx&action=default&mobileredirect=true
A11: =IF(OR(D11<>"", B11<>""), ROW()-1, "") -> 10 | B11: Integrasi TCES TICS | D11: Pembuatan Template Dokumen TSD | E11: DONE | F11: MEDIUM | G11: ENHANCEMENT | H11: TCES | J11: 1 | K11: 46244 | L11: 46248 | M11: 46248 | N11: haviz.indra@elistec.com | O11: syafix.said@elistec.com | S11: athallah.bariq@elistec.com | T11: mohammad.danang@elistec.com | W11: https://tugu.sharepoint.com/:w:/r/sites/TUGUFILESHARING/Documents/IT/External%20Share/2026%20Manage%20Service%20Elistec/API%20Integration/3.%20Document/FSD/Draft%20Update%20-%20FSD.docx?d=wa917d2afb98d4c3183414e3215d95dac&csf=1&web=1&e=wEFSN6
A12: =IF(OR(D12<>"", B12<>""), ROW()-1, "") -> 11 | B12: Integrasi TCES TICS | D12: Training TCES dan flow sistem aplikasi | E12: DONE | F12: MEDIUM | G12: MAINTENANCE | H12: TCES | J12: 1 | K12: 46245 | L12: 46245 | M12: 46245 | N12: haviz.indra@elistec.com | O12: syafix.said@elistec.com | S12: athallah.bariq@elistec.com | T12: mohammad.danang@elistec.com | W12: penjelasan detail aplikasi TCES oleh mas Egy. Untuk catatan meeting dengan mas Atha
A13: =IF(OR(D13<>"", B13<>""), ROW()-1, "") -> 12 | B13: Integrasi TCES TICS | D13: Akses ke database TICS | E13: DONE | F13: CRITICAL | G13: ENHANCEMENT | H13: TCES | J13: 1 | K13: 46246 | L13: 46248 | M13: 46248 | N13: haviz.indra@elistec.com | O13: syafix.said@elistec.com | S13: athallah.bariq@elistec.com | T13: mohammad.danang@elistec.com | V13: belum dapat terkoneksi ke database, terdapat masalah pada windows / driver | W13: perlu pengecekan ke tim dev yang sukses koneksi ke database posgress : https://tugu.sharepoint.com/:i:/r/sites/TUGUFILESHARING/Documents/IT/External%20Share/2026%20Manage%20Service%20Elistec/API%20Integration/3.%20Document/Supporting%20Data/Database%20-%20Access%20TICS%20untuk%20API%20Integration.png?d=w720062a542a64700b98d4562231fe932&csf=1&web=1&e=ULdtV3
A14: =IF(OR(D14<>"", B14<>""), ROW()-1, "") -> 13 | B14: Pengembangan Mass Product Retail | D14: Pencarian bugs atau kendala dari pembuatan polis asuransi hingga claim asuransi | E14: DONE | F14: MEDIUM | G14: NEW_APPLICATION | H14: Policy Automation | J14: 1 | K14: 46247 | L14: 46252 | M14: 46252 | O14: syafix.said@elistec.com | R14: mohammad.danang@elistec.com | W14: Percobaan dari pembautan product dan klaim asuransi berhasil, namun memerlukan skala lebih kecil agar lebih dapat di tracing
A15: =IF(OR(D15<>"", B15<>""), ROW()-1, "") -> 14 | B15: Integrasi TCES TICS | D15: Pembuatan Dokumen FSD - Membuat diagram arsitektur API Integration | E15: DONE | F15: MEDIUM | G15: ENHANCEMENT | H15: TCES | J15: 1 | K15: 46248 | L15: 46248 | M15: 46248 | N15: haviz.indra@elistec.com | O15: syafix.said@elistec.com | S15: athallah.bariq@elistec.com | T15: mohammad.danang@elistec.com | W15: Pembuatan diagram arsitektur selesai dan telah di share pada folder dokumen Link : https://tugu.sharepoint.com/:f:/r/sites/TUGUFILESHARING/Documents/IT/External%20Share/2026%20Manage%20Service%20Elistec/API%20Integration/3.%20Document/Supporting%20Data?d=wd5b4e9c0d69b42f0a10270cfabdbe03a&csf=1&web=1&e=96mrdg
A16: =IF(OR(D16<>"", B16<>""), ROW()-1, "") -> 15 | B16: Integrasi TCES TICS | D16: Pembuatan Dokumen FSD - Penambahan Penjelasan User Flow Diagram | E16: DONE | F16: MEDIUM | G16: ENHANCEMENT | H16: TCES | J16: 1 | K16: 46248 | L16: 46252 | M16: 46252 | N16: haviz.indra@elistec.com | O16: syafix.said@elistec.com | S16: athallah.bariq@elistec.com | T16: mohammad.danang@elistec.com | W16: Penambahan informasi alur flow diagram API Integration beserta penjelasannya Link : https://tugu.sharepoint.com/:f:/r/sites/TUGUFILESHARING/Documents/IT/External%20Share/2026%20Manage%20Service%20Elistec/API%20Integration/3.%20Document/FSD?d=wf9d56180a2a049ea8c4d830dca7145dc&csf=1&web=1&e=ej4DZu
A17: =IF(OR(D17<>"", B17<>""), ROW()-1, "") -> 16 | B17: Integrasi TCES TICS | D17: Pembuatan Draft BRD | E17: DONE | F17: HIGH | G17: ENHANCEMENT | H17: TCES | J17: 1 | K17: 46248 | L17: 46252 | M17: 46252 | N17: haviz.indra@elistec.com | O17: syafix.said@elistec.com | S17: athallah.bariq@elistec.com | T17: mohammad.danang@elistec.com | W17: Pembuatan BRD pada ARMS telah dilakukan, diperlukan komunikasi dengan tim BA internal untuk review dari pembuatan dokumen BRD tersebut
A18: =IF(OR(D18<>"", B18<>""), ROW()-1, "") -> 17 | B18: Integrasi TCES TICS | D18: Gathering database schema dan pendokumentasian | E18: DONE | F18: MEDIUM | G18: ENHANCEMENT | H18: TCES | J18: 1 | K18: 46248 | L18: 46253 | M18: 46249 | N18: haviz.indra@elistec.com | O18: syafix.said@elistec.com | S18: athallah.bariq@elistec.com | T18: mohammad.danang@elistec.com | V18: menunggu table object jsonb dari mas rian untuk keseuaian dengan mass product | W18: telah mendapatkan informasi skema database dan table yang digunakan untuk melakukan penyimpanan informasi payload TCES ke TICS - Done https://tugu.sharepoint.com/:i:/r/sites/TUGUFILESHARING/Documents/IT/External%20Share/2026%20Manage%20Service%20Elistec/API%20Integration/3.%20Document/Supporting%20Data/API%20Integration%20-%20Overview%20Diagram-Database%20Flow%20Process.drawio.png?d=w5c6ac1a30bbe4fef85e031c2dddc0ff6&csf=1&web=1&e=HvLxGL
A19: =IF(OR(D19<>"", B19<>""), ROW()-1, "") -> 18 | B19: Integrasi TCES TICS | D19: Diskusi dengan tim IT Infra dan IT App untuk kebutuhan permohonan penggunaan docker pada API Integration | E19: DONE | F19: HIGH | G19: ENHANCEMENT | H19: TCES | J19: 1 | K19: 46248 | L19: 46253 | M19: 46253 | N19: haviz.indra@elistec.com | O19: syafix.said@elistec.com | S19: athallah.bariq@elistec.com | T19: mohammad.danang@elistec.com | V19: Sehubungan dengan code integrasi yang sedang di develop oleh tim DEV sudah selesai, maka diperlukan metode deploy ke dalam server dev / uat untuk dilakukan pengetesan pada selasa depan. untuk metode yang digunakan masih bersifat tradisional dan mencoba permohonan penggunaan docker sebagai techtag pengembangan project | W19: informasi dari mas Rian, sehubungan saat ini api integration tidak menggunakan docker dan di code langsung dari CI/CD ke server, maka penggunaan docker akan menjadi tentaive dan akan di bahas lagi nanti
A20: =IF(OR(D20<>"", B20<>""), ROW()-1, "") -> 19 | B20: Pengembangan Mass Product Retail | D20: Pengujian pembuatan master product baru, scheme baru, polis baru, declaration baru, dan proses claim baru, dengan nama product terbaru adalah TPACC | E20: DONE | F20: MEDIUM | G20: NEW_APPLICATION | H20: Policy Automation | J20: 1 | K20: 46252 | L20: 46254 | M20: 46254 | O20: syafix.said@elistec.com | R20: mohammad.danang@elistec.com | W20: Pembuatan product baru khusus untuk skala kecil untuk pengujian proses end-to-end mass product
A21: =IF(OR(D21<>"", B21<>""), ROW()-1, "") -> 20 | B21: Integrasi TCES TICS | D21: Update Draft BRD | E21: DONE | F21: HIGH | G21: ENHANCEMENT | H21: TCES | J21: 1 | K21: 46252 | L21: 46276 | M21: 46276 | N21: haviz.indra@elistec.com | O21: syafix.said@elistec.com | S21: athallah.bariq@elistec.com | T21: mohammad.danang@elistec.com | V21: Review pembuatan BRD di setujui dan memerlukan update dari sisi offline | W21: Update sedang in progress dengan penambahan informasi yang di gather dari tim infra, support, dan development. Link : https://intraapps.tugu.com/approval-center/brd/11 Dokumen telah di submit ke ARMS dan sedang dalam review DH dan GHIT
A22: =IF(OR(D22<>"", B22<>""), ROW()-1, "") -> 21 | B22: Integrasi TCES TICS | D22: Pembuatan data payload test API Integration sebanyak 1000 buah untuk pengujian performance test | E22: DONE | F22: HIGH | G22: ENHANCEMENT | H22: TCES | J22: 1 | K22: 46254 | L22: 46254 | M22: 46254 | N22: haviz.indra@elistec.com | O22: syafix.said@elistec.com | S22: athallah.bariq@elistec.com | T22: mohammad.danang@elistec.com | W22: Pembentukan data sampling payload untuk performance test berhasil. Link : https://tugu.sharepoint.com/:t:/r/sites/TUGUFILESHARING/Documents/IT/External%20Share/2026%20Manage%20Service%20Elistec/API%20Integration/3.%20Document/Supporting%20Data/Payload%20Pengujian%20-%20Masuk%20TICS.txt?d=w687437cca59a4dcab467c4e56c0b0792&csf=1&web=1&e=b8MQT8
A23: =IF(OR(D23<>"", B23<>""), ROW()-1, "") -> 22 | B23: Integrasi TCES TICS | D23: Meeting Product Mapping TProperty dengn mas julyan dan mas fergy | E23: DONE | F23: CRITICAL | G23: ENHANCEMENT | H23: TCES | J23: 1 | K23: 46254 | L23: 46254 | M23: 46254 | N23: haviz.indra@elistec.com | O23: syafix.said@elistec.com | S23: athallah.bariq@elistec.com | T23: mohammad.danang@elistec.com | V23: Meeting pembahasan product TProperty / non MV masih terdapat ketidaksesuaian data product dengan data premium class, sehingga perlu diperjelas mapping antara TStore dengan THome, jenis All Risk dengan non All Risk, Property Only atau Property dan Content | W23: Mas Jul dan mas Egy sedang melakukan pengecekan object ref code untuk TProperty dengan jenis product Basic, Max, Basic+
A24: =IF(OR(D24<>"", B24<>""), ROW()-1, "") -> 23 | B24: Integrasi TCES TICS | D24: Membantu QA melakukan proses pengujian Stress Test dan Performance Test | E24: DONE | F24: HIGH | G24: ENHANCEMENT | H24: TCES | J24: 1 | K24: 46254 | L24: 46255 | M24: 46255 | N24: haviz.indra@elistec.com | O24: syafix.said@elistec.com | S24: athallah.bariq@elistec.com | T24: mohammad.danang@elistec.com | W24: Pembentukan TC untuk pengujian API Integration berhasil di lakukan dan di update pada file berikut : https://tugu.sharepoint.com/:x:/r/sites/TUGUFILESHARING/Documents/IT/External%20Share/2026%20Manage%20Service%20Elistec/API%20Integration/5.%20Testing/SIT/QA_API_Endpoint_Integration_Tracker%20-%20Updated.xlsx?d=w87365ae29a1e4c53b9ef5beef22dfa62&csf=1&web=1&e=XtAaI4
A25: =IF(OR(D25<>"", B25<>""), ROW()-1, "") -> 24 | B25: Integrasi TCES TICS | D25: Pengecekan hasil QA Testing dengan value yang berada pada sistem TCES untuk memastikan kesesuaian dengan TICS | E25: DONE | F25: CRITICAL | G25: ENHANCEMENT | H25: TCES | J25: 1 | K25: 46255 | L25: 46262 | M25: 46262 | N25: haviz.indra@elistec.com | O25: syafix.said@elistec.com | S25: athallah.bariq@elistec.com | T25: mohammad.danang@elistec.com | V25: Terdapat kendala yaitu : 1. Data TCES TRide masuk ke API Integration & berhasil mendapatkan BP dummy dan masuk ke acceptance. namun di TICS g muncul, baik di TICS UAT / TICS Retail UAT (Rian) 2. Data TProperty untuk product Max tidak dapat masuk, karena object ref code tidak ada. sesuai dengan info detail product belum clear oleh tim product (Juliyan) 3. Data Travela tidak terkirim dari TCES. tim project Elistec belum integrasikan enkripsi dll untuk API Integration (Rifqi)
A26: =IF(OR(D26<>"", B26<>""), ROW()-1, "") -> 25 | B26: Integrasi TCES TICS | D26: Pengecekan Ulang Endpoint API Integration sebelum melakukan testing | E26: DONE | F26: HIGH | G26: ENHANCEMENT | H26: TCES | J26: 1 | K26: 46258 | L26: 46258 | M26: 46258 | N26: haviz.indra@elistec.com | O26: syafix.said@elistec.com | S26: athallah.bariq@elistec.com | T26: mohammad.danang@elistec.com | W26: Update sedang in progress dengan penambahan informasi yang di gather dari tim infra, support, dan development terdapat update terbaru dari tim dev untuk menyelaraskan field yang kosong antara TCES dengan API Integration Pembahasan dengan tim elistec (mas Rifqi) untuk informasi kolom yang kosong untuk kebutuhan informasi yang akan di kirimkan dari TCES ke TICS
A27: =IF(OR(D27<>"", B27<>""), ROW()-1, "") -> 26 | B27: Integrasi TCES TICS | D27: Melakukan meeting terkait progress review task yang sudah dikerjakan bersama tim dan stakeholder | E27: DONE | F27: HIGH | G27: ENHANCEMENT | H27: TCES | J27: 1 | K27: 46258 | L27: 46258 | M27: 46258 | N27: haviz.indra@elistec.com | O27: syafix.said@elistec.com | S27: athallah.bariq@elistec.com | T27: mohammad.danang@elistec.com | W27: Meeting Weekly Update Progress, Meeting pembahasan strategi pengembangan API Integrasi dan Strategi Testing (SIT). catatan dengan mas Atha
A28: =IF(OR(D28<>"", B28<>""), ROW()-1, "") -> 27 | B28: Integrasi TCES TICS | D28: Membuat Data Order TCES untuk kebutuhan pengetesan end-to-end ke TICS | E28: DONE | F28: HIGH | G28: ENHANCEMENT | H28: TCES | J28: 1 | K28: 46258 | L28: 46260 | M28: 46260 | N28: haviz.indra@elistec.com | O28: syafix.said@elistec.com | S28: athallah.bariq@elistec.com | T28: mohammad.danang@elistec.com | W28: Update tambahan pada file berikut : https://tugu.sharepoint.com/:x:/r/sites/TUGUFILESHARING/Documents/IT/External%20Share/2026%20Manage%20Service%20Elistec/API%20Integration/5.%20Testing/SIT/QA_API_Endpoint_Integration_Tracker%20-%20Updated.xlsx?d=w87365ae29a1e4c53b9ef5beef22dfa62&csf=1&web=1&e=XtAaI4"
A29: =IF(OR(D29<>"", B29<>""), ROW()-1, "") -> 28 | B29: Integrasi TCES TICS | D29: Membuat data Payload untuk pengujian Travela dan TFire | E29: DONE | F29: HIGH | G29: ENHANCEMENT | H29: TCES | J29: 1 | K29: 46260 | L29: 46261 | M29: 46261 | N29: haviz.indra@elistec.com | O29: syafix.said@elistec.com | S29: athallah.bariq@elistec.com | T29: mohammad.danang@elistec.com | W29: Payload di buat pada link berikut : https://tugu.sharepoint.com/:t:/r/sites/TUGUFILESHARING/Documents/IT/External%20Share/2026%20Manage%20Service%20Elistec/API%20Integration/5.%20Testing/SIT/Pengujian%20Data%20TProperty%20(3%20Sept%202026)/Payload%20Sample%20Testing%20TFire%20-%20TProperty.txt?d=w1b4006f8664f40719485f5be0bdd9cb7&csf=1&web=1&e=T7ye88
A30: =IF(OR(D30<>"", B30<>""), ROW()-1, "") -> 29 | B30: Pengembangan Mass Product Retail | D30: Pengetesan master data region untuk pencocokan data polis dengan region BP | E30: TODO | F30: HIGH | G30: NEW_APPLICATION | H30: Policy Automation | J30: 0 | K30: 46260 | L30: 46262 | M30: 46262 | O30: syafix.said@elistec.com | R30: mohammad.danang@elistec.com | V30: saat ini sedang difokuskan ke Integrasi TCES TICS
A31: =IF(OR(D31<>"", B31<>""), ROW()-1, "") -> 30 | B31: Integrasi TCES TICS | D31: Membuat test case untuk end-to-end TCES untuk produk Tride dan execute testing sampai terbentuk polis number (BA) | E31: DONE | F31: HIGH | G31: ENHANCEMENT | H31: TCES | J31: 1 | K31: 46261 | L31: 46261 | M31: 46261 | N31: haviz.indra@elistec.com | O31: syafix.said@elistec.com | S31: athallah.bariq@elistec.com | T31: mohammad.danang@elistec.com | W31: Update tambahan pada file berikut : https://tugu.sharepoint.com/:x:/r/sites/TUGUFILESHARING/Documents/IT/External%20Share/2026%20Manage%20Service%20Elistec/API%20Integration/5.%20Testing/SIT/QA_API_Endpoint_Integration_Tracker%20-%20Updated.xlsx?d=w87365ae29a1e4c53b9ef5beef22dfa62&csf=1&web=1&e=XtAaI4"
A32: =IF(OR(D32<>"", B32<>""), ROW()-1, "") -> 31 | B32: Integrasi TCES TICS | D32: Mencari temuan hasil pengecekan input TCES ke TICS via API Integration (T-Ride) | E32: DONE | F32: CRITICAL | G32: ENHANCEMENT | H32: TCES | J32: 1 | K32: 46262 | L32: 46262 | M32: 46262 | N32: haviz.indra@elistec.com | O32: syafix.said@elistec.com | S32: athallah.bariq@elistec.com | T32: mohammad.danang@elistec.com | V32: Terdapat temuan ketidakcocokan data untuk Correspondent dan Producer ID, sedang di info kan ke mas Rian
A33: =IF(OR(D33<>"", B33<>""), ROW()-1, "") -> 32 | B33: Integrasi TCES TICS | D33: Pembuatan Sequence Diagram untuk flow end-to-end API Integration | E33: DONE | F33: HIGH | G33: ENHANCEMENT | H33: TCES | J33: 1 | K33: 46262 | L33: 46262 | M33: 46262 | N33: haviz.indra@elistec.com | O33: syafix.said@elistec.com | S33: athallah.bariq@elistec.com | T33: mohammad.danang@elistec.com | W33: Sequence diagram tersedia pada link
A34: =IF(OR(D34<>"", B34<>""), ROW()-1, "") -> 33 | B34: Integrasi TCES TICS | D34: Pembuatan timesheet elistec | E34: DONE | F34: MEDIUM | G34: ENHANCEMENT | H34: TCES | J34: 1 | K34: 46265 | L34: 46265 | M34: 46265 | N34: haviz.indra@elistec.com | O34: syafix.said@elistec.com | S34: athallah.bariq@elistec.com | T34: mohammad.danang@elistec.com | V34: Timesheet membutuhkan format sesuai dengan elistec dan sedang dalam pembahasan submit timesheet | W34: Timesheet telah di buat dan selesai
A35: =IF(OR(D35<>"", B35<>""), ROW()-1, "") -> 34 | B35: Integrasi TCES TICS | D35: Pembuatan Data Travel dengan QA dan pengujian pada environment DEV | E35: DONE | F35: HIGH | G35: ENHANCEMENT | H35: TCES | J35: 1 | K35: 46265 | L35: 46266 | M35: 46266 | N35: haviz.indra@elistec.com | O35: syafix.said@elistec.com | S35: athallah.bariq@elistec.com | T35: mohammad.danang@elistec.com | W35: Data berhasil masuk dengan beberapa sample yang di buat dan dalam pengecekan oleh DEV terkait integrasi dengan TICS
A36: =IF(OR(D36<>"", B36<>""), ROW()-1, "") -> 35 | B36: Integrasi TCES TICS | D36: Pengujian TRide 4 Roda, end-to-end dari TCES hingga SAP | E36: DONE | F36: CRITICAL | G36: ENHANCEMENT | H36: TCES | J36: 1 | K36: 46266 | L36: 46266 | M36: 46266 | N36: haviz.indra@elistec.com | O36: syafix.said@elistec.com | S36: athallah.bariq@elistec.com | T36: mohammad.danang@elistec.com | V36: Data telah masuk ke TICS, menggunakan BP yang tersedia dan tidak tersedia. untuk pengujian dengan kendaraan bekas belum dapat dilakukan karena integrasi pada aplikasi sedang mati. kendala yang di dapatkan dari TICS : Kendala sudah di put pada file summary | W36: Pembuatan data pengujian TCES selesai, ada pada link berikut : https://tugu.sharepoint.com/:f:/r/sites/TUGUFILESHARING/Documents/IT/External%20Share/2026%20Manage%20Service%20Elistec/API%20Integration/5.%20Testing/SIT/Pengujian%20Data%20TDrive%20(1%20Sept%202026)?d=w518951b3aafd41d5831983d7b22bf629&csf=1&web=1&e=wdW3fP
A37: =IF(OR(D37<>"", B37<>""), ROW()-1, "") -> 36 | B37: Integrasi TCES TICS | D37: Melakukan Pengujian Perbaikan dari TDrive pada tanggal 1/9/2026 atau pada no row 31 | E37: DONE | F37: CRITICAL | G37: ENHANCEMENT | H37: TCES | J37: 1 | K37: 46267 | L37: 46267 | M37: 46267 | N37: haviz.indra@elistec.com | O37: syafix.said@elistec.com | S37: athallah.bariq@elistec.com | T37: mohammad.danang@elistec.com
A38: =IF(OR(D38<>"", B38<>""), ROW()-1, "") -> 37 | B38: Integrasi TCES TICS | D38: Membuat Test Case untuk pengujian end-to-end Travela | E38: DONE | F38: CRITICAL | G38: ENHANCEMENT | H38: TCES | J38: 1 | K38: 46267 | L38: 46267 | M38: 46267 | N38: haviz.indra@elistec.com | O38: syafix.said@elistec.com | S38: athallah.bariq@elistec.com | T38: mohammad.danang@elistec.com
A39: =IF(OR(D39<>"", B39<>""), ROW()-1, "") -> 38 | B39: Integrasi TCES TICS | D39: Membuat Matrix Pengujian Data TFire bersama QA dan TW | E39: DONE | F39: CRITICAL | G39: ENHANCEMENT | H39: TCES | J39: 1 | K39: 46268 | L39: 46268 | M39: 46268 | N39: haviz.indra@elistec.com | O39: syafix.said@elistec.com | S39: athallah.bariq@elistec.com | T39: mohammad.danang@elistec.com
A40: =IF(OR(D40<>"", B40<>""), ROW()-1, "") -> 39 | B40: Integrasi TCES TICS | D40: Membuat Summary Pengujian TFire u/ Tanggal 3 Sept | E40: DONE | F40: CRITICAL | G40: ENHANCEMENT | H40: TCES | J40: 1 | K40: 46268 | L40: 46268 | M40: 46268 | N40: haviz.indra@elistec.com | O40: syafix.said@elistec.com | S40: athallah.bariq@elistec.com | T40: mohammad.danang@elistec.com | W40: File summary telah di buat, link ke file : https://tugu.sharepoint.com/:w:/r/sites/TUGUFILESHARING/Documents/IT/External%20Share/2026%20Manage%20Service%20Elistec/API%20Integration/5.%20Testing/SIT/Pengujian%20Data%20TProperty%20(3%20Sept%202026)/Summary%20-%2003%20September%202026.docx?d=wc65a2cd45ec84dce8fb8242dc2f09c2c&csf=1&web=1&e=Sz1tfL
A41: =IF(OR(D41<>"", B41<>""), ROW()-1, "") -> 40 | B41: Integrasi TCES TICS | D41: Membuat data input untuk pengujian yang sudah di Fix untuk Travela dan TFire | E41: DONE | F41: CRITICAL | G41: ENHANCEMENT | H41: TCES | J41: 1 | K41: 46268 | L41: 46269 | M41: 46269 | N41: haviz.indra@elistec.com | O41: syafix.said@elistec.com | S41: athallah.bariq@elistec.com | T41: mohammad.danang@elistec.com
A42: =IF(OR(D42<>"", B42<>""), ROW()-1, "") -> 41 | B42: Integrasi TCES TICS | D42: Pengujian kembali dari data TCES untuk TDrive, TRide, TFire, dan Travela setelah terdapat perbaikan pada aplikasi | E42: DONE | F42: CRITICAL | G42: ENHANCEMENT | H42: TCES | J42: 1 | K42: 46269 | L42: 46269 | M42: 46269 | N42: haviz.indra@elistec.com | O42: syafix.said@elistec.com | S42: athallah.bariq@elistec.com | T42: mohammad.danang@elistec.com
A43: =IF(OR(D43<>"", B43<>""), ROW()-1, "") -> 42 | B43: Integrasi TCES TICS | D43: Meng-update kembali QA Tracker untuk pengujian sebelum dan sesudah fixing | E43: DONE | F43: CRITICAL | G43: ENHANCEMENT | H43: TCES | J43: 1 | K43: 46269 | L43: 46269 | M43: 46269 | N43: haviz.indra@elistec.com | O43: syafix.said@elistec.com | S43: athallah.bariq@elistec.com | T43: mohammad.danang@elistec.com
A44: =IF(OR(D44<>"", B44<>""), ROW()-1, "") -> 43 | B44: Integrasi TCES TICS | D44: Meeting Pembahasan CMS TCES | E44: DONE | F44: CRITICAL | G44: ENHANCEMENT | H44: TCES | J44: 1 | K44: 46269 | L44: 46269 | M44: 46269 | N44: haviz.indra@elistec.com | O44: syafix.said@elistec.com | S44: athallah.bariq@elistec.com | T44: mohammad.danang@elistec.com | W44: Catatan pada mas atha pada link berikut
A45: =IF(OR(D45<>"", B45<>""), ROW()-1, "") -> 44 | B45: Integrasi TCES TICS | D45: Meeting Pembahasan Pembagian Pekerjaan dan Percepatan untuk Go Live TCES Khusus untuk product TRide dan TDrive | E45: DONE | F45: CRITICAL | G45: ENHANCEMENT | H45: TCES | J45: 1 | K45: 46272 | L45: 46272 | M45: 46272 | N45: haviz.indra@elistec.com | O45: syafix.said@elistec.com | S45: athallah.bariq@elistec.com | T45: mohammad.danang@elistec.com
A46: =IF(OR(D46<>"", B46<>""), ROW()-1, "") -> 45 | B46: Integrasi TCES TICS | D46: Membuat laporan BAST Elistec dan kelengkapan informasi data task pengerjaan project dari keseluruhan member | E46: DONE | F46: CRITICAL | G46: ENHANCEMENT | H46: TCES | J46: 1 | K46: 46272 | L46: 46273 | M46: 46273 | N46: haviz.indra@elistec.com | O46: syafix.said@elistec.com | S46: athallah.bariq@elistec.com | T46: mohammad.danang@elistec.com
A47: =IF(OR(D47<>"", B47<>""), ROW()-1, "") -> 46 | B47: Integrasi TCES TICS | D47: Perbaikan Struktur BRD | E47: DONE | F47: CRITICAL | G47: ENHANCEMENT | H47: TCES | J47: 1 | K47: 46272 | L47: 46276 | M47: 46276 | N47: haviz.indra@elistec.com | O47: syafix.said@elistec.com | S47: athallah.bariq@elistec.com | T47: mohammad.danang@elistec.com
A48: =IF(OR(D48<>"", B48<>""), ROW()-1, "") -> 47 | B48: Integrasi TCES TICS | D48: Penambahan informasi link evidence untuk semua timesheet kebutuhan BAST | E48: DONE | F48: CRITICAL | G48: ENHANCEMENT | H48: TCES | J48: 1 | K48: 46273 | L48: 46273 | M48: 46273 | N48: haviz.indra@elistec.com | O48: syafix.said@elistec.com | S48: athallah.bariq@elistec.com | T48: mohammad.danang@elistec.com | W48: Penambahan link evidence untuk kebutuhan Timesheet BAST
A49: =IF(OR(D49<>"", B49<>""), ROW()-1, "") -> 48 | B49: Pengembangan Mass Product Retail | D49: Pembuatan TC Kebutuhan Testing Mass Product | E49: TODO | F49: MEDIUM | G49: NEW_APPLICATION | H49: Policy Automation | J49: 0 | K49: 46275 | L49: 46275 | M49: 46275 | O49: syafix.said@elistec.com | R49: mohammad.danang@elistec.com
A50: =IF(OR(D50<>"", B50<>""), ROW()-1, "") -> 49 | B50: Pengembangan Mass Product Retail | D50: Meeting penjelasan work flow mass product dengan developer, qa, dan BA | E50: TODO | F50: MEDIUM | G50: NEW_APPLICATION | H50: Policy Automation | J50: 0 | K50: 46275 | L50: 46275 | M50: 46275 | O50: syafix.said@elistec.com | R50: mohammad.danang@elistec.com
A51: =IF(OR(D51<>"", B51<>""), ROW()-1, "") -> 50 | B51: Integrasi TCES TICS | D51: Finalisasi FSD | E51: DONE | F51: CRITICAL | G51: ENHANCEMENT | H51: TCES | J51: 1 | K51: 46275 | L51: 46276 | M51: 46276 | N51: haviz.indra@elistec.com | O51: syafix.said@elistec.com | S51: athallah.bariq@elistec.com | T51: mohammad.danang@elistec.com | V51: finalisasi semua struktur dan konten dan formatting dokumen FSD | W51: FSD telah di submit untuk di review
A52: =IF(OR(D52<>"", B52<>""), ROW()-1, "") -> 51 | B52: Integrasi TCES TICS | D52: Finalisasi TSD (BA) | E52: DONE | F52: CRITICAL | G52: ENHANCEMENT | H52: TCES | J52: 1 | K52: 46275 | L52: 46276 | M52: 46276 | N52: haviz.indra@elistec.com | O52: syafix.said@elistec.com | S52: athallah.bariq@elistec.com | T52: mohammad.danang@elistec.com | V52: finalisasi semua struktur dan konten dan formatting dokumen TSD
A53: =IF(OR(D53<>"", B53<>""), ROW()-1, "") -> 52 | B53: Integrasi TCES TICS | D53: Pengujian Kembali dari Data TCES untuk TDRive, TRide, pada tanggal 8 Sept untuk penambahan pengujian promo | E53: DONE | F53: HIGH | G53: ENHANCEMENT | H53: TCES | J53: 1 | K53: 46275 | L53: 46276 | M53: 46276 | N53: haviz.indra@elistec.com | O53: syafix.said@elistec.com | S53: athallah.bariq@elistec.com | T53: mohammad.danang@elistec.com | W53: Hasil pengujian pada link berikut : https://tugu.sharepoint.com/:x:/r/sites/TUGUFILESHARING/Documents/IT/External%20Share/2026%20Manage%20Service%20Elistec/API%20Integration/5.%20Testing/SIT/Pengujian%20TDrive%20%26%20TRide%20Lanjutan%20(11%20Sept%202026)/Testing%20T-Drive.xlsx?d=wc8ca09898ba44887a42cb2fbee6c31e5&csf=1&web=1&e=LImI7L
A54: =IF(OR(D54<>"", B54<>""), ROW()-1, "") -> 53 | B54: Integrasi TCES TICS | D54: Lanjutan - Pengujian Kembali dari Data TCES untuk TDRive, TRide, pada tanggal 10 Sept untuk penambahan pengujian promo | E54: DONE | F54: CRITICAL | G54: ENHANCEMENT | H54: TCES | J54: 1 | K54: 46276 | L54: 46276 | M54: 46276 | N54: haviz.indra@elistec.com | O54: syafix.said@elistec.com | S54: athallah.bariq@elistec.com | T54: mohammad.danang@elistec.com
A55: =IF(OR(D55<>"", B55<>""), ROW()-1, "") -> 54 | B55: Integrasi TCES TICS | D55: Mempelajari Treaty Travela dengan mas Egy dan mba Etha | E55: DONE | F55: CRITICAL | G55: ENHANCEMENT | H55: TCES | J55: 1 | K55: 46276 | L55: 46276 | M55: 46276 | N55: haviz.indra@elistec.com | O55: syafix.said@elistec.com | S55: athallah.bariq@elistec.com | T55: mohammad.danang@elistec.com | W55: Informasi dari mas Egy, bahwa Travela tidak membutuhkan Treaty, dan sudah di jelaskan kepada mba etha
A56: =IF(OR(D56<>"", B56<>""), ROW()-1, "") -> 55 | B56: Integrasi TCES TICS | D56: Update TCES Payload untuk penambahan informasi kode kendaraan agar sync dengan TICS | E56: DONE | F56: HIGH | G56: ENHANCEMENT | H56: TCES | J56: 1 | K56: 46280 | L56: 46283 | M56: 46283 | N56: haviz.indra@elistec.com | O56: syafix.said@elistec.com | S56: athallah.bariq@elistec.com | T56: mohammad.danang@elistec.com | V56: untuk integrasi masih di formulasikan oleh mas Jul dan segera setelah mendapatkan hasil akan di implementasikan ke dalam tces khusus untuk MV
A57: =IF(OR(D57<>"", B57<>""), ROW()-1, "") -> 56 | B57: API Settlement Payment | D57: Perancangan Sistem dan Project API Settlement Payment | E57: DONE | F57: HIGH | G57: ENHANCEMENT | H57: TCES | J57: 1 | K57: 46280 | L57: 46283 | M57: 46283 | N57: haviz.indra@elistec.com | O57: syafix.said@elistec.com | S57: athallah.bariq@elistec.com | T57: mohammad.danang@elistec.com
A58: =IF(OR(D58<>"", B58<>""), ROW()-1, "") -> 57 | B58: API Settlement Payment | D58: Meeting Pembahasan Settlement Payment Flow | E58: DONE | F58: HIGH | G58: ENHANCEMENT | H58: TCES | J58: 1 | K58: 46280 | L58: 46280 | M58: 46280 | N58: haviz.indra@elistec.com | O58: syafix.said@elistec.com | S58: athallah.bariq@elistec.com | T58: mohammad.danang@elistec.com | W58: Meeting pembahasan Settlement Payment TCES dengan mas Rifqi, Tim Developer, dan TW
A59: =IF(OR(D59<>"", B59<>""), ROW()-1, "") -> 58 | B59: API Settlement Payment | D59: Membuat Diagram Proses Perancangan API Settlement Payment | E59: DONE | F59: HIGH | G59: ENHANCEMENT | H59: TCES | J59: 1 | K59: 46280 | L59: 46283 | M59: 46283 | N59: haviz.indra@elistec.com | O59: syafix.said@elistec.com | S59: athallah.bariq@elistec.com | T59: mohammad.danang@elistec.com | V59: Pembuatan flow diagram, HLD, LLD, Arsitektur, Flowchart, sequence
A60: =IF(OR(D60<>"", B60<>""), ROW()-1, "") -> 59 | B60: Integrasi TCES TICS | D60: Meeting pembahasan Claim Polis TCES dengan Business User dan Elistec | E60: DONE | F60: LOW | G60: ENHANCEMENT | H60: TCES | J60: 1 | K60: 46281 | L60: 46281 | M60: 46281 | N60: haviz.indra@elistec.com | O60: syafix.said@elistec.com | S60: athallah.bariq@elistec.com | T60: mohammad.danang@elistec.com
A61: =IF(OR(D61<>"", B61<>""), ROW()-1, "") -> 60 | B61: API Settlement Payment | D61: Pembuatan BRD API Settlement Payment | E61: DONE | F61: HIGH | G61: ENHANCEMENT | H61: TCES | J61: 1 | K61: 46281 | L61: 46296 | M61: 46296 | N61: haviz.indra@elistec.com | O61: syafix.said@elistec.com | S61: athallah.bariq@elistec.com | T61: mohammad.danang@elistec.com | W61: BRD telah di sesuaikan dan sedang dalam review BA
A62: =IF(OR(D62<>"", B62<>""), ROW()-1, "") -> 61 | B62: Integrasi TCES TICS | D62: Membantu QA melakukan pengecekan data testing yang blocked | E62: DONE | F62: CRITICAL | G62: ENHANCEMENT | H62: TCES | J62: 1 | K62: 46282 | L62: 46282 | M62: 46282 | N62: haviz.indra@elistec.com | O62: syafix.said@elistec.com | S62: athallah.bariq@elistec.com | T62: mohammad.danang@elistec.com | W62: Perbaikan telah dilakukan, dan untuk data dapat berjalan masuk ke TICS
A63: =IF(OR(D63<>"", B63<>""), ROW()-1, "") -> 62 | B63: Integrasi TCES TICS | D63: Meeting Sharing Knowledge TCES oleh tim Elistec dan Tugu | E63: DONE | F63: HIGH | G63: ENHANCEMENT | H63: TCES | J63: 1 | K63: 46283 | L63: 46283 | M63: 46283 | N63: haviz.indra@elistec.com | O63: syafix.said@elistec.com | S63: athallah.bariq@elistec.com | T63: mohammad.danang@elistec.com
A64: =IF(OR(D64<>"", B64<>""), ROW()-1, "") -> 63 | B64: API Settlement Payment | D64: Melengkapi Dokumen TSD | E64: DONE | F64: MEDIUM | G64: ENHANCEMENT | H64: TCES | J64: 1 | K64: 46283 | L64: 46300 | M64: 46300 | N64: haviz.indra@elistec.com | O64: syafix.said@elistec.com | S64: athallah.bariq@elistec.com | T64: mohammad.danang@elistec.com | W64: 1. Penambahan Penjelasan dan Diagram (18/9)
A65: =IF(OR(D65<>"", B65<>""), ROW()-1, "") -> 64 | B65: API Settlement Payment | D65: Melengkapi Dokumen FSD | E65: DONE | F65: MEDIUM | G65: ENHANCEMENT | H65: TCES | J65: 1 | K65: 46283 | L65: 46300 | M65: 46300 | N65: haviz.indra@elistec.com | O65: syafix.said@elistec.com | S65: athallah.bariq@elistec.com | T65: mohammad.danang@elistec.com | W65: 1. Penambahan Penjelasan dan Diagram (18/9)
A66: =IF(OR(D66<>"", B66<>""), ROW()-1, "") -> 65 | B66: API Settlement Payment | D66: Membuat Diagram Sequence API Settlemen Payment | E66: DONE | F66: HIGH | G66: ENHANCEMENT | H66: TCES | J66: 1 | K66: 46286 | L66: 46288 | M66: 46288 | N66: haviz.indra@elistec.com | O66: syafix.said@elistec.com | S66: athallah.bariq@elistec.com | T66: mohammad.danang@elistec.com
A67: =IF(OR(D67<>"", B67<>""), ROW()-1, "") -> 66 | B67: API Settlement Payment | D67: Membuat ERD API Settlemen Payment | E67: DONE | F67: HIGH | G67: ENHANCEMENT | H67: TCES | J67: 1 | K67: 46286 | L67: 46288 | M67: 46288 | N67: haviz.indra@elistec.com | O67: syafix.said@elistec.com | S67: athallah.bariq@elistec.com | T67: mohammad.danang@elistec.com
A68: =IF(OR(D68<>"", B68<>""), ROW()-1, "") -> 67 | B68: API Settlement Payment | D68: Perancangan Struktur Payload untuk Settlement Payment TCES - TICS | E68: DONE | F68: CRITICAL | G68: ENHANCEMENT | H68: TCES | J68: 1 | K68: 46286 | L68: 46288 | M68: 46288 | N68: haviz.indra@elistec.com | O68: syafix.said@elistec.com | S68: athallah.bariq@elistec.com | T68: mohammad.danang@elistec.com
A69: =IF(OR(D69<>"", B69<>""), ROW()-1, "") -> 68 | B69: API Settlement Payment | D69: Membuat penambahan kolom untuk menggunakan table lama yang sudah dibuat untuk sesuai dengan Settlement Payment | E69: DONE | F69: CRITICAL | G69: ENHANCEMENT | H69: TCES | J69: 1 | K69: 46287 | L69: 46289 | M69: 46289 | N69: haviz.indra@elistec.com | O69: syafix.said@elistec.com | S69: athallah.bariq@elistec.com | T69: mohammad.danang@elistec.com | V69: terdapat sebuah table kebutuhan settlement payment yang dibuat mas rian, dan table tersebut sedang digunakan namun dapat di alter untuk penambahan kolom yang dibutuhkan sesuai dengan kebutuhan rekonsiliasi Settlement Payment | W69: Membuat DDL query penambahan kolom untuk tces_settlement_header & tces_settlement_detail
A70: =IF(OR(D70<>"", B70<>""), ROW()-1, "") -> 69 | B70: API Settlement Payment | D70: Pendefinisian informasi pengambilan data ZSDDT0002 untuk spesifik zreq id tertentu dan informasi balikan dari SAP terkait GJAHR dan BELNR | E70: DONE | F70: CRITICAL | G70: ENHANCEMENT | H70: TCES | J70: 1 | K70: 46287 | L70: 46289 | M70: 46289 | N70: haviz.indra@elistec.com | O70: syafix.said@elistec.com | S70: athallah.bariq@elistec.com | T70: mohammad.danang@elistec.com | V70: Informasi dari mas daus bahwa ZSDDT0002 akan dapat di sync jika mendapatkan ZREQ_ID_TICS dengan ZREQ_ID dari Stagging dapat di temukan di file log. untuk data saat ini belum ada yang masuk ke ZSDDT0002 untuk beberapa polis terakhir yang sudah di buat. untuk informasi enforce ini dari mas Egy akan membicarakan langsung dengan mas daus | W70: butuh informasi untuk enforce data dari SAP ke TICS agar ZSDDT0002 dapat ter-update. terkait hal ini dibutuhkan meeting untuk memperjelas flow process pengambilan data tersebut
A71: =IF(OR(D71<>"", B71<>""), ROW()-1, "") -> 70 | B71: API Settlement Payment | D71: Update diagram Sequence API Settlement Payment | E71: DONE | F71: MEDIUM | G71: ENHANCEMENT | H71: TCES | J71: 1 | K71: 46288 | L71: 46288 | M71: 46288 | N71: haviz.indra@elistec.com | O71: syafix.said@elistec.com | S71: athallah.bariq@elistec.com | T71: mohammad.danang@elistec.com | V71: Sesuai dengan update yang diberikan, bahwa proses rekonsiliasi akan membutuhkan pengecekan ke stagging, sehingga kebutuhan value untuk zreq id di sesuaikan untuk query | W71: Update kembali diagram Sequence API Settlement Payment
A72: =IF(OR(D72<>"", B72<>""), ROW()-1, "") -> 71 | B72: API Settlement Payment | D72: Update diagram FlowChart API Settlement Payment | E72: DONE | F72: MEDIUM | G72: ENHANCEMENT | H72: TCES | J72: 1 | K72: 46288 | L72: 46288 | M72: 46288 | N72: haviz.indra@elistec.com | O72: syafix.said@elistec.com | S72: athallah.bariq@elistec.com | T72: mohammad.danang@elistec.com | V72: Sesuai dengan update yang diberikan, bahwa proses rekonsiliasi akan membutuhkan pengecekan ke stagging, sehingga kebutuhan value untuk zreq id di sesuaikan untuk query | W72: Update kembali diagram FlowChart API Settlement Payment
A73: =IF(OR(D73<>"", B73<>""), ROW()-1, "") -> 72 | B73: API Settlement Payment | D73: Perancangan model scheduler pada API Settlement Payment untuk melakukan rekonsiliasi data | E73: DONE | F73: HIGH | G73: ENHANCEMENT | H73: TCES | J73: 1 | K73: 46288 | L73: 46289 | M73: 46289 | N73: haviz.indra@elistec.com | O73: syafix.said@elistec.com | S73: athallah.bariq@elistec.com | T73: mohammad.danang@elistec.com | V73: untuk polis dan premium class yang belum ditemukan, aplikasi dapat melakukan pencarian kembali secara mandiri, untuk memastikan data tersebut menjadi rekonsoliasi | W73: dibutuhkan perancangan config scheduler, masa waktu, log. penambahan yang impact pada desain database dan proses akan di tuangkan pada dokumen TSD & FSD
A74: =IF(OR(D74<>"", B74<>""), ROW()-1, "") -> 73 | B74: API Settlement Payment | D74: Pengecekan api-doc / Swagger untuk API Settlement Payment | E74: DONE | F74: MEDIUM | G74: ENHANCEMENT | H74: TCES | J74: 1 | K74: 46288 | L74: 46289 | M74: 46289 | N74: haviz.indra@elistec.com | O74: syafix.said@elistec.com | S74: athallah.bariq@elistec.com | T74: mohammad.danang@elistec.com
A75: =IF(OR(D75<>"", B75<>""), ROW()-1, "") -> 74 | B75: API Settlement Payment | D75: Pembuatan Test Case scenario untuk melihat transaction date dan bill date sesuai | E75: DONE | F75: HIGH | G75: ENHANCEMENT | H75: TCES | J75: 1 | K75: 46289 | L75: 46290 | M75: 46290 | N75: haviz.indra@elistec.com | O75: syafix.said@elistec.com | S75: athallah.bariq@elistec.com | T75: mohammad.danang@elistec.com
A76: =IF(OR(D76<>"", B76<>""), ROW()-1, "") -> 75 | B76: API Settlement Payment | D76: Pengecekan API Settlement Payment integrasi antara TCES dengan TICS | E76: DONE | F76: HIGH | G76: ENHANCEMENT | H76: TCES | J76: 1 | K76: 46289 | L76: 46295 | M76: 46295 | N76: haviz.indra@elistec.com | O76: syafix.said@elistec.com | S76: athallah.bariq@elistec.com | T76: mohammad.danang@elistec.com
A77: =IF(OR(D77<>"", B77<>""), ROW()-1, "") -> 76 | B77: API Settlement Payment | D77: Finalisasi Diagram Arsitektural, FlowChart, Sequence API Settlement Payment | E77: DONE | F77: MEDIUM | G77: ENHANCEMENT | H77: TCES | J77: 1 | K77: 46289 | L77: 46289 | M77: 46289 | N77: haviz.indra@elistec.com | O77: syafix.said@elistec.com | S77: athallah.bariq@elistec.com | T77: mohammad.danang@elistec.com
A78: =IF(OR(D78<>"", B78<>""), ROW()-1, "") -> 77 | B78: API Settlement Payment | D78: Membuat table definition untuk kebutuhan update dokumen TSD | E78: DONE | F78: MEDIUM | G78: ENHANCEMENT | H78: TCES | J78: 1 | K78: 46293 | L78: 46293 | M78: 46293 | N78: haviz.indra@elistec.com | O78: syafix.said@elistec.com | S78: athallah.bariq@elistec.com | T78: mohammad.danang@elistec.com | V78: pada TSD dibutuhkan informasi tambahan mengenai informasi table yang digunakan | W78: perlu dibuatkan table definition untuk table yang digunakan untuk API Settlement Payment
A79: =IF(OR(D79<>"", B79<>""), ROW()-1, "") -> 78 | B79: API Settlement Payment | D79: Meeting Pembahasan rekonsiliasi Settlement Payment antara API Settlement vs Stagging | E79: DONE | F79: MEDIUM | G79: ENHANCEMENT | H79: TCES | J79: 1 | K79: 46293 | L79: 46293 | M79: 46293 | N79: haviz.indra@elistec.com | O79: syafix.said@elistec.com | S79: athallah.bariq@elistec.com | T79: mohammad.danang@elistec.com
A80: =IF(OR(D80<>"", B80<>""), ROW()-1, "") -> 79 | B80: API Settlement Payment | D80: Percobaan enforce manual stagging untuk spesifik no polis dan request id tertentu ke stagging dan SAP | E80: DONE | F80: HIGH | G80: ENHANCEMENT | H80: TCES | J80: 1 | K80: 46294 | L80: 46296 | M80: 46296 | N80: haviz.indra@elistec.com | O80: syafix.said@elistec.com | S80: athallah.bariq@elistec.com | T80: mohammad.danang@elistec.com | V80: Data balikan dari SAP belum masuk ke TICS, sehingga diperlukan enforce manual ke stagging untuk menjalankan retry process ke SAP dan kembali ke TICS
A81: =IF(OR(D81<>"", B81<>""), ROW()-1, "") -> 80 | B81: API Settlement Payment | D81: Input data sampling khusus untuk bisnis class TProperty dan Travela via payload untuk pengecekan Stagging | E81: DONE | F81: CRITICAL | G81: ENHANCEMENT | H81: TCES | J81: 1 | K81: 46294 | L81: 46294 | M81: 46294 | N81: haviz.indra@elistec.com | O81: syafix.said@elistec.com | S81: athallah.bariq@elistec.com | T81: mohammad.danang@elistec.com | V81: dibutuhkan pengecekan untuk Non MV, dimana data yang MV sudah dapat di ambil datanya dari stagging sedangkan non-MV terdapat kendala
A82: =IF(OR(D82<>"", B82<>""), ROW()-1, "") -> 81 | B82: API Settlement Payment | D82: Melakukan rekonsiliasi data secara manual untuk data MV dan Non-MV Pre proses oleh aplikasi | E82: DONE | F82: CRITICAL | G82: ENHANCEMENT | H82: TCES | J82: 1 | K82: 46295 | L82: 46297 | M82: 46297 | N82: haviz.indra@elistec.com | O82: syafix.said@elistec.com | S82: athallah.bariq@elistec.com | T82: mohammad.danang@elistec.com | V82: sehubungan dengan tidak adanya proses enforcement otomatis dari stagging ke TICS, maka proses dilakukan secara manual terlebih dahulu | W82: hasil output dari pengujian dengan beberapa jenis kategori bisnis telah mendapatkan hasil, namun tidak berhasil utnuk TProperty, karena memerlukan update informasi product terlebih dahulu
A83: =IF(OR(D83<>"", B83<>""), ROW()-1, "") -> 82 | B83: API Settlement Payment | D83: Pengecekan Rekonsiliasi dengan sejumlah premi yang ditambahkan dan pengecekan manual | E83: DONE | F83: CRITICAL | G83: ENHANCEMENT | H83: TCES | J83: 1 | K83: 46296 | L83: 46297 | M83: 46297 | N83: haviz.indra@elistec.com | O83: syafix.said@elistec.com | S83: athallah.bariq@elistec.com | T83: mohammad.danang@elistec.com | V83: Proses rekonsiliasi gagal, dan membutuhkan insight dari mas DAus
A84: =IF(OR(D84<>"", B84<>""), ROW()-1, "") -> 83 | B84: API Settlement Payment | D84: Update & finalisasi laporan akhir bulan API Settlement Payment | E84: DONE | F84: CRITICAL | G84: ENHANCEMENT | H84: TCES | J84: 1 | K84: 46296 | L84: 46297 | M84: 46297 | N84: haviz.indra@elistec.com | O84: syafix.said@elistec.com | S84: athallah.bariq@elistec.com | T84: mohammad.danang@elistec.com
A85: =IF(OR(D85<>"", B85<>""), ROW()-1, "") -> 84 | B85: API Settlement Payment | D85: Pembuatan Timesheet & Project Summary | E85: DONE | F85: CRITICAL | G85: ENHANCEMENT | H85: TCES | J85: 1 | K85: 46297 | L85: 46297 | M85: 46297 | N85: haviz.indra@elistec.com | O85: syafix.said@elistec.com | S85: athallah.bariq@elistec.com | T85: mohammad.danang@elistec.com
A86: =IF(OR(D86<>"", B86<>""), ROW()-1, "") -> 85 | B86: API Settlement Payment | D86: Meeting Pembahasan integrasi Settlement BengkelNet | E86: DONE | F86: CRITICAL | G86: ENHANCEMENT | H86: TCES | J86: 1 | K86: 46301 | L86: 46301 | M86: 46301 | N86: haviz.indra@elistec.com | O86: syafix.said@elistec.com | S86: athallah.bariq@elistec.com | T86: mohammad.danang@elistec.com | W86: Pembahasan integrasi Bengkel Net dengan TCES dan TICS
A87: =IF(OR(D87<>"", B87<>""), ROW()-1, "") -> 86 | B87: Staging Cloud | D87: Mempelajari Alur Process Stagging Cloud | E87: DONE | F87: MEDIUM | G87: MIGRATION | H87: Staging Cloud | J87: 1 | K87: 46302 | L87: 46307 | M87: 46307 | N87: iqbal.ali@elistec.com | O87: syafix.said@elistec.com | S87: athallah.bariq@elistec.com | T87: mohammad.danang@elistec.com
A88: =IF(OR(D88<>"", B88<>""), ROW()-1, "") -> 87 | B88: API Settlement Payment | D88: Pengecekan input data TCES dengan sejumlah no polis untuk melakukan proses rekonsiliasi secara otomatis dengan scheduler. | E88: DONE | F88: HIGH | G88: ENHANCEMENT | H88: TCES | J88: 1 | K88: 46302 | L88: 46303 | M88: 46303 | N88: haviz.indra@elistec.com | O88: syafix.said@elistec.com | S88: athallah.bariq@elistec.com | T88: mohammad.danang@elistec.com
A89: =IF(OR(D89<>"", B89<>""), ROW()-1, "") -> 88 | B89: Staging Cloud | D89: Perancangan diagram alur proses staging cloud - master data | E89: DONE | F89: MEDIUM | G89: NEW_APPLICATION | H89: Staging Cloud | J89: 1 | K89: 46303 | L89: 46304 | M89: 46304 | N89: iqbal.ali@elistec.com | O89: syafix.said@elistec.com | S89: athallah.bariq@elistec.com | T89: mohammad.danang@elistec.com | V89: Berdasarkan informasi yang ada pada diagram terdapat kekurangan, sehingga perlu di buat diagram kembali untuk memberikan flow informasi secara jelas | W89: pembentukan diagram baru untuk staging cloud khusus untuk get BP (Business Partner) / Master Data
A90: =IF(OR(D90<>"", B90<>""), ROW()-1, "") -> 89 | B90: Staging Cloud | D90: Perancangan proses validasi data input untuk di proses oleh SAP dari SP ke bentuk service | E90: DONE | F90: CRITICAL | G90: NEW_APPLICATION | H90: Staging Cloud | J90: 1 | K90: 46303 | L90: 46307 | M90: 46307 | N90: iqbal.ali@elistec.com | O90: syafix.said@elistec.com | S90: athallah.bariq@elistec.com | T90: mohammad.danang@elistec.com | V90: Saat ini proses validasi dilakukan dengan SP perlu di pindahkan ke bentuk service
A91: =IF(OR(D91<>"", B91<>""), ROW()-1, "") -> 90 | B91: API Settlement Payment | D91: Pengubahan counter percobaan scheduler API Settlement menjadi 60x yang sebelumnya 84x | E91: DONE | F91: HIGH | G91: ENHANCEMENT | H91: TCES | J91: 1 | K91: 46304 | L91: 46304 | M91: 46304 | N91: haviz.indra@elistec.com | O91: syafix.said@elistec.com | S91: athallah.bariq@elistec.com | T91: mohammad.danang@elistec.com | V91: Scheduler ingin di set oleh bu Etha menjadi 60 x pengambilan data per 2 jam sekali, sehingga menjadi 5 hari max | W91: Scheduler telah di update untuk pengambilan settlement menjadi 60x sesuai request dan sudah di deploy ke UAT
A92: =IF(OR(D92<>"", B92<>""), ROW()-1, "") -> 91 | B92: Integrasi TCES TICS | D92: Restrukturisasi dan merging dokumen BRD API Settlement & API Integration | E92: DONE | F92: MEDIUM | G92: ENHANCEMENT | H92: TCES | J92: 1 | K92: 46304 | L92: 46318 | M92: 46318 | N92: haviz.indra@elistec.com | O92: syafix.said@elistec.com | S92: athallah.bariq@elistec.com | T92: mohammad.danang@elistec.com | V92: Penggabungan dokumen BRD API Settlement & Integration
A93: =IF(OR(D93<>"", B93<>""), ROW()-1, "") -> 92 | B93: Integrasi TCES TICS | D93: Restrukturisasi dan merging dokumen FSD API Settlement & API Integration | E93: DONE | F93: MEDIUM | G93: ENHANCEMENT | H93: TCES | J93: 1 | K93: 46304 | L93: 46318 | M93: 46318 | N93: haviz.indra@elistec.com | O93: syafix.said@elistec.com | S93: athallah.bariq@elistec.com | T93: mohammad.danang@elistec.com | V93: Penggabungan dokumen FSD API Settlement & Integration
A94: =IF(OR(D94<>"", B94<>""), ROW()-1, "") -> 93 | B94: Integrasi TCES TICS | D94: Restrukturisasi dan merging dokumen TSD API Settlement & API Integration | E94: DONE | F94: MEDIUM | G94: ENHANCEMENT | H94: TCES | J94: 1 | K94: 46304 | L94: 46318 | M94: 46318 | N94: haviz.indra@elistec.com | O94: syafix.said@elistec.com | S94: athallah.bariq@elistec.com | T94: mohammad.danang@elistec.com | V94: Penggabungan dokumen TSD API Settlement & Integration
A95: =IF(OR(D95<>"", B95<>""), ROW()-1, "") -> 94 | B95: Staging Cloud | D95: Pembuatan Test Case Staging Cloud | E95: DONE | F95: HIGH | G95: NEW_APPLICATION | H95: Staging Cloud | J95: 1 | K95: 46307 | L95: 46309 | M95: 46309 | N95: iqbal.ali@elistec.com | O95: syafix.said@elistec.com | S95: athallah.bariq@elistec.com | V95: Pembuatan Test Case Pengujian Staging Cloud
A96: =IF(OR(D96<>"", B96<>""), ROW()-1, "") -> 95 | B96: Staging Cloud | D96: Mengkomunikasikan mitirgasi terkait kebutuhan enkripsi antara TICS dengan Staging Cloud | E96: DONE | F96: MEDIUM | G96: NEW_APPLICATION | H96: Staging Cloud | J96: 1 | K96: 46308 | L96: 46311 | M96: 46311 | N96: iqbal.ali@elistec.com | O96: syafix.said@elistec.com | S96: athallah.bariq@elistec.com | T96: syifa.kurnia@elistec,com | W96: Pembahasan dengan mas julian, mas daus dan iqbal untuk proses pengecekan data / tracing di Staging Cloud
A97: =IF(OR(D97<>"", B97<>""), ROW()-1, "") -> 96 | B97: Staging Cloud | D97: Validasi pengecekan alur proses data testing untuk Staging Cloud dengan dev dan tim internal terkait | E97: DONE | F97: HIGH | G97: NEW_APPLICATION | H97: Staging Cloud | J97: 1 | K97: 46309 | L97: 46311 | M97: 46311 | N97: iqbal.ali@elistec.com | O97: syafix.said@elistec.com | S97: athallah.bariq@elistec.com | T97: syifa.kurnia@elistec,com
A98: =IF(OR(D98<>"", B98<>""), ROW()-1, "") -> 97 | B98: Staging Cloud | D98: Finalisasi Diagram Arsitektur Staging Cloud | E98: DONE | F98: HIGH | G98: NEW_APPLICATION | H98: Staging Cloud | J98: 1 | K98: 46309 | L98: 46311 | M98: 46311 | N98: iqbal.ali@elistec.com | O98: syafix.said@elistec.com | S98: athallah.bariq@elistec.com | T98: syifa.kurnia@elistec,com
A99: =IF(OR(D99<>"", B99<>""), ROW()-1, "") -> 98 | B99: Staging Cloud | D99: Persiapan Pembuatan BRD dan dokumen FSD, TSD Staging Cloud | E99: DONE | F99: MEDIUM | G99: NEW_APPLICATION | H99: Staging Cloud | J99: 1 | K99: 46310 | L99: 46311 | M99: 46311 | N99: iqbal.ali@elistec.com | O99: syafix.said@elistec.com | S99: athallah.bariq@elistec.com | T99: syifa.kurnia@elistec,com
A100: =IF(OR(D100<>"", B100<>""), ROW()-1, "") -> 99 | B100: Staging Cloud | D100: Implementasi Kafka UI di SC - Outbound | E100: Done | F100: HIGH | G100: NEW_APPLICATION | H100: Staging Cloud | J100: 1 | K100: 46311 | L100: 46314 | M100: 46314 | N100: iqbal.ali@elistec.com | O100: syafix.said@elistec.com | S100: athallah.bariq@elistec.com | T100: syifa.kurnia@elistec,com | V100: dibutuhkan kafka ui untuk dapat melihat informasi data stream yang akan di kirimkan untuk di proses, dikarenakan data tersebut berada dalam topic di sebuah aplikasi kafka, maka dibutuhkan kafka ui untuk dapat melihat informasi di dalam nya | W100: implementasi kafka ui berhasil dan tim DEV, BA, QA, TW dapat melihat informasi tersebut secara langsung
...

Sheet Haviz
A1: No. | B1: project_name | C1: requirement_code | D1: title | E1: status | F1: priority | G1: jenis_task | H1: module_name | I1: bug_type | J1: progress | K1: start_date | L1: due_date | M1: completed_date | N1: developer_emails | O1: ba_emails | P1: infra_emails | Q1: master_data_emails | R1: tester_emails | S1: technical_writer_emails | T1: quality_assurance_emails | U1: system_analyst_emails | V1: kendala | W1: solusi | X1: evidence | Y1: kode_task | Z1: Milestone
A2: =IF(OR(D2<>"", B2<>""), ROW()-1, "") -> 1 | B2: Integrasi TCES TICS | D2: Pelajari enkripsi pertukaran data di TCES & Transfer knowledge API Integration TICS | E2: DONE | F2: MEDIUM | G2: ENHANCEMENT | H2: TCES | J2: 1 | K2: 46239 | L2: 46239 | M2: 46239 | N2: haviz.indra@elistec.com | O2: syafix.said@elistec.com | S2: athallah.bariq@elistec.com | T2: mohammad.danang@elistec.com
A3: =IF(OR(D3<>"", B3<>""), ROW()-1, "") -> 2 | B3: Integrasi TCES TICS | D3: Eksplorasi Codebase API TICS Integration | E3: DONE | F3: MEDIUM | G3: ENHANCEMENT | H3: TCES | J3: 1 | K3: 46240 | L3: 46241 | M3: 46241 | N3: haviz.indra@elistec.com | O3: syafix.said@elistec.com | S3: athallah.bariq@elistec.com | T3: mohammad.danang@elistec.com
A4: =IF(OR(D4<>"", B4<>""), ROW()-1, "") -> 3 | B4: Integrasi TCES TICS | D4: Meeting Mekanisme Enkripsi Terbaru TCES ke TICS dengan Tim Elistec | E4: DONE | F4: MEDIUM | G4: ENHANCEMENT | H4: TCES | J4: 1 | K4: 46244 | L4: 46244 | M4: 46244 | N4: haviz.indra@elistec.com | O4: syafix.said@elistec.com | S4: athallah.bariq@elistec.com | T4: mohammad.danang@elistec.com
A5: =IF(OR(D5<>"", B5<>""), ROW()-1, "") -> 4 | B5: Integrasi TCES TICS | D5: Sharing Knowledge Penggunaan dan Alur Proses Aplikasi TCES - Pembelian Phase | E5: DONE | F5: MEDIUM | G5: ENHANCEMENT | H5: TCES | J5: 1 | K5: 46245 | L5: 46245 | M5: 46245 | N5: haviz.indra@elistec.com | O5: syafix.said@elistec.com | S5: athallah.bariq@elistec.com | T5: mohammad.danang@elistec.com
A6: =IF(OR(D6<>"", B6<>""), ROW()-1, "") -> 5 | B6: Integrasi TCES TICS | D6: Pelajari Enkripsi Signature & Payload terbaru (dari hasil meeting kemarin) + Sampling | E6: DONE | F6: MEDIUM | G6: ENHANCEMENT | H6: TCES | J6: 1 | K6: 46245 | L6: 46246 | M6: 46246 | N6: haviz.indra@elistec.com | O6: syafix.said@elistec.com | S6: athallah.bariq@elistec.com | T6: mohammad.danang@elistec.com
A7: =IF(OR(D7<>"", B7<>""), ROW()-1, "") -> 6 | B7: Integrasi TCES TICS | D7: Implementasi Enkripsi API TCES to TICS - Membuat endpoint baru /api/v2/tics/transaction/store untuk pertukaran data tces ke tics | E7: DONE | F7: HIGH | G7: ENHANCEMENT | H7: TCES | J7: 1 | K7: 46247 | L7: 46247 | M7: 46247 | N7: haviz.indra@elistec.com | O7: syafix.said@elistec.com | S7: athallah.bariq@elistec.com | T7: mohammad.danang@elistec.com
A8: =IF(OR(D8<>"", B8<>""), ROW()-1, "") -> 7 | B8: Integrasi TCES TICS | D8: Implementasi Enkripsi API TCES to TICS - Menerapkan otentikasi baru dengan menggunakan Digital Signature pada endpoint | E8: DONE | F8: HIGH | G8: ENHANCEMENT | H8: TCES | J8: 1 | K8: 46247 | L8: 46247 | M8: 46247 | N8: haviz.indra@elistec.com | O8: syafix.said@elistec.com | S8: athallah.bariq@elistec.com | T8: mohammad.danang@elistec.com
A9: =IF(OR(D9<>"", B9<>""), ROW()-1, "") -> 8 | B9: Integrasi TCES TICS | D9: Implementasi Enkripsi API TCES to TICS - Menerapkan fungsi decript pada data insured yang dikirim tces | E9: DONE | F9: HIGH | G9: ENHANCEMENT | H9: TCES | J9: 1 | K9: 46248 | L9: 46248 | M9: 46248 | N9: haviz.indra@elistec.com | O9: syafix.said@elistec.com | S9: athallah.bariq@elistec.com | T9: mohammad.danang@elistec.com
A10: =IF(OR(D10<>"", B10<>""), ROW()-1, "") -> 9 | B10: Integrasi TCES TICS | D10: Implementasi Enkripsi API TCES to TICS - Testing Penerapan Signature dan Enkripsinya by Postman | E10: DONE | F10: HIGH | G10: ENHANCEMENT | H10: TCES | J10: 1 | K10: 46248 | L10: 46248 | M10: 46248 | N10: haviz.indra@elistec.com | O10: syafix.said@elistec.com | S10: athallah.bariq@elistec.com | T10: mohammad.danang@elistec.com
A11: =IF(OR(D11<>"", B11<>""), ROW()-1, "") -> 10 | B11: Integrasi TCES TICS | D11: Penyesuaian mapping data pada integrasi TCES ke TICS - Penambahan fungsi untuk insert data ke tabel tces_acceptance_object_detail | E11: DONE | F11: HIGH | G11: ENHANCEMENT | H11: TCES | J11: 1 | K11: 46252 | L11: 46252 | M11: 46252 | N11: haviz.indra@elistec.com | O11: syafix.said@elistec.com | S11: athallah.bariq@elistec.com | T11: mohammad.danang@elistec.com
A12: =IF(OR(D12<>"", B12<>""), ROW()-1, "") -> 11 | B12: Integrasi TCES TICS | D12: Penyesuaian mapping data pada integrasi TCES ke TICS - Testing dan memastikan proses otentikasi signature, decrypt insured dan insert data ke database sudah berjalan. | E12: DONE | F12: HIGH | G12: ENHANCEMENT | H12: TCES | J12: 1 | K12: 46252 | L12: 46252 | M12: 46252 | N12: haviz.indra@elistec.com | O12: syafix.said@elistec.com | S12: athallah.bariq@elistec.com | T12: mohammad.danang@elistec.com
A13: =IF(OR(D13<>"", B13<>""), ROW()-1, "") -> 12 | B13: Integrasi TCES TICS | D13: Proses penambahan variable baru untuk keperluan verify signature & decrypt data pada file .env yang ada di server dev. variable yang di tambahkan : INTEGRATION_PUBLIC_KEY & TICS_PARTNER_PRIVATE_KEY | E13: DONE | F13: HIGH | G13: ENHANCEMENT | H13: TCES | J13: 1 | K13: 46253 | L13: 46253 | M13: 46253 | N13: haviz.indra@elistec.com | O13: syafix.said@elistec.com | S13: athallah.bariq@elistec.com | T13: mohammad.danang@elistec.com
... A41: =IF(OR(D41<>"", B41<>""), ROW()-1, "") -> 40 | B41: Integrasi TCES TICS | D41: Membantu QA dan BA Monitoring & Validasi Data Dashboard & Database ketika melakukan testing E2E Integrasi TCES ke TICS (MV) dengan Diskon/Promo + BP Belum Terdaftar | E41: DONE | F41: MEDIUM | G41: ENHANCEMENT | H41: TCES | J41: 1 | K41: 46279 | L41: 46279 | M41: 46279 | N41: haviz.indra@elistec.com | O41: syafix.said@elistec.com | S41: athallah.bariq@elistec.com | T41: mohammad.danang@elistec.com
A42: 41 | B42: API Settlement Payment | D42: Briefing Penjelasan Alur Settlement Payment bersama Bu Etha dan Mas Abel | E42: DONE | F42: MEDIUM | G42: ENHANCEMENT | H42: TCES | J42: 1 | K42: 46280 | L42: 46280 | M42: 46280 | N42: haviz.indra@elistec.com | O42: syafix.said@elistec.com | S42: athallah.bariq@elistec.com | T42: mohammad.danang@elistec.com
A43: 41 | B43: API Settlement Payment | D43: Meeting Terkait Espay Settlement Notification dengan Mas Rifqi (TCES) | E43: DONE | F43: MEDIUM | G43: ENHANCEMENT | H43: TCES | J43: 1 | K43: 46280 | L43: 46280 | M43: 46280 | N43: haviz.indra@elistec.com | O43: syafix.said@elistec.com | S43: athallah.bariq@elistec.com | T43: mohammad.danang@elistec.com
A44: 42 | B44: Integrasi TCES TICS | D44: Membantu QA dan BA Monitoring & Validasi Data Dashboard & Database ketika melakukan testing E2E Integrasi TCES ke TICS (MV) dengan Diskon/Promo + BP Belum Terdaftar | E44: DONE | F44: MEDIUM | G44: ENHANCEMENT | H44: TCES | J44: 1 | K44: 46280 | L44: 46280 | M44: 46280 | N44: haviz.indra@elistec.com | O44: syafix.said@elistec.com | S44: athallah.bariq@elistec.com | T44: mohammad.danang@elistec.com
A45: 43 | B45: Integrasi TCES TICS | D45: Meeting Integrasi Claim TCES (Tim IT Tugu, Tim Claim Tugu, Tim IT Elistec) | E45: DONE | F45: MEDIUM | G45: ENHANCEMENT | H45: TCES | J45: 1 | K45: 46281 | L45: 46281 | M45: 46281 | N45: haviz.indra@elistec.com | O45: syafix.said@elistec.com | S45: athallah.bariq@elistec.com | T45: mohammad.danang@elistec.com
A46: 44 | B46: API Settlement Payment | D46: Implementasi API Settlement Payment Espay to TICS - Setup middleware untuk Otentikasi Digital Signature | E46: DONE | F46: HIGH | G46: ENHANCEMENT | H46: TCES | J46: 1 | K46: 46282 | L46: 46282 | M46: 46282 | N46: haviz.indra@elistec.com | O46: syafix.said@elistec.com | S46: athallah.bariq@elistec.com | T46: mohammad.danang@elistec.com
A47: =IF(OR(D47<>"", B47<>""), ROW()-1, "") -> 46 | B47: Integrasi TCES TICS | D47: Meeting Sharing Knowledge TCES oleh tim Elistec dan Tugu | E47: DONE | F47: HIGH | G47: ENHANCEMENT | H47: TCES | J47: 1 | K47: 46283 | L47: 46283 | M47: 46283 | N47: haviz.indra@elistec.com | O47: syafix.said@elistec.com | S47: athallah.bariq@elistec.com | T47: mohammad.danang@elistec.com
A48: =IF(OR(D48<>"", B48<>""), ROW()-1, "") -> 47 | B48: API Settlement Payment | D48: Implementasi endpoint baru POST /api/v2/tics/settlement/store melalui pembuatan SettlementController untuk menerima dan menyimpan data payload settlement transaksi (Espay/Tces) ke tabel integration_payload dengan kategori TCES SETTLEMENT | E48: DONE | F48: HIGH | G48: ENHANCEMENT | H48: TCES | J48: 1 | K48: 46286 | L48: 46286 | M48: 46286 | N48: haviz.indra@elistec.com | O48: syafix.said@elistec.com | S48: athallah.bariq@elistec.com | T48: mohammad.danang@elistec.com
A49: =IF(OR(D49<>"", B49<>""), ROW()-1, "") -> 48 | B49: API Settlement Payment | D49: Pengembangan endpoint POST /api/v2/tics/settlement/store untuk proses validasi, dilanjutkan dengan ekstraksi data ke tces_settlement_header & tces_settlement_detail serta penanganan proteksi duplikasi rq_uuid (HTTP 409) | E49: DONE | F49: HIGH | G49: ENHANCEMENT | H49: TCES | J49: 1 | K49: 46287 | L49: 46287 | M49: 46287 | N49: haviz.indra@elistec.com | O49: syafix.said@elistec.com | S49: athallah.bariq@elistec.com | T49: mohammad.danang@elistec.com
A50: =IF(OR(D50<>"", B50<>""), ROW()-1, "") -> 49 | B50: API Settlement Payment | D50: Mengimplementasikan data enrichment pada tces_settlement_detail untuk memetakan pol_nbr, quo_nbr (via acceptance), dan zsddt0002_docs (via zsddt0002) saat proses store settlement di endpoint POST /api/v2/tics/settlement/store. | E50: DONE | F50: HIGH | G50: ENHANCEMENT | H50: TCES | J50: 1 | K50: 46288 | L50: 46288 | M50: 46288 | N50: haviz.indra@elistec.com | O50: syafix.said@elistec.com | S50: athallah.bariq@elistec.com | T50: mohammad.danang@elistec.com
A51: =IF(OR(D51<>"", B51<>""), ROW()-1, "") -> 50 | B51: API Settlement Payment | D51: Membuat task scheduler SettlementService::syncMissingSettlementDocs, Artisan command settlement:sync-missing-docs, serta mendaftarkan task scheduler berkala (setiap 2 jam) untuk rekonsiliasi data settlement yang belum lengkap. | E51: DONE | F51: HIGH | G51: ENHANCEMENT | H51: TCES | J51: 1 | K51: 46288 | L51: 46288 | M51: 46288 | N51: haviz.indra@elistec.com | O51: syafix.said@elistec.com | S51: athallah.bariq@elistec.com | T51: mohammad.danang@elistec.com
A52: =IF(OR(D52<>"", B52<>""), ROW()-1, "") -> 51 | B52: API Settlement Payment | D52: Memperbarui dokumentasi OpenAPI/Swagger untuk endpoint settlement store beserta dokumentasi teknisnya | E52: DONE | F52: HIGH | G52: ENHANCEMENT | H52: TCES | J52: 1 | K52: 46289 | L52: 46289 | M52: 46289 | N52: haviz.indra@elistec.com | O52: syafix.said@elistec.com | S52: athallah.bariq@elistec.com | T52: mohammad.danang@elistec.com
A53: =IF(OR(D53<>"", B53<>""), ROW()-1, "") -> 52 | B53: API Settlement Payment | D53: Menambahkan validasi payload pada endpoint store settlement guna memastikan nilai amount sesuai dengan total akumulasi settlement_amount serta count_trx cocok dengan jumlah item detail data. | E53: DONE | F53: HIGH | G53: ENHANCEMENT | H53: TCES | J53: 1 | K53: 46289 | L53: 46289 | M53: 46289 | N53: haviz.indra@elistec.com | O53: syafix.said@elistec.com | S53: athallah.bariq@elistec.com | T53: mohammad.danang@elistec.com | V53: Payload settlement rentan mengalami selisih finansial jika data detail terpotong saat transmisi, serta perbandingan angka desimal di PHP berisiko terkena floating-point precision error. | W53: Ditambahkan validasi kustom di SettlementStoreRequest untuk mencocokkan count_trx dengan ukuran array, serta memverifikasi nominal amount terhadap total akumulasi detail menggunakan komparasi bertoleransi presisi desimal.
A54: =IF(OR(D54<>"", B54<>""), ROW()-1, "") -> 53 | B54: API Settlement Payment | D54: Mengimplementasikan terminable middleware beserta model TcesIntegrationLog untuk mencatat audit trail API integrasi (Settlement dan Transaction v2), dengan penanganan sanitasi data dan request headers. | E54: DONE | F54: HIGH | G54: ENHANCEMENT | H54: TCES | J54: 1 | K54: 46290 | L54: 46290 | M54: 46290 | N54: haviz.indra@elistec.com | O54: syafix.said@elistec.com | S54: athallah.bariq@elistec.com | T54: mohammad.danang@elistec.com | V54: Pencatatan audit trail lengkap (payload & response) berisiko menambah latensi respon API ke klien serta menimbulkan celah kebocoran data sensitif (seperti kredensial password, token Authorization, dan cookie). | W54: Menggunakan terminable middleware (method terminate()) agar pencatatan log dieksekusi di background setelah respon terkirim ke klien (tanpa menambah latensi), serta menerapkan sanitasi otomatis (masking ********) pada data sensitif sebelum disimpan ke tabel tces_integration_log.
A55: =IF(OR(D55<>"", B55<>""), ROW()-1, "") -> 54 | B55: API Settlement Payment | D55: Membantu QA dan BA Monitoring & Validasi Data di Database ketika melakukan testing integrasi API Settlement | E55: DONE | F55: MEDIUM | G55: ENHANCEMENT | H55: TCES | J55: 1 | K55: 46293 | L55: 46293 | M55: 46293 | N55: haviz.indra@elistec.com | O55: syafix.said@elistec.com | S55: athallah.bariq@elistec.com | T55: mohammad.danang@elistec.com
A56: =IF(OR(D56<>"", B56<>""), ROW()-1, "") -> 55 | B56: API Settlement Payment | D56: Meeting API Settlement Payment - Kelanjutan Data Stagging | E56: DONE | F56: HIGH | G56: ENHANCEMENT | H56: TCES | J56: 1 | K56: 46293 | L56: 46293 | M56: 46293 | N56: haviz.indra@elistec.com | O56: syafix.said@elistec.com | S56: athallah.bariq@elistec.com | T56: mohammad.danang@elistec.com
A57: =IF(OR(D57<>"", B57<>""), ROW()-1, "") -> 56 | B57: API Settlement Payment | D57: Menambahkan aturan validasi dengan menerapkan format string numerik dua desimal non-negatif untuk field finansial, validasi standar tanggal-waktu (rq_datetime dan settlement_date), serta memastikan keunikan setiap tx_id menggunakan aturan distinct. | E57: DONE | F57: HIGH | G57: ENHANCEMENT | H57: TCES | J57: 1 | K57: 46294 | L57: 46294 | M57: 46294 | N57: haviz.indra@elistec.com | O57: syafix.said@elistec.com | S57: athallah.bariq@elistec.com | T57: mohammad.danang@elistec.com | V57: Field finansial rentan menerima format desimal acak atau bernilai negatif, format tanggal antar field belum seragam, dan terdapat risiko duplikasi tx_id dalam satu batch array. | W57: Diterapkan validasi string numerik presisi 2 desimal non-negatif (regex & gte:0), standardisasi format tanggal (date_format), serta aturan distinct pada data.*.tx_id untuk memastikan keunikan data.
A58: =IF(OR(D58<>"", B58<>""), ROW()-1, "") -> 57 | B58: API Settlement Payment | D58: Membantu QA dan BA Monitoring & Validasi Data di Database ketika melakukan testing integrasi API Settlement | E58: DONE | F58: MEDIUM | G58: ENHANCEMENT | H58: TCES | J58: 1 | K58: 46294 | L58: 46294 | M58: 46294 | N58: haviz.indra@elistec.com | O58: syafix.said@elistec.com | S58: athallah.bariq@elistec.com | T58: mohammad.danang@elistec.com | V58: Proses enforce tidak berjalan karena terdapat data yang tidak sesuai dengan SAP sehingga dokumen accounting tidak terproses | W58: Melakukan follow-up ke mas Egy untuk dilakukan perbaikan data
A59: =IF(OR(D59<>"", B59<>""), ROW()-1, "") -> 58 | B59: API Settlement Payment | D59: Melakukan sinkronisasi codebase dengan dokumen TSD bersama Technical Writter | E59: DONE | F59: MEDIUM | G59: ENHANCEMENT | H59: TCES | J59: 1 | K59: 46295 | L59: 46295 | M59: 46295 | N59: haviz.indra@elistec.com | O59: syafix.said@elistec.com | S59: athallah.bariq@elistec.com | T59: mohammad.danang@elistec.com
A60: =IF(OR(D60<>"", B60<>""), ROW()-1, "") -> 59 | B60: API Settlement Payment | D60: Membantu QA dan BA Monitoring & Validasi Data di Database ketika melakukan testing integrasi API Settlement | E60: DONE | F60: MEDIUM | G60: ENHANCEMENT | H60: TCES | J60: 1 | K60: 46295 | L60: 46295 | M60: 46295 | N60: haviz.indra@elistec.com | O60: syafix.said@elistec.com | S60: athallah.bariq@elistec.com | T60: mohammad.danang@elistec.com | V60: Proses enforce tidak berjalan karena terdapat data yang tidak sesuai dengan SAP sehingga dokumen accounting tidak terproses | W60: Melakukan follow-up ke mas Egy untuk dilakukan perbaikan data
A61: =IF(OR(D61<>"", B61<>""), ROW()-1, "") -> 60 | B61: API Settlement Payment | D61: Membantu QA dan BA Monitoring & Validasi Data di Database ketika melakukan testing integrasi API Settlement | E61: DONE | F61: MEDIUM | G61: ENHANCEMENT | H61: TCES | J61: 1 | K61: 46296 | L61: 46297 | M61: 46297 | N61: haviz.indra@elistec.com | O61: syafix.said@elistec.com | S61: athallah.bariq@elistec.com | T61: mohammad.danang@elistec.com | V61: Proses enforce tidak berjalan karena terdapat data yang tidak sesuai dengan SAP sehingga dokumen accounting tidak terproses | W61: Melakukan follow-up ke mas Egy untuk dilakukan perbaikan data
A62: =IF(OR(D62<>"", B62<>""), ROW()-1, "") -> 61 | B62: API Settlement Payment | D62: Menyiapkan skenario untuk batas retry untuk scheduler syncMissingSettlementDocs() agar tidak terus menerus menarik data terupdate jika sudah melebihi batas yang ditentukan. | E62: DONE | F62: HIGH | G62: ENHANCEMENT | H62: TCES | J62: 1 | K62: 46300 | L62: 46300 | M62: 46300 | N62: haviz.indra@elistec.com | O62: syafix.said@elistec.com | S62: athallah.bariq@elistec.com | T62: mohammad.danang@elistec.com
A63: =IF(OR(D63<>"", B63<>""), ROW()-1, "") -> 62 | B63: API Settlement Payment | D63: Implementasi batas retry scheduler syncMissingSettlementDocs() max 7hari | E63: DONE | F63: HIGH | G63: ENHANCEMENT | H63: TCES | J63: 1 | K63: 46301 | L63: 46302 | M63: 46302 | N63: haviz.indra@elistec.com | O63: syafix.said@elistec.com | S63: athallah.bariq@elistec.com | T63: mohammad.danang@elistec.com | V63: Scheduler sebelumnya memproses seluruh data lama tanpa batas waktu sehingga membebani database dengan data yang gagal permanen, serta perbandingan awal berbasis timestamp (jam/menit) berisiko memotong transaksi yang dibuat di hari H-7. | W63: Menambahkan filter whereDate('created_at', '>=', ...) agar pemindaian dibatasi murni pada tanggal 7 hari terakhir (mengabaikan jam), dengan pengecualian bypass otomatis jika parameter rq_uuid dispesifikasikan untuk kebutuhan penanganan manual.
A64: =IF(OR(D64<>"", B64<>""), ROW()-1, "") -> 63 | B64: Integrasi TCES Claim - BengkelNet | D64: Meeting Integrasi Claim & Settlement TCES x Bengkel.net x Tugu | E64: DONE | F64: HIGH | G64: ENHANCEMENT | H64: TCES | J64: 1 | K64: 46301 | L64: 46301 | M64: 46301 | N64: haviz.indra@elistec.com | O64: syafix.said@elistec.com | S64: athallah.bariq@elistec.com | T64: mohammad.danang@elistec.com
A65: =IF(OR(D65<>"", B65<>""), ROW()-1, "") -> 64 | B65: API Settlement Payment | D65: Membantu QA dan BA Monitoring & Validasi Data di Database ketika melakukan testing integrasi API Settlement sekaligus testing batas scheduler syncMissingSettlementDocs() | E65: DONE | F65: MEDIUM | G65: ENHANCEMENT | H65: TCES | J65: 1 | K65: 46302 | L65: 46302 | M65: 46302 | N65: haviz.indra@elistec.com | O65: syafix.said@elistec.com | S65: athallah.bariq@elistec.com | T65: mohammad.danang@elistec.com
A66: =IF(OR(D66<>"", B66<>""), ROW()-1, "") -> 65 | B66: API Settlement Payment | D66: Melakukan validasi pada dokumen TSD agar sesuai dengan codebase yang diimplementasikan | E66: DONE | F66: MEDIUM | G66: ENHANCEMENT | H66: TCES | J66: 1 | K66: 46303 | L66: 46303 | M66: 46303 | N66: haviz.indra@elistec.com | O66: syafix.said@elistec.com | S66: athallah.bariq@elistec.com | T66: mohammad.danang@elistec.com
A67: =IF(OR(D67<>"", B67<>""), ROW()-1, "") -> 66 | B67: API Settlement Payment | D67: Implementasi filter tanggal sinkronisasi missing settlement menjadi 5 hari yang dapat dikonfigurasi secara dinamis melalui .env (SETTLEMENT_SYNC_DAYS) beserta penyelarasan pada service dan command terkait | E67: DONE | F67: HIGH | G67: ENHANCEMENT | H67: TCES | J67: 1 | K67: 46304 | L67: 46304 | M67: 46304 | N67: haviz.indra@elistec.com | O67: syafix.said@elistec.com | S67: athallah.bariq@elistec.com | T67: mohammad.danang@elistec.com | V67: Nilai batas hari sinkronisasi sebelumnya di-hardcode pada kode program sehingga tidak fleksibel saat ada perubahan requirement dari klien, serta berisiko null jika membaca .env secara langsung saat konfigurasi di-cache. | W67: Parameter batas hari dipindahkan ke variabel .env (SETTLEMENT_SYNC_DAYS) dan didaftarkan melalui config/services.php, sehingga batas hari dapat diubah sewaktu-waktu dengan mudah dan tetap aman saat dijalankan di server production.
A68: =IF(OR(D68<>"", B68<>""), ROW()-1, "") -> 67 | B68: VIRTUAL ACCOUNT | D68: Melakukan riset mengenai deployment .NET ke GCP | E68: IN_PROGRESS | F68: MEDIUM | G68: ENHANCEMENT | H68: TCES | J68: 0.2 | K68: 46307 | L68: 46311 | N68: haviz.indra@elistec.com | O68: syafix.said@elistec.com | S68: athallah.bariq@elistec.com | T68: syifa.kurnia@elistec.com
A69: =IF(OR(D69<>"", B69<>""), ROW()-1, "") -> 68 | B69: API Settlement Payment | D69: Melakukan validasi dan sinkronisasi pada dokumen FSD agar sesuai dengan codebase yang diimplementasikan | E69: DONE | F69: MEDIUM | G69: ENHANCEMENT | H69: TCES | J69: 1 | K69: 46308 | L69: 46308 | M69: 46308 | N69: haviz.indra@elistec.com | O69: syafix.said@elistec.com | S69: athallah.bariq@elistec.com | T69: syifa.kurnia@elistec.com
A70: =IF(OR(D70<>"", B70<>""), ROW()-1, "") -> 69 | B70: Integrasi TCES TICS | D70: Melakukan perbaikan pada case false positive di middleware IntegrationCryptoVerifyService ketika kondisi payload tidak memiliki atribut insured namun tetap menjalankan proses decrypt yang seharusnya dilewati | E70: DONE | F70: MEDIUM | G70: ENHANCEMENT | H70: TCES | J70: 1 | K70: 46309 | L70: 46309 | M70: 46309 | N70: haviz.indra@elistec.com | O70: syafix.said@elistec.com | S70: athallah.bariq@elistec.com | T70: syifa.kurnia@elistec.com | V70: Middleware kriptografi mewajibkan keberadaan objek insured, padahal payload transaksi settlement tidak memiliki objek tersebut sehingga selalu memicu error log palsu. | W70: Proses dekripsi insured diubah menjadi kondisional sehingga request settlement yang valid langsung ditandai sukses tanpa melempar exception atau mencemari log.
A71: =IF(OR(D71<>"", B71<>""), ROW()-1, "") -> 70 | B71: Integrasi TCES TICS | D71: Sanitasi Error code 500 pada endpoint transaksi dan settlement | E71: DONE | F71: MEDIUM | G71: ENHANCEMENT | H71: TCES | J71: 1 | K71: 46310 | L71: 46310 | M71: 46310 | N71: haviz.indra@elistec.com | O71: syafix.said@elistec.com | S71: athallah.bariq@elistec.com | T71: syifa.kurnia@elistec.com | V71: Pesan error $e->getMessage() dikembalikan langsung ke respon HTTP 500 sehingga berisiko mengekspos detail teknis internal dan query database ke pihak luar. | W71: Respon HTTP 500 disanitasi dengan pesan generik yang aman bagi klien, sedangkan detail exception lengkap dicatat secara privat ke log internal aplikasi.
A72: =IF(OR(D72<>"", B72<>""), ROW()-1, "") -> 71 | B72: Integrasi TCES TICS | D72: Menghapus Kunci Privat RSA yang Tertulis Langsung pada Berkas Konfigurasi Git. Pengamanan Sistem Kriptografi Kini Dialihkan ke Variabel Environment Menggunakan Prinsip Fail-Closed. | E72: DONE | F72: MEDIUM | G72: ENHANCEMENT | H72: TCES | J72: 1 | K72: 46310 | L72: 46310 | M72: 46310 | N72: haviz.indra@elistec.com | O72: syafix.said@elistec.com | S72: athallah.bariq@elistec.com | T72: syifa.kurnia@elistec.com | V72: Kunci privat RSA 2048-bit tertulis secara hardcoded di berkas config/integration.php sebagai fallback sehingga berisiko bocor melalui riwayat repositori Git. | W72: Nilai hardcoded dihapus seutuhnya dan dialihkan murni ke environment variable, serta diterapkan prinsip fail-closed agar sistem menolak berjalan jika kunci belum dikonfigurasi.
A73: =IF(OR(D73<>"", B73<>""), ROW()-1, "") -> 72 | B73: Integrasi TCES TICS | D73: Melakukan sinkronisasi pada dokumen TSD agar sesuai dengan codebase yang diimplementasikan | E73: DONE | F73: MEDIUM | G73: ENHANCEMENT | H73: TCES | J73: 1 | K73: 46311 | L73: 46311 | M73: 46311 | N73: haviz.indra@elistec.com | O73: syafix.said@elistec.com | S73: athallah.bariq@elistec.com | T73: syifa.kurnia@elistec.com | V73: Kunci privat RSA 2048-bit tertulis secara hardcoded di berkas config/integration.php sebagai fallback sehingga berisiko bocor melalui riwayat repositori Git. | W73: Nilai hardcoded dihapus seutuhnya dan dialihkan murni ke environment variable, serta diterapkan prinsip fail-closed agar sistem menolak berjalan jika kunci belum dikonfigurasi.
A74: 73 | B74: Integrasi TCES Claim - BengkelNet | D74: Mempelajari Dokumentasi API Bengkel.net Claim | E74: DONE | F74: MEDIUM | G74: ENHANCEMENT | H74: TCES | J74: 1 | K74: 46314 | L74: 46314 | M74: 46314 | N74: haviz.indra@elistec.com | O74: syafix.said@elistec.com | S74: athallah.bariq@elistec.com | T74: syifa.kurnia@elistec.com
A75: =IF(OR(D75<>"", B75<>""), ROW()-1, "") -> 74 | B75: Integrasi TCES Claim - BengkelNet | D75: Koordinasi dengan tim TCES (Mas Rifqi) terkait pembuatan endpoint untuk pengecekan Polis yang sudah ter-ekstraksi untuk melakukan claim ke bengkel.net | E75: DONE | F75: MEDIUM | G75: ENHANCEMENT | H75: TCES | J75: 1 | K75: 46315 | L75: 46315 | M75: 46315 | N75: haviz.indra@elistec.com | O75: syafix.said@elistec.com | S75: athallah.bariq@elistec.com | T75: syifa.kurnia@elistec.com | V75: Di TICS, data polis dari TCES perlu melewati tahap integrasi SAP dan proses ekstraksi dari tabel staging ke tabel utama (acceptance) via scheduler. Jika proses ini belum rampung (atau sempat pending saat service SAP UAT mati), polis belum terdaftar di tabel utama, sehingga klaim di bengkel.net merespons 'polis tidak ditemukan' | W75: Kami sepakat untuk menyediakan endpoint POST /api/v2/tics/policy/check-status untuk mem-populate dropdown pilihan nomor polis di halaman klaim, TCES bisa memfilter hanya polis yang is_claimable = true yang bisa dipilih untuk proses klaim.
A76: =IF(OR(D76<>"", B76<>""), ROW()-1, "") -> 75 | B76: Integrasi TCES Claim - BengkelNet | D76: Menyiapkan API Specification untuk Endpoint Policy Check bersama Technical Writer | E76: DONE | F76: MEDIUM | G76: ENHANCEMENT | H76: TCES | J76: 1 | K76: 46316 | L76: 46316 | M76: 46316 | N76: haviz.indra@elistec.com | O76: syafix.said@elistec.com | S76: athallah.bariq@elistec.com | T76: syifa.kurnia@elistec.com
A77: =IF(OR(D77<>"", B77<>""), ROW()-1, "") -> 76 | B77: Integrasi TCES Claim - BengkelNet | D77: Implementasi endpoint baru POST /api/v2/tics/policy/check-status untuk memeriksa kesiapan klaim polis secara bulk | E77: DONE | F77: HIGH | G77: ENHANCEMENT | H77: TCES | J77: 1 | K77: 46317 | L77: 46317 | M77: 46317 | N77: haviz.indra@elistec.com | O77: syafix.said@elistec.com | S77: athallah.bariq@elistec.com | T77: syifa.kurnia@elistec.com | V77: Di TICS, data polis dari TCES perlu melewati tahap integrasi SAP dan proses ekstraksi dari tabel staging ke tabel utama (acceptance) via scheduler. Jika proses ini belum rampung (atau sempat pending saat service SAP UAT mati), polis belum terdaftar di tabel utama, sehingga klaim di bengkel.net merespons 'polis tidak ditemukan' | W77: Menyediakan endpoint POST /api/v2/tics/policy/check-status untuk mem-populate dropdown pilihan nomor polis di halaman klaim, TCES bisa memfilter hanya polis yang is_claimable = true yang bisa dipilih untuk proses klaim.
A78: =IF(OR(D78<>"", B78<>""), ROW()-1, "") -> 77 | B78: Integrasi TCES Claim - BengkelNet | D78: Melakukan Meeting Progress bersama stakeholder | E78: DONE | F78: HIGH | G78: ENHANCEMENT | H78: TCES | J78: 1 | K78: 46318 | L78: 46318 | M78: 46318 | N78: haviz.indra@elistec.com | O78: syafix.said@elistec.com | S78: athallah.bariq@elistec.com | T78: syifa.kurnia@elistec.com
A79: =IF(OR(D79<>"", B79<>""), ROW()-1, "")
A80: =IF(OR(D80<>"", B80<>""), ROW()-1, "")
A81: =IF(OR(D81<>"", B81<>""), ROW()-1, "")
A82: =IF(OR(D82<>"", B82<>""), ROW()-1, "")
A83: =IF(OR(D83<>"", B83<>""), ROW()-1, "")
A84: =IF(OR(D84<>"", B84<>""), ROW()-1, "")
A85: =IF(OR(D85<>"", B85<>""), ROW()-1, "")
A86: =IF(OR(D86<>"", B86<>""), ROW()-1, "")
A87: =IF(OR(D87<>"", B87<>""), ROW()-1, "")
A88: =IF(OR(D88<>"", B88<>""), ROW()-1, "")
A89: =IF(OR(D89<>"", B89<>""), ROW()-1, "")
A90: =IF(OR(D90<>"", B90<>""), ROW()-1, "")
... A150: =IF(OR(D150<>"", B150<>""), ROW()-1, "")

Sheet Danang
A1: No. | B1: project_name | C1: requirement_code | D1: title | E1: status | F1: priority | G1: jenis_task | H1: module_name | I1: bug_type | J1: progress | K1: start_date | L1: due_date | M1: completed_date | N1: developer_emails | O1: ba_emails | P1: infra_emails | Q1: master_data_emails | R1: tester_emails | S1: technical_writer_emails | T1: quality_assurance_emails | U1: system_analyst_emails | V1: kendala | W1: solusi | X1: evidence | Y1: kode_task | Z1: Milestone
A2: =IF(OR(D2<>"", B2<>""), ROW()-1, "") -> 1 | B2: Integrasi TCES TICS | D2: Sharing knowledge mengenai sistem business flow TCIS dan TCES | E2: DONE | F2: HIGH | G2: NEW_APPLICATION | H2: TCES | J2: 1 | K2: 46239 | L2: 46239 | M2: 46239 | N2: haviz.indra@elistec.com | O2: syafix.said@elistec.com | S2: athallah.bariq@elistec.com | T2: mohammad.danang@elistec.com | W2: mempelajari business flow dari TCIS mengisi data di form quotation dan TECS mensimulasi perhitungan asuransi dan pengenalan produk-produk yang ada didalam TCES
A3: =IF(OR(D3<>"", B3<>""), ROW()-1, "") -> 2 | B3: Integrasi TCES TICS | D3: Melakukan Pengecekan TICS - Sanitize URL Evidance (QA) untuk selanjutnya dinaikkan ke tahap Production | E3: DONE | F3: HIGH | G3: ENHANCEMENT | H3: TCES | J3: 1 | K3: 46240 | L3: 46240 | M3: 46240 | N3: haviz.indra@elistec.com | O3: syafix.said@elistec.com | S3: athallah.bariq@elistec.com | T3: mohammad.danang@elistec.com | W3: memiliki hasil berupa dokumentasi testing step by step testing beserta actual result dan follow up hasil testing ke mas farhan untuk dinaikkan ke tahap production
A4: =IF(OR(D4<>"", B4<>""), ROW()-1, "") -> 3 | B4: Integrasi TCES TICS | D4: Membuat Test Case untuk kebutuhan pengujian testing API integration terdiri dari no test case, kategori, mode fitur, skenario, expected result, actual result, status testing | E4: DONE | F4: HIGH | G4: NEW_APPLICATION | H4: TCES | J4: 1 | K4: 46241 | L4: 46246 | M4: 46246 | N4: haviz.indra@elistec.com | O4: syafix.said@elistec.com | S4: athallah.bariq@elistec.com | T4: mohammad.danang@elistec.com | V4: membutuhkan requirment lebih detail terkait pembuatan test case | W4: Telah di lakukan permintaan meeting offline dengan tim vendor pada hari senin siang dengan membahas pembuatan test case dan test execution yang dilakukan untuk test API Integration
A5: =IF(OR(D5<>"", B5<>""), ROW()-1, "") -> 4 | B5: Integrasi TCES TICS | D5: Meeting membahas timeline flow testing dan cara kerja untuk membuat test case dan hit scenario integrasi TICS dan TECS | E5: DONE | F5: HIGH | G5: NEW_APPLICATION | H5: TCES | J5: 1 | K5: 46244 | L5: 46244 | M5: 46244 | N5: haviz.indra@elistec.com | O5: syafix.said@elistec.com | S5: athallah.bariq@elistec.com | T5: mohammad.danang@elistec.com | W5: membahas mulai dari flow business dari TCES dan agen portal dev Tugu untuk alur testing, mendapatkan dokumentasi testing, dan mendapatkan dokumentasi berupa BRD dari tim vendor
A6: =IF(OR(D6<>"", B6<>""), ROW()-1, "") -> 5 | B6: Integrasi TCES TICS | D6: Meeting mengenai testing flow produk TCES beserta penjelasan produk TCES | E6: DONE | F6: HIGH | G6: NEW_APPLICATION | H6: TCES | J6: 1 | K6: 46245 | L6: 46245 | M6: 46245 | N6: haviz.indra@elistec.com | O6: syafix.said@elistec.com | S6: athallah.bariq@elistec.com | T6: mohammad.danang@elistec.com | W6: meeting mengenai testing flow produk TCES mulai dari simulasi pembayaran premi dari tdrive, tride, dan produk tces lainnya
A7: =IF(OR(D7<>"", B7<>""), ROW()-1, "") -> 6 | B7: Integrasi TCES TICS | D7: Membuat Tes Case Pengujian API - Update Test case untuk API Integration dengan menambahkan sheet Information capture, dan menambahkan detail seperti remarks, tgl testing | E7: DONE | F7: HIGH | G7: ENHANCEMENT | H7: TCES | J7: 1 | K7: 46246 | L7: 46246 | M7: 46246 | N7: haviz.indra@elistec.com | O7: syafix.said@elistec.com | S7: athallah.bariq@elistec.com | T7: mohammad.danang@elistec.com | W7: pengecekkan dan penambahan test case untuk dokumentasi yang digunakan untuk menjalankan testing pada tanggal 18 Agustus 2026 mendatang
A8: =IF(OR(D8<>"", B8<>""), ROW()-1, "") -> 7 | B8: Integrasi TCES TICS | D8: Membuat Test Case Pengujian API - Update Test case untuk API Integration untuk menambahkan 3 skenario negative yaitu scenario Timestamp, signature, dan User-Id dengan masing-masing case invalid | E8: DONE | F8: HIGH | G8: ENHANCEMENT | H8: TCES | J8: 1 | K8: 46247 | L8: 46247 | M8: 46247 | N8: haviz.indra@elistec.com | O8: syafix.said@elistec.com | S8: athallah.bariq@elistec.com | T8: mohammad.danang@elistec.com | W8: menambahkan scenario condition pada test case API Integration menjadi 10 TC untuk kebutuhan testing pada tanggal 18 Agustus 2026 mendatang
A9: =IF(OR(D9<>"", B9<>""), ROW()-1, "") -> 8 | B9: Integrasi TCES TICS | D9: Melakukan simulasi hit scenario Test Case API Integration TCES TICS - testing penerapan signature, timestamp, dan user-id menggunakan postman | E9: DONE | F9: MEDIUM | G9: ENHANCEMENT | H9: TCES | J9: 1 | K9: 46248 | L9: 46248 | M9: 46248 | N9: haviz.indra@elistec.com | O9: syafix.said@elistec.com | S9: athallah.bariq@elistec.com | T9: mohammad.danang@elistec.com
A10: =IF(OR(D10<>"", B10<>""), ROW()-1, "") -> 9 | B10: Integrasi TCES TICS | D10: Membuat Test Case Pengujian API - Adjustment QA API Tracker TCES-TICS: Standarisasi Kolom Skenario (Payload/Expected Result) & Panduan Referensi HTTP | E10: DONE | F10: HIGH | G10: ENHANCEMENT | H10: TCES | J10: 1 | K10: 46252 | L10: 46252 | M10: 46252 | N10: haviz.indra@elistec.com | O10: syafix.said@elistec.com | S10: athallah.bariq@elistec.com | T10: mohammad.danang@elistec.com
A11: =IF(OR(D11<>"", B11<>""), ROW()-1, "") -> 10 | B11: Integrasi TCES TICS | D11: Melakukan approval Test Case Pengujian API TCES-TICS ke user untuk memvalidasi Test Case yang telah dibuat untuk selanjutnya bisa dilakukan execution testing | E11: DONE | F11: HIGH | G11: ENHANCEMENT | H11: TCES | J11: 1 | K11: 46253 | L11: 46253 | M11: 46253 | N11: haviz.indra@elistec.com | O11: syafix.said@elistec.com | S11: athallah.bariq@elistec.com | T11: mohammad.danang@elistec.com
A12: =IF(OR(D12<>"", B12<>""), ROW()-1, "") -> 11 | B12: Integrasi TCES TICS | D12: Menjalankan execute Test Case API Integration TCES - TICS menggunakan Postman untuk mengetahui hasil testing sesuai dengan expected yang diminta sesuai dengan skenario | E12: DONE | F12: HIGH | G12: ENHANCEMENT | H12: TCES | J12: 1 | K12: 46254 | L12: 46254 | M12: 46254 | N12: haviz.indra@elistec.com | O12: syafix.said@elistec.com | S12: athallah.bariq@elistec.com | T12: mohammad.danang@elistec.com
A13: =IF(OR(D13<>"", B13<>""), ROW()-1, "") -> 12 | B13: Integrasi TCES TICS | D13: Mereview test case yang sudah diexecute untuk memastikan hasil yang diterima sesuai dengan ekspektasi yang diminta dalam scenario | E13: DONE | F13: HIGH | G13: ENHANCEMENT | H13: TCES | J13: 1 | K13: 46255 | L13: 46255 | M13: 46255 | N13: haviz.indra@elistec.com | O13: syafix.said@elistec.com | S13: athallah.bariq@elistec.com | T13: mohammad.danang@elistec.com
A14: =IF(OR(D14<>"", B14<>""), ROW()-1, "") -> 13 | B14: Integrasi TCES TICS | D14: Melakukan meeting terkait progress review task yang sudah dikerjakan bersama tim dan stakeholder | E14: DONE | F14: HIGH | G14: ENHANCEMENT | H14: TCES | J14: 1 | K14: 46258 | L14: 46258 | M14: 46258 | N14: haviz.indra@elistec.com | O14: syafix.said@elistec.com | S14: athallah.bariq@elistec.com | T14: mohammad.danang@elistec.com
A15: =IF(OR(D15<>"", B15<>""), ROW()-1, "") -> 14 | B15: Integrasi TCES TICS | D15: Testing end-to-end fitur TCES dengan memastikan data nomor polis yang sudah terbentuk masuk kedalam TICS | E15: DONE | F15: HIGH | G15: ENHANCEMENT | H15: TCES | J15: 1 | K15: 46260 | L15: 46260 | M15: 46260 | N15: haviz.indra@elistec.com | O15: syafix.said@elistec.com | S15: athallah.bariq@elistec.com | T15: mohammad.danang@elistec.com
A16: =IF(OR(D16<>"", B16<>""), ROW()-1, "") -> 15 | B16: Integrasi TCES TICS | D16: Membuat test case untuk end-to-end TCES untuk produk Tride dan execute testing sampai terbentuk polis number | E16: DONE | F16: HIGH | G16: ENHANCEMENT | H16: TCES | J16: 1 | K16: 46261 | L16: 46261 | M16: 46261 | N16: haviz.indra@elistec.com | O16: syafix.said@elistec.com | S16: athallah.bariq@elistec.com | T16: mohammad.danang@elistec.com
A17: =IF(OR(D17<>"", B17<>""), ROW()-1, "") -> 16 | B17: Integrasi TCES TICS | D17: Membuat dan menjalankan test-case end-to-end TCES untuk produk Tride sampai terbentuk polis dan terintegrasi dengan TICS | E17: DONE | F17: HIGH | G17: ENHANCEMENT | H17: TCES | J17: 1 | K17: 46262 | L17: 46262 | M17: 46262 | N17: haviz.indra@elistec.com | O17: syafix.said@elistec.com | S17: athallah.bariq@elistec.com | T17: mohammad.danang@elistec.com
A18: =IF(OR(D18<>"", B18<>""), ROW()-1, "") -> 17 | B18: Integrasi TCES TICS | D18: Mengexecute testing produk T-Travella dan T-Property sampai terbentuk polis dan terdaftar di Payload | E18: DONE | F18: HIGH | G18: ENHANCEMENT | H18: TCES | J18: 1 | K18: 46265 | L18: 46265 | M18: 46265 | N18: haviz.indra@elistec.com | O18: syafix.said@elistec.com | S18: athallah.bariq@elistec.com | T18: mohammad.danang@elistec.com | W18: https://elistec1-my.sharepoint.com/:x:/g/personal/mohammad_danang_elistec_com/IQCvT__J-UIaQLm3PvL_eUm2AUB4angj9Gfr0Kl7KGKrLvY?rtime=-PLRQm3-3kg&wdExp=TEAMS-TREATMENT&web=1
A19: =IF(OR(D19<>"", B19<>""), ROW()-1, "") -> 18 | B19: Integrasi TCES TICS | D19: Menjalankan execute Test Case Produk TCES TDrive secara end-to-end sampai data polis masuk kedalam TICS | E19: DONE | F19: HIGH | G19: ENHANCEMENT | H19: TCES | J19: 1 | K19: 46266 | L19: 46266 | M19: 46266 | N19: haviz.indra@elistec.com | O19: syafix.said@elistec.com | S19: athallah.bariq@elistec.com | T19: mohammad.danang@elistec.com | W19: https://elistec1-my.sharepoint.com/:w:/g/personal/athallah_bariq_elistec_com/IQB37tXK9ZlpQ5Y85-uIC9YJAWOGFZvYbnehNwwQkILeOJo?e=7SIuhQ
A20: =IF(OR(D20<>"", B20<>""), ROW()-1, "") -> 19 | B20: Integrasi TCES TICS | D20: Menjalankan execute Test Case Produk TCES TTravella secara end-to-end sampai data polis masuk kedalam TICS | E20: DONE | F20: HIGH | G20: ENHANCEMENT | H20: TCES | J20: 1 | K20: 46267 | L20: 46267 | M20: 46267 | N20: haviz.indra@elistec.com | O20: syafix.said@elistec.com | S20: athallah.bariq@elistec.com | T20: mohammad.danang@elistec.com | W20: https://elistec1-my.sharepoint.com/:x:/r/personal/athallah_bariq_elistec_com/_layouts/15/Doc.aspx?sourcedoc=%7B181A00B4-5EB8-4A43-BCDD-D6F2F97DB010%7D&file=Evidence%20Testing.xlsx&action=default&mobileredirect=true
A21: =IF(OR(D21<>"", B21<>""), ROW()-1, "") -> 20 | B21: Integrasi TCES TICS | D21: Menjalankan execute Test Case Produk TCES TFire secara end-to-end sampai data polis masuk kedalam TICS | E21: DONE | F21: HIGH | G21: ENHANCEMENT | H21: TCES | J21: 1 | K21: 46268 | L21: 46268 | M21: 46268 | N21: haviz.indra@elistec.com | O21: syafix.said@elistec.com | S21: athallah.bariq@elistec.com | T21: mohammad.danang@elistec.com | W21: https://elistec1-my.sharepoint.com/:x:/r/personal/athallah_bariq_elistec_com/_layouts/15/Doc.aspx?sourcedoc=%7B845FE71D-6A71-4558-A0D4-176D3FD6CD77%7D&file=Task%20Tracker%20-%20Update.xlsx&fromShare=true&action=default&mobileredirect=true
A22: =IF(OR(D22<>"", B22<>""), ROW()-1, "") -> 21 | B22: Integrasi TCES TICS | D22: Meeting sharing knowledge pengenalan aplikasi BAST TCES | E22: DONE | F22: HIGH | G22: ENHANCEMENT | H22: TCES | J22: 1 | K22: 46269 | L22: 46269 | M22: 46269 | N22: haviz.indra@elistec.com | O22: syafix.said@elistec.com | S22: athallah.bariq@elistec.com | T22: mohammad.danang@elistec.com | W22: https://cms-dev.tugu.com/dashboard/voucher/type
A23: =IF(OR(D23<>"", B23<>""), ROW()-1, "") -> 22 | B23: Integrasi TCES TICS | D23: Meeting Review Progress Bersama Seluruh Tim ERP Tugu | E23: DONE | F23: HIGH | G23: ENHANCEMENT | H23: TCES | J23: 1 | K23: 46272 | L23: 46272 | M23: 46272 | N23: haviz.indra@elistec.com | O23: syafix.said@elistec.com | S23: athallah.bariq@elistec.com | T23: mohammad.danang@elistec.com
A24: =IF(OR(D24<>"", B24<>""), ROW()-1, "") -> 23 | B24: Integrasi TCES TICS | D24: Testing end-to-end produk MV (Tride dan Tdrive) di TCES sampai masuk kedalam TICS menggunakan BP yang sudah terdaftar | E24: DONE | F24: HIGH | G24: ENHANCEMENT | H24: TCES | J24: 1 | K24: 46272 | L24: 46273 | M24: 46273 | N24: haviz.indra@elistec.com | O24: syafix.said@elistec.com | S24: athallah.bariq@elistec.com | T24: mohammad.danang@elistec.com
A25: =IF(OR(D25<>"", B25<>""), ROW()-1, "") -> 24 | B25: Integrasi TCES TICS | D25: Testing end-to-end produk MV (Tride dan Tdrive) di TCES sampai masuk kedalam TICS menggunakan BP yang belum terdaftar | E25: DONE | F25: HIGH | G25: ENHANCEMENT | H25: TCES | J25: 1 | K25: 46274 | L25: 46274 | M25: 46274 | N25: haviz.indra@elistec.com | O25: syafix.said@elistec.com | S25: athallah.bariq@elistec.com | T25: mohammad.danang@elistec.com
A26: =IF(OR(D26<>"", B26<>""), ROW()-1, "") -> 25 | B26: Integrasi TCES TICS | D26: Retest produk MV (Tride dan Tdrive) secara end-to-end untuk memastikan promo diskon sudah masuk di TCES dan TICS | E26: DONE | F26: HIGH | G26: ENHANCEMENT | H26: TCES | J26: 1 | K26: 46275 | L26: 46275 | M26: 46275 | N26: haviz.indra@elistec.com | O26: syafix.said@elistec.com | S26: athallah.bariq@elistec.com | T26: mohammad.danang@elistec.com
A27: =IF(OR(D27<>"", B27<>""), ROW()-1, "") -> 26 | B27: Integrasi TCES TICS | D27: Lanjutan : Retest produk MV (Tride dan Tdrive) secara end-to-end untuk memastikan promo diskon sudah masuk di TCES dan TICS | E27: DONE | F27: HIGH | G27: ENHANCEMENT | H27: TCES | J27: 1 | K27: 46276 | L27: 46276 | M27: 46276 | N27: haviz.indra@elistec.com | O27: syafix.said@elistec.com | S27: athallah.bariq@elistec.com | T27: mohammad.danang@elistec.com | W27: Testing TDrive : https://elistec1-my.sharepoint.com/:x:/g/personal/athallah_bariq_elistec_com/IQC0ABoYuF5DSrzd1vL5fbAQAczJ-qS0H4UPLKfqLHCTvkU?e=y4y76T Testing TRide : https://elistec1-my.sharepoint.com/:x:/g/personal/athallah_bariq_elistec_com/IQDDQ6ijwzFLS5uCjht0pVR2AVfjYFaSZGKwRKnXbTVNDZ0?e=wEetzn
A28: =IF(OR(D28<>"", B28<>""), ROW()-1, "") -> 27 | B28: Integrasi TCES TICS | D28: Lanjutan : Testing end-to-end produk MV (Tdrive) di TCES sampai masuk kedalam TICS menggunakan BP yang belum terdaftar | E28: DONE | F28: HIGH | G28: ENHANCEMENT | H28: TCES | J28: 1 | K28: 46279 | L28: 46279 | M28: 46279 | N28: haviz.indra@elistec.com | O28: syafix.said@elistec.com | S28: athallah.bariq@elistec.com | T28: mohammad.danang@elistec.com | W28: Testing TDrive : https://elistec1-my.sharepoint.com/:x:/g/personal/athallah_bariq_elistec_com/IQC0ABoYuF5DSrzd1vL5fbAQAczJ-qS0H4UPLKfqLHCTvkU?e=y4y76T
A29: 28 | B29: Integrasi TCES TICS | D29: Lanjutan : Testing end-to-end produk MV (TRide) di TCES sampai masuk kedalam TICS menggunakan BP yang belum terdaftar | E29: DONE | F29: HIGH | G29: ENHANCEMENT | H29: TCES | J29: 1 | K29: 46280 | L29: 46280 | M29: 46280 | N29: haviz.indra@elistec.com | O29: syafix.said@elistec.com | S29: athallah.bariq@elistec.com | T29: mohammad.danang@elistec.com | W29: Testing T-Ride.xlsx
A30: 29 | B30: Integrasi TCES TICS | D30: Lanjutan : Retesting end-to-end produk MV (TRide) di TCES sampai masuk kedalam TICS menggunakan BP yang belum terdaftar | E30: DONE | F30: HIGH | G30: ENHANCEMENT | H30: TCES | J30: 1 | K30: 46281 | L30: 46281 | M30: 46281 | N30: haviz.indra@elistec.com | O30: syafix.said@elistec.com | S30: athallah.bariq@elistec.com | T30: mohammad.danang@elistec.com
A31: 30 | B31: Integrasi TCES TICS | D31: ReTesting status blocked end-to-end produk TRide dari TCES sampai polis tergenerate ke TICS karena polis belum difixing di Stagging dan SAP | E31: DONE | F31: HIGH | G31: ENHANCEMENT | H31: TCES | J31: 1 | K31: 46282 | L31: 46282 | M31: 46282 | N31: haviz.indra@elistec.com | O31: syafix.said@elistec.com | S31: athallah.bariq@elistec.com | T31: mohammad.danang@elistec.com
A32: 31 | B32: Integrasi TCES TICS | D32: Transfer Knowledge Accessment Integrasi di TCES | E32: DONE | F32: HIGH | G32: ENHANCEMENT | H32: TCES | J32: 1 | K32: 46283 | L32: 46283 | M32: 46283 | N32: haviz.indra@elistec.com | O32: syafix.said@elistec.com | S32: athallah.bariq@elistec.com | T32: mohammad.danang@elistec.com | W32: 18 September 2026 - Meeting Transfer Knowledge TCES.docx
A33: 32 | B33: Integrasi TCES TICS | D33: Membuat Test case scenario untuk pembuatan quotation number di Form Quotation TICS | E33: DONE | F33: HIGH | G33: ENHANCEMENT | H33: TCES | J33: 1 | K33: 46286 | L33: 46286 | M33: 46286 | N33: haviz.indra@elistec.com | O33: syafix.said@elistec.com | S33: athallah.bariq@elistec.com | T33: mohammad.danang@elistec.com
A34: 33 | B34: Integrasi TCES TICS | D34: testing terkait periode closing, dengan transaction date dan bill date sudah sesuai. | E34: DONE | F34: HIGH | G34: ENHANCEMENT | H34: TCES | J34: 1 | K34: 46287 | L34: 46287 | M34: 46287 | N34: haviz.indra@elistec.com | O34: syafix.said@elistec.com | S34: athallah.bariq@elistec.com | T34: mohammad.danang@elistec.com | W34: Testing untuk skenario: Manual input individual Manual input multiple Manual input open cover Upload multiple, bulk enforce Upload open cover, bulk enforce
A35: 34 | B35: Integrasi TCES TICS | D35: [Lanjutan] testing terkait periode closing, dengan transaction date dan bill date sudah sesuai (diatur ketanggal 20261001). | E35: DONE | F35: HIGH | G35: ENHANCEMENT | H35: TCES | J35: 1 | K35: 46288 | L35: 46288 | M35: 46288 | N35: haviz.indra@elistec.com | O35: syafix.said@elistec.com | S35: athallah.bariq@elistec.com | T35: mohammad.danang@elistec.com | W35: Testing untuk skenario: Manual input individual Manual input multiple Manual input open cover Upload multiple, bulk enforce Upload open cover, bulk enforce
A36: =IF(OR(Syafix!D75<>"", Syafix!B75<>""), ROW()-1, "") -> 35 | B36: Integrasi TCES TICS | D36: Menambahkan matriks policy type untuk test case scenario TICS | E36: DONE | F36: HIGH | G36: ENHANCEMENT | H36: TCES | J36: 1 | K36: 46289 | L36: 46289 | M36: 46289 | N36: haviz.indra@elistec.com | O36: syafix.said@elistec.com | S36: athallah.bariq@elistec.com | T36: mohammad.danang@elistec.com
A37: =IF(OR(Syafix!D76<>"", Syafix!B76<>""), ROW()-1, "") -> 36 | B37: Integrasi TCES TICS | D37: Menjalankan Scenario testing QA Tracker Settlement API TCES | E37: DONE | F37: HIGH | G37: ENHANCEMENT | H37: TCES | J37: 1 | K37: 46290 | L37: 46290 | M37: 46290 | N37: haviz.indra@elistec.com | O37: syafix.said@elistec.com | S37: athallah.bariq@elistec.com | T37: mohammad.danang@elistec.com | W37: menjalankan TC-POS-001 https://elistec1-my.sharepoint.com/:x:/g/personal/syafix_said_elistec_com/IQCAjPGo_c1sRJlZsjmtI8BEAZgWIzwscBGDEBZih6ngtN0?e=3bP0WZ&wdExp=TEAMS-TREATMENT&web=1
A38: 37 | B38: Integrasi TCES TICS | D38: Menjalankan Scenario Negative testing QA Tracker Settlement API TCES | E38: DONE | F38: HIGH | G38: ENHANCEMENT | H38: TCES | J38: 1 | K38: 46293 | L38: 46294 | M38: 46294 | N38: haviz.indra@elistec.com | O38: syafix.said@elistec.com | S38: athallah.bariq@elistec.com | T38: mohammad.danang@elistec.com | W38: https://elistec1-my.sharepoint.com/:x:/g/personal/syafix_said_elistec_com/IQCAjPGo_c1sRJlZsjmtI8BEAZgWIzwscBGDEBZih6ngtN0?e=3bP0WZ&wdExp=TEAMS-TREATMENT&web=1
A39: 38 | B39: Integrasi TCES TICS | D39: Meeting API Settlement Payment - Kelanjutan Data Stagging | E39: DONE | F39: HIGH | G39: ENHANCEMENT | H39: TCES | J39: 1 | K39: 46293 | L39: 46293 | M39: 46293 | N39: haviz.indra@elistec.com | O39: syafix.said@elistec.com | S39: athallah.bariq@elistec.com | T39: mohammad.danang@elistec.com | W39: https://elistec1-my.sharepoint.com/:x:/g/personal/syafix_said_elistec_com/IQCAjPGo_c1sRJlZsjmtI8BEAZgWIzwscBGDEBZih6ngtN0?e=3bP0WZ&wdExp=TEAMS-TREATMENT&web=1
A40: 39 | B40: Integrasi TCES TICS | D40: Menjalankan Scenario Positive testing QA Tracker Settlement API TCES | E40: DONE | F40: HIGH | G40: ENHANCEMENT | H40: TCES | J40: 1 | K40: 46295 | L40: 46295 | M40: 46295 | N40: haviz.indra@elistec.com | O40: syafix.said@elistec.com | S40: athallah.bariq@elistec.com | T40: mohammad.danang@elistec.com | W40: https://elistec1-my.sharepoint.com/:x:/g/personal/syafix_said_elistec_com/IQCAjPGo_c1sRJlZsjmtI8BEAZgWIzwscBGDEBZih6ngtN0?e=3bP0WZ&wdExp=TEAMS-TREATMENT&web=1
A41: 40 | B41: Integrasi TCES TICS | D41: Menjalankan testing Settlement API TCES secara end-to-end | E41: DONE | F41: HIGH | G41: ENHANCEMENT | H41: TCES | J41: 1 | K41: 46296 | L41: 46296 | M41: 46296 | N41: haviz.indra@elistec.com | O41: syafix.said@elistec.com | S41: athallah.bariq@elistec.com | T41: mohammad.danang@elistec.com
A42: =IF(OR(D42<>"", B42<>""), ROW()-1, "") -> 41 | B42: Integrasi TCES TICS | D42: (Lanjutan) Menjalankan testing Settlement API TCES secara end-to-end | E42: DONE | F42: HIGH | G42: ENHANCEMENT | H42: TCES | J42: 1 | K42: 46297 | L42: 46297 | M42: 46297 | N42: haviz.indra@elistec.com | O42: syafix.said@elistec.com | S42: athallah.bariq@elistec.com | T42: mohammad.danang@elistec.com
A43: 42 | B43: Integrasi TCES TICS | D43: Execute testing API Settlement melakukan enforce dan settlement polis MV dari TCES | E43: DONE | F43: HIGH | G43: ENHANCEMENT | H43: TCES | J43: 1 | K43: 46300 | L43: 46300 | M43: 46300 | N43: haviz.indra@elistec.com | O43: syafix.said@elistec.com | S43: athallah.bariq@elistec.com | T43: mohammad.danang@elistec.com | V43: pilih paket Plus dan Ultimate diperluasan "Tanggung Jawab Hukum terhadap Pihak Ketiga" ini nilai defaultnya seharusnya bukan 0 | W43: sedang dilakukan perbaikan oleh mas riefqi selaku tim TCES | X43: https://jam.dev/c/31bd2319-c95b-4f29-8ee6-22116f6c1755
A44: 43 | B44: Integrasi TCES TICS | D44: Melakukan Meeting terkait Settlement TCES - TICS - Bengkel Net | E44: DONE | F44: HIGH | G44: ENHANCEMENT | H44: TCES | J44: 1 | K44: 46301 | L44: 46301 | M44: 46301 | N44: haviz.indra@elistec.com | O44: syafix.said@elistec.com | S44: athallah.bariq@elistec.com | T44: mohammad.danang@elistec.com
A45: 44 | B45: Integrasi TCES TICS | D45: Lanjutan testing Settlement API TCES untuk enforce polis MV | E45: DONE | F45: HIGH | G45: ENHANCEMENT | H45: TCES | J45: 1 | K45: 46301 | L45: 46301 | M45: 46301 | N45: haviz.indra@elistec.com | O45: syafix.said@elistec.com | S45: athallah.bariq@elistec.com | T45: mohammad.danang@elistec.com | V45: list dropdown harga pada TPL lebih diperbanyak listnya dan jika memilih paket Plus Ultimate pada bagian TPL harus klik list bawah dulu baru pilih yang atas | W45: sedang dilakukan perbaikan oleh mas riefqi selaku tim TCES
A46: 45 | B46: Integrasi TCES TICS | D46: Membuat data polis TCES MV untuk proses enforce dan settlement API | E46: DONE | F46: HIGH | G46: ENHANCEMENT | H46: TCES | J46: 1 | K46: 46302 | L46: 46302 | M46: 46302 | N46: haviz.indra@elistec.com | O46: syafix.said@elistec.com | S46: athallah.bariq@elistec.com | T46: mohammad.danang@elistec.com
A47: 46 | B47: Integrasi TCES TICS | D47: Membuat data polis TCES non MV untuk proses enforce dan settlement API | E47: DONE | F47: HIGH | G47: ENHANCEMENT | H47: TCES | J47: 1 | K47: 46303 | L47: 46303 | M47: 46303 | N47: haviz.indra@elistec.com | O47: syafix.said@elistec.com | S47: athallah.bariq@elistec.com | T47: mohammad.danang@elistec.com
A48: 47 | B48: Integrasi TCES TICS | D48: Transfer Knowledge untuk handover pekerjaan ke anak baru | E48: DONE | F48: HIGH | G48: ENHANCEMENT | H48: TCES | J48: 1 | K48: 46304 | L48: 46304 | M48: 46304 | N48: haviz.indra@elistec.com | O48: syafix.said@elistec.com | S48: athallah.bariq@elistec.com | T48: mohammad.danang@elistec.com
A49: =IF(OR(D49<>"", B49<>""), ROW()-1, "")
A50: =IF(OR(D50<>"", B50<>""), ROW()-1, "")
A51: =IF(OR(D51<>"", B51<>""), ROW()-1, "")
A52: =IF(OR(D52<>"", B52<>""), ROW()-1, "")
A53: =IF(OR(D53<>"", B53<>""), ROW()-1, "")
A54: =IF(OR(D54<>"", B54<>""), ROW()-1, "")
A55: =IF(OR(D55<>"", B55<>""), ROW()-1, "")
A56: =IF(OR(D56<>"", B56<>""), ROW()-1, "")
A57: =IF(OR(D57<>"", B57<>""), ROW()-1, "")
A58: =IF(OR(D58<>"", B58<>""), ROW()-1, "")
A59: =IF(OR(D59<>"", B59<>""), ROW()-1, "")
A60: =IF(OR(D60<>"", B60<>""), ROW()-1, "")
... A150: =IF(OR(D150<>"", B150<>""), ROW()-1, "")

Sheet Atha
A1: No. | B1: project_name | C1: requirement_code | D1: title | E1: status | F1: priority | G1: jenis_task | H1: module_name | I1: bug_type | J1: progress | K1: start_date | L1: due_date | M1: completed_date | N1: developer_emails | O1: ba_emails | P1: infra_emails | Q1: master_data_emails | R1: tester_emails | S1: technical_writer_emails | T1: quality_assurance_emails | U1: system_analyst_emails | V1: kendala | W1: solusi | X1: evidence | Y1: kode_task | Z1: Milestone
A2: =IF(OR(D2<>"", B2<>""), ROW()-1, "") -> 1 | B2: Integrasi TCES TICS | D2: Membuat Dokumen Hasil Technical Meeting, Mendalami Dokumen TCES Integration Guide | E2: DONE | F2: HIGH | G2: ENHANCEMENT | H2: TCES | J2: 1 | K2: 46239 | L2: 46239 | M2: 46239 | N2: haviz.indra@elistec.com | O2: syafix.said@elistec.com | S2: athallah.bariq@elistec.com | T2: mohammad.danang@elistec.com | W2: Membuat dokumen terkait penjelasan dan panduan dari hasil technical meeting pembahasan integration TCES TICS, Mendalami Technical Integration Guide dan Mapping Product TCES Document
A3: =IF(OR(D3<>"", B3<>""), ROW()-1, "") -> 2 | B3: Integrasi TCES TICS | D3: Membuat Dokumen Project Management Untuk Tim | E3: DONE | F3: HIGH | G3: ENHANCEMENT | H3: TCES | J3: 1 | K3: 46240 | L3: 46240 | M3: 46240 | N3: haviz.indra@elistec.com | O3: syafix.said@elistec.com | S3: athallah.bariq@elistec.com | T3: mohammad.danang@elistec.com
A4: =IF(OR(D4<>"", B4<>""), ROW()-1, "") -> 3 | B4: Integrasi TCES TICS | D4: Menambahkan Data Pada Dokumen Project Management Tim, Mempersiapkan Technical Document | E4: DONE | F4: MEDIUM | G4: ENHANCEMENT | H4: TCES | J4: 1 | K4: 46241 | L4: 46247 | M4: 46247 | N4: haviz.indra@elistec.com | O4: syafix.said@elistec.com | S4: athallah.bariq@elistec.com | T4: mohammad.danang@elistec.com | V4: Terdapat data di dokumen project management yang kurang lengkap, membutuhkan informasi lebih lanjut mengenai requirement technical document | W4: Melengkapi data di dokumen project management, akan diadakan meeting pembahasan requirement technical document lebih lanjut
A5: =IF(OR(D5<>"", B5<>""), ROW()-1, "") -> 4 | B5: Integrasi TCES TICS | D5: Meeting Terkait Penjelasan Teknis Proses Dokumentasi Integrasi TCES TICS | E5: DONE | F5: HIGH | G5: ENHANCEMENT | H5: TCES | J5: 1 | K5: 46244 | L5: 46244 | M5: 46244 | N5: haviz.indra@elistec.com | O5: syafix.said@elistec.com | S5: athallah.bariq@elistec.com | T5: mohammad.danang@elistec.com
A6: =IF(OR(D6<>"", B6<>""), ROW()-1, "") -> 5 | B6: Integrasi TCES TICS | D6: Membuat Template Functional Specification Document (FSD) | E6: DONE | F6: MEDIUM | G6: ENHANCEMENT | H6: TCES | J6: 1 | K6: 46244 | L6: 46248 | M6: 46248 | N6: haviz.indra@elistec.com | O6: syafix.said@elistec.com | S6: athallah.bariq@elistec.com | T6: mohammad.danang@elistec.com
A7: =IF(OR(D7<>"", B7<>""), ROW()-1, "") -> 6 | B7: Integrasi TCES TICS | D7: Membuat Template Technical Specification Document (TSD) | E7: DONE | F7: MEDIUM | G7: ENHANCEMENT | H7: TCES | J7: 1 | K7: 46244 | L7: 46248 | M7: 46248 | N7: haviz.indra@elistec.com | O7: syafix.said@elistec.com | S7: athallah.bariq@elistec.com | T7: mohammad.danang@elistec.com
A8: =IF(OR(D8<>"", B8<>""), ROW()-1, "") -> 7 | B8: Integrasi TCES TICS | D8: Sharing Knowledge Penggunaan dan Alur Proses Aplikasi TCES - Pembelian Phase | E8: DONE | F8: HIGH | G8: ENHANCEMENT | H8: TCES | J8: 1 | K8: 46245 | L8: 46245 | M8: 46245 | N8: haviz.indra@elistec.com | O8: syafix.said@elistec.com | S8: athallah.bariq@elistec.com | T8: mohammad.danang@elistec.com
A9: =IF(OR(D9<>"", B9<>""), ROW()-1, "") -> 8 | B9: Integrasi TCES TICS | D9: Membuat Dokumen FSD - Menambahkan Penulisan Terkait Document Overview | E9: DONE | F9: MEDIUM | G9: ENHANCEMENT | H9: TCES | J9: 1 | K9: 46248 | L9: 46252 | M9: 46252 | N9: haviz.indra@elistec.com | O9: syafix.said@elistec.com | S9: athallah.bariq@elistec.com | T9: mohammad.danang@elistec.com | W9: Menambahkan detail penulisan pada FSD (Functional Specification Document) terkait dengan document overview yang terdiri dari latar belakang, tujuan, ruang lingkup proyek, istilah dan definisi
A10: =IF(OR(D10<>"", B10<>""), ROW()-1, "") -> 9 | B10: Integrasi TCES TICS | D10: Membuat Dokumen TSD - Menambahkan Penulisan Terkait Document Overview | E10: DONE | F10: MEDIUM | G10: ENHANCEMENT | H10: TCES | J10: 1 | K10: 46248 | L10: 46252 | M10: 46252 | N10: haviz.indra@elistec.com | O10: syafix.said@elistec.com | S10: athallah.bariq@elistec.com | T10: mohammad.danang@elistec.com | W10: Menambahkan detail penulisan pada TSD (Technical Specification Document) terkait dengan document overview yang terdiri dari latar belakang, tujuan, ruang lingkup proyek, istilah dan definisi
A11: =IF(OR(D11<>"", B11<>""), ROW()-1, "") -> 10 | B11: Integrasi TCES TICS | D11: Membuat Dokumen TSD - Spesifikasi Basis Data - Melakuakan Pendefinisian Skema Tabel Pencatatan Log Integrasi | E11: DONE | F11: MEDIUM | G11: ENHANCEMENT | H11: TCES | J11: 1 | K11: 46252 | L11: 46252 | M11: 46252 | N11: haviz.indra@elistec.com | O11: syafix.said@elistec.com | S11: athallah.bariq@elistec.com | T11: mohammad.danang@elistec.com | W11: Menambahkan penulisan spesifikasi basis data terkait terkait dengan pendefinisan skema tabel pencatatan log integrasi yang mana mendokumentasikan seluruh tabel yang terlibat dalam alur integrasi dari TCES hingga TICS
A12: =IF(OR(D12<>"", B12<>""), ROW()-1, "") -> 11 | B12: Integrasi TCES TICS | D12: Membuat Dokumen TSD - Menambahkan penjelasan rinci dari arsitektur diagram | E12: DONE | F12: MEDIUM | G12: ENHANCEMENT | H12: TCES | J12: 1 | K12: 46252 | L12: 46254 | M12: 46254 | N12: haviz.indra@elistec.com | O12: syafix.said@elistec.com | S12: athallah.bariq@elistec.com | T12: mohammad.danang@elistec.com | W12: Menambahkan penulisan teknis rinici terkait dengan pendefinisan arsitektur diagram integrasi yang mana mendokumentasikan seluruh proses yang terlibat dalam alur integrasi dari TCES hingga TICS
A13: =IF(OR(D13<>"", B13<>""), ROW()-1, "") -> 12 | B13: Integrasi TCES TICS | D13: Membuat Dokumen TSD - Menambahkan detail penulisan terkait mekanisme enkripsi digital signature | E13: DONE | F13: MEDIUM | G13: ENHANCEMENT | H13: TCES | J13: 1 | K13: 46253 | L13: 46253 | M13: 46253 | N13: haviz.indra@elistec.com | O13: syafix.said@elistec.com | S13: athallah.bariq@elistec.com | T13: mohammad.danang@elistec.com | W13: Menambahkan penulisian rinci terkait mekanisme dari enkripsi digital signature, mulai dari penggunaan algoritma hingga cara kerja
A14: =IF(OR(D14<>"", B14<>""), ROW()-1, "") -> 13 | B14: Integrasi TCES TICS | D14: Membuat Dokumen TSD - Menambahkan detail penulisan terkait pemetaan data field integrasi | E14: DONE | F14: MEDIUM | G14: ENHANCEMENT | H14: TCES | J14: 1 | K14: 46253 | L14: 46254 | M14: 46254 | N14: haviz.indra@elistec.com | O14: syafix.said@elistec.com | S14: athallah.bariq@elistec.com | T14: mohammad.danang@elistec.com | W14: Menambahkan penulisian rinci terkait pemetaan data field integrasi per tabel databasenya (mulai dari tces_acceptence hingga ke tces_deduction)
